Workbook

Sheet Heinz-Kraft Merger
A1: Kraft Heinz Company | B1: In July of 2015 Heinz acquired all of the stock of Kraft in exchange for $42.855B worth of new Kraft Heinz stock.
A2: 2015 Acquisition of Kraft by Heinz | B2: In addition, the Kraft shareholders received a special cash dividend of $16.50 per share ($9.782B).
A3: In millions except per share data | B3: Total consideration was $52.6B or $88.79 per share representing a 31% control premium.
B5: Goodwill and intangible assets acquired were valued at $78.8B including $65.1B created via this transaction.
B7: The transaction was expected to result in 51%/49% ownership of Kraft Heinz in favor of the Heinz shareholders.
B8: Based on the valuation of Kraft, the new company (Kraft Heinz) was valued at $87.5 billion and Heinz was valued at $44.6B.
B10: Combined | C10: Heinz | E10: Acquisition of
A11: FYE Near 12/31: | B11: 2015 | C11: 2014 | D11: Change | E11: Kraft | F11: (From acquisition footnote)
A12: Assets
A13: Cash and Equivalents | B13: 4837 | C13: 2298 | D13: =+B13-C13 -> 2539
A14: Trade receivables | B14: 871 | C14: 690 | D14: =+B14-C14 -> 181
A15: Inventories | B15: 2618 | C15: 1185 | D15: =+B15-C15 -> 1433
A16: Other current assets | B16: =+B17-SUM(B13:B15) -> 1454 | C16: =+C17-SUM(C13:C15) -> 742 | D16: =+B16-C16 -> 712
A17: Total current assets | B17: 9780 | C17: 4915 | D17: =+B17-C17 -> 4865 | E17: =314+3423 -> 3737
A18: PP&E - Net | B18: 6524 | C18: 2365 | D18: =+B18-C18 -> 4159 | E18: 4193
A19: Goodwill | B19: 43051 | C19: 14959 | D19: =+B19-C19 -> 28092 | E19: 29029
A20: Other intangibles | B20: 62120 | C20: 13188 | D20: =+B20-C20 -> 48932 | E20: 49749
A21: Other assets | B21: 1498 | C21: 1144 | D21: =+B21-C21 -> 354 | E21: 214
A22: Total assets | B22: =SUM(B17:B21) -> 122973 | C22: =SUM(C17:C21) -> 36571 | D22: =SUM(D17:D21) -> 86402 | E22: =SUM(E17:E21) -> 86922
A23: Liabilities and Equity:
A24: Accounts payable | B24: 2844 | C24: 1651 | D24: =+B24-C24 -> 1193
A25: Other current liabilities | B25: =+B26-B24 -> 4088 | C25: =+C26-C24 -> 1441 | D25: =+D26-D24 -> 2647
A26: Total current liabilities | B26: 6932 | C26: 3092 | D26: =+B26-C26 -> 3840 | E26: 3026
A27: Long-term debt | B27: 25151 | C27: 13358 | D27: =+B27-C27 -> 11793 | E27: 9286
A28: Other liabilities | B28: =+B29-SUM(B26:B27) -> 24677 | C28: =+C29-SUM(C26:C27) -> 4465 | D28: =+B28-C28 -> 20212 | E28: =4734+17239 -> 21973
A29: Total liabilities and redeemable NCI) | B29: =56737+23 -> 56760 | C29: =20886+29 -> 20915 | D29: =+B29-C29 -> 35845 | E29: =SUM(E26:E28) -> 34285
A30: Preferred stock | B30: 8320 | C30: 8320 | D30: =+B30-C30 -> 0
A31: Common Equity | B31: 57893 | C31: 7336 | D31: =+B31-C31 -> 50557 | E31: =+E22-E29 -> 52637
A32: Total liabilities and equity | B32: =SUM(B29:B31) -> 122973 | C32: =SUM(C29:C31) -> 36571 | D32: =SUM(D29:D31) -> 86402 | E32: =SUM(E29:E31) -> 86922
B33: =+B32-B22 -> 0 | C33: =+C32-C22 -> 0 | D33: =+D32-D22 -> 0 | E33: =+E32-E22 -> 0
A34: Net Cash used in acquisition | E34: 9468
A35: Cash acquired | E35: 314
A36: Special cash dividend paid ($16.50 per share) | E36: =SUM(E34:E35) -> 9782 | F36: =+E36/16.5 -> 592.84848 | G36: Shares
A37: Equity Issued at fair value | E37: 42855 | F37: =+E37/F36 -> 72.286598 | G37: Price per share
A38: Total consideration | E38: =SUM(E36:E37) -> 52637 | F38: =+E38/F36 -> 88.786598 | G38: Including special dividend
F39: 61.33 | G39: Kraft stock price immediately prior to merger announcemt
F40: =(+F38-F39)/F38 -> 0.30924259 | G40: Control Premium to Kraft shareholders.
A42: Kraft Foods
A43: Last Balance Sheet compared to Valuation
A44: =+A3 -> In millions except per share data
B45: Kraft | C45: Acquisition of
B46: Alone | C46: Kraft
B47: 42004 | C47: (see above) | D47: Change
A48: Assets
A49: Total current assets | B49: 4791 | C49: =+E17 -> 3737 | D49: =+C49-B49 -> -1054
A50: PP&E - Net | B50: 4192 | C50: =+E18 -> 4193 | D50: =+C50-B50 -> 1
A51: Goodwill | B51: 11404 | C51: =+E19 -> 29029 | D51: =+C51-B51 -> 17625
A52: Other intangibles | B52: =2228+6 -> 2234 | C52: =+E20 -> 49749 | D52: =+C52-B52 -> 47515
A53: Other assets | B53: 326 | C53: =+E21 -> 214 | D53: =+C53-B53 -> -112
A54: Total assets | B54: =SUM(B49:B53) -> 22947 | C54: =+E22 -> 86922 | D54: =+C54-B54 -> 63975
A55: Liabilities and Equity:
A56: Total current liabilities | B56: 4773 | C56: 3026 | D56: =+C56-B56 -> -1747
A57: Long-term debt | B57: 8627 | C57: 9286 | D57: =+C57-B57 -> 659
A58: Other liabilities | B58: =340+3399+1443 -> 5182 | C58: =4734+17239 -> 21973 | D58: =+C58-B58 -> 16791
A59: Total liabilities and redeemable NCI) | B59: =SUM(B56:B58) -> 18582 | C59: =SUM(C56:C58) -> 34285 | D59: =+C59-B59 -> 15703
A60: Common Equity | B60: =+B54-B59 -> 4365 | C60: =+C54-C59 -> 52637 | D60: =+C60-B60 -> 48272
A61: Total liabilities and equity | B61: =+B60+B59 -> 22947 | C61: =SUM(C59:C60) -> 86922 | D61: =+C61-B61 -> 63975
A64: Kraft Heinz Inc
A65: Stock Price And Dividen History | B65: Closing Stock
A66: December 31: | B66: Price | C66: Dividends
A67: 2022 | B67: 40.71 | C67: 1.6
A68: 2021 | B68: 35.9 | C68: 1.6
A69: =+A68-1 -> 2020 | B69: 34.66 | C69: 1.6
A70: =+A69-1 -> 2019 | B70: 32.13 | C70: =0.4*4 -> 1.6 | D70: Big drop Nov 2018 - Feb 2019
A71: =+A70-1 -> 2018 | B71: 43.04 | C71: =0.625*4 -> 2.5 | D71: Bleeding started in Nov. 2017
A72: =+A71-1 -> 2017 | B72: 77.76 | C72: =(0.6*2)+(0.625*2) -> 2.45 | D72: High at 97.77 in February 2017
A73: =+A72-1 -> 2016 | B73: 87.32 | C73: =+C74+1.2 -> 2.35
A74: =+A73-1 -> 2015 | B74: 72.76 | C74: =0.575*2 -> 1.15
A75: July 2, 2015 | B75: =+F37 -> 72.286598

Sheet As Reported
A1: Kraft Heinz Company | B1: As reported | K1: =+B1 -> As reported | R1: =+B1 -> As reported
A2: Consolidated Balance Sheets | K2: Common Size on Total Assets | R2: Horizontal(Growth) Analysis
A3: in millions except per share data | F3: Late Filing | G3: Restated | P3: Restated | R3: 5 Year | S3: Annual | T3: 2021 to | U3: 2020 to | V3: 2019 to | W3: 2018 to | X3: 2017 to
A4: Fiscal year ended 12/31 | B4: 2022 | C4: 2021 | D4: 2020 | E4: 2019 | F4: 2018 | G4: 2017 | H4: 2016 | I4: 2015 | K4: 2022 | L4: 2021 | M4: 2020 | N4: 2019 | O4: 2018 | P4: 2017 | R4: CAGR | S4: Average | T4: 2022 | U4: 2021 | V4: 2020 | W4: 2019 | X4: 2018
A5: Assets:
A6: Cash and equivalents | B6: 1040 | C6: 3445 | D6: 3417 | E6: 2279 | F6: 1130 | G6: 1629 | K6: =+B6/B$18 -> 0.011490062 | L6: =+C6/C$18 -> 0.036886738 | M6: =+D6/D$18 -> 0.034228188 | N6: =+E6/E$18 -> 0.022464268 | O6: =+F6/F$18 -> 0.01092199 | P6: =+G6/G$18 -> 0.0135646 | R6: =RATE(5,0,-G6,B6) -> -0.085839502 | S6: =AVERAGE(T6:X6) -> 0.10398284 | T6: =(+B6-C6)/C6 -> -0.69811321 | U6: =(+C6-D6)/D6 -> 0.0081943225 | V6: =(+D6-E6)/E6 -> 0.49934182 | W6: =(+E6-F6)/F6 -> 1.0168142 | X6: =(+F6-G6)/G6 -> -0.3063229
A7: Trade receivables | B7: 2120 | C7: 1957 | D7: 2063 | E7: 1973 | F7: 2129 | G7: 921 | K7: =+B7/B$18 -> 0.02342205 | L7: =+C7/C$18 -> 0.020954237 | M7: =+D7/D$18 -> 0.020665131 | N7: =+E7/E$18 -> 0.019448004 | O7: =+F7/F$18 -> 0.020577802 | P7: =+G7/G$18 -> 0.0076691203 | R7: =RATE(5,0,-G7,B7) -> 0.18144973 | S7: =AVERAGE(T7:X7) -> 0.26317381 | T7: =(+B7-C7)/C7 -> 0.083290751 | U7: =(+C7-D7)/D7 -> -0.051381483 | V7: =(+D7-E7)/E7 -> 0.045615813 | W7: =(+E7-F7)/F7 -> -0.073273837 | X7: =(+F7-G7)/G7 -> 1.3116178
A8: Income tax receivable | B8: 0 | C8: 0 | D8: 0 | E8: 0 | F8: 152 | G8: 538 | K8: =+B8/B$18 -> 0 | L8: =+C8/C$18 -> 0 | M8: =+D8/D$18 -> 0 | N8: =+E8/E$18 -> 0 | O8: =+F8/F$18 -> 0.0014691526 | P8: =+G8/G$18 -> 0.0044798987 | R8: =RATE(5,0,-G8,B8) -> -0.99999941 | S8: =AVERAGE(T8:X8) -> -0.85873606 | W8: =(+E8-F8)/F8 -> -1 | X8: =(+F8-G8)/G8 -> -0.71747212
A9: Inventories | B9: 3651 | C9: 2729 | D9: 2554 | E9: 2721 | F9: 2667 | G9: 2760 | K9: =+B9/B$18 -> 0.040336747 | L9: =+C9/C$18 -> 0.029220293 | M9: =+D9/D$18 -> 0.025583492 | N9: =+E9/E$18 -> 0.026821094 | O9: =+F9/F$18 -> 0.025777829 | P9: =+G9/G$18 -> 0.02298238 | R9: =RATE(5,0,-G9,B9) -> 0.057549125 | S9: =AVERAGE(T9:X9) -> 0.066309997 | T9: =(+B9-C9)/C9 -> 0.33785269 | U9: =(+C9-D9)/D9 -> 0.068519969 | V9: =(+D9-E9)/E9 -> -0.061374495 | W9: =(+E9-F9)/F9 -> 0.020247469 | X9: =(+F9-G9)/G9 -> -0.033695652
A10: Prepaid expenses | B10: 240 | C10: 136 | D10: 351 | E10: 384 | F10: 400 | G10: 345 | K10: =+B10/B$18 -> 0.0026515528 | L10: =+C10/C$18 -> 0.0014561963 | M10: =+D10/D$18 -> 0.0035159772 | N10: =+E10/E$18 -> 0.0037851158 | O10: =+F10/F$18 -> 0.0038661911 | P10: =+G10/G$18 -> 0.0028727975 | R10: =RATE(5,0,-G10,B10) -> -0.070009677 | S10: =AVERAGE(T10:X10) -> 0.037130612 | T10: =(+B10-C10)/C10 -> 0.76470588 | U10: =(+C10-D10)/D10 -> -0.61253561 | V10: =(+D10-E10)/E10 -> -0.0859375 | W10: =(+E10-F10)/F10 -> -0.04 | X10: =(+F10-G10)/G10 -> 0.15942029
A11: Other current assets | B11: 842 | C11: 716 | D11: 574 | E11: 618 | F11: 1221 | G11: 655 | K11: =+B11/B$18 -> 0.0093025311 | L11: =+C11/C$18 -> 0.0076664454 | M11: =+D11/D$18 -> 0.0057497746 | N11: =+E11/E$18 -> 0.0060916708 | O11: =+F11/F$18 -> 0.011801548 | P11: =+G11/G$18 -> 0.0054541518 | R11: =RATE(5,0,-G11,B11) -> 0.051511818 | S11: =AVERAGE(T11:X11) -> 0.14448633 | T11: =(+B11-C11)/C11 -> 0.17597765 | U11: =(+C11-D11)/D11 -> 0.24738676 | V11: =(+D11-E11)/E11 -> -0.071197411 | W11: =(+E11-F11)/F11 -> -0.49385749 | X11: =(+F11-G11)/G11 -> 0.86412214
A12: Assets held for sale | B12: 4 | C12: 11 | D12: 1863 | E12: 122 | F12: 1376 | G12: 353 | K12: =+B12/B$18 -> 4.4192547e-05 | L12: =+C12/C$18 -> 0.00011778059 | M12: =+D12/D$18 -> 0.018661725 | N12: =+E12/E$18 -> 0.0012025628 | O12: =+F12/F$18 -> 0.013299697 | P12: =+G12/G$18 -> 0.0029394131 | R12: =RATE(5,0,-G12,B12) -> -0.59181498 | S12: =AVERAGE(T12:X12) -> 2.9253425 | T12: =(+B12-C12)/C12 -> -0.63636364 | U12: =(+C12-D12)/D12 -> -0.99409554 | V12: =(+D12-E12)/E12 -> 14.270492 | W12: =(+E12-F12)/F12 -> -0.91133721 | X12: =(+F12-G12)/G12 -> 2.898017
A13: Total current assets | B13: =SUM(B6:B12) -> 7897 | C13: =SUM(C6:C12) -> 8994 | D13: =SUM(D6:D12) -> 10822 | E13: =SUM(E6:E12) -> 8097 | F13: =SUM(F6:F12) -> 9075 | G13: =SUM(G6:G12) -> 7201 | H13: 8753 | I13: 9780 | K13: =+B13/B$18 -> 0.087247136 | L13: =+C13/C$18 -> 0.09630169 | M13: =+D13/D$18 -> 0.10840429 | N13: =+E13/E$18 -> 0.079812716 | O13: =+F13/F$18 -> 0.087714211 | P13: =+G13/G$18 -> 0.059962362 | R13: =RATE(5,0,-G13,B13) -> 0.018623908 | S13: =AVERAGE(T13:X13) -> 0.039626412 | T13: =(+B13-C13)/C13 -> -0.1219702 | U13: =(+C13-D13)/D13 -> -0.16891517 | V13: =(+D13-E13)/E13 -> 0.3365444 | W13: =(+E13-F13)/F13 -> -0.1077686 | X13: =(+F13-G13)/G13 -> 0.26024163
A14: Property, plant & equipment - net | B14: 6740 | C14: 6806 | D14: 6876 | E14: 7055 | F14: 7078 | G14: 7061 | H14: 6688 | I14: 6524 | K14: =+B14/B$18 -> 0.074464442 | L14: =+C14/C$18 -> 0.07287406 | M14: =+D14/D$18 -> 0.068877091 | N14: =+E14/E$18 -> 0.069541646 | O14: =+F14/F$18 -> 0.068412252 | P14: =+G14/G$18 -> 0.058796589 | R14: =RATE(5,0,-G14,B14) -> -0.0092621911 | S14: =AVERAGE(T14:X14) -> -0.0092183309 | T14: =(+B14-C14)/C14 -> -0.0096973259 | U14: =(+C14-D14)/D14 -> -0.010180337 | V14: =(+D14-E14)/E14 -> -0.025372077 | W14: =(+E14-F14)/F14 -> -0.0032495055 | X14: =(+F14-G14)/G14 -> 0.002407591
A15: Goodwill | B15: 30833 | C15: 31296 | D15: 33089 | E15: 35546 | F15: 36503 | G15: 44825 | H15: 44125 | I15: 43051 | K15: =+B15/B$18 -> 0.3406472 | L15: =+C15/C$18 -> 0.33509647 | M15: =+D15/D$18 -> 0.33145347 | N15: =+E15/E$18 -> 0.3503795 | O15: =+F15/F$18 -> 0.35281894 | P15: =+G15/G$18 -> 0.3732555 | R15: =RATE(5,0,-G15,B15) -> -0.072104439 | S15: =AVERAGE(T15:X15) -> -0.069995093 | T15: =(+B15-C15)/C15 -> -0.014794223 | U15: =(+C15-D15)/D15 -> -0.054187192 | V15: =(+D15-E15)/E15 -> -0.069121701 | W15: =(+E15-F15)/F15 -> -0.026217023 | X15: =(+F15-G15)/G15 -> -0.18565533
A16: Intangible assets | B16: 42649 | C16: 43542 | D16: 46667 | E16: 48652 | F16: 49468 | G16: 59432 | H16: 59297 | I16: 62120 | K16: =+B16/B$18 -> 0.47119198 | L16: =+C16/C$18 -> 0.46621839 | M16: =+D16/D$18 -> 0.46746469 | N16: =+E16/E$18 -> 0.47956629 | O16: =+F16/F$18 -> 0.47813186 | P16: =+G16/G$18 -> 0.49488725 | R16: =RATE(5,0,-G16,B16) -> -0.064211505 | S16: =AVERAGE(T16:X16) -> -0.062484402 | T16: =(+B16-C16)/C16 -> -0.020508934 | U16: =(+C16-D16)/D16 -> -0.066963807 | V16: =(+D16-E16)/E16 -> -0.040799967 | W16: =(+E16-F16)/F16 -> -0.016495512 | X16: =(+F16-G16)/G16 -> -0.16765379
A17: Other assets | B17: 2394 | C17: 2756 | D17: 2376 | E17: 2100 | F17: 1337 | G17: 1573 | H17: 1617 | I17: 1498 | K17: =+B17/B$18 -> 0.026449239 | L17: =+C17/C$18 -> 0.02950939 | M17: =+D17/D$18 -> 0.023800461 | N17: =+E17/E$18 -> 0.020699852 | O17: =+F17/F$18 -> 0.012922744 | P17: =+G17/G$18 -> 0.013098291 | R17: =RATE(5,0,-G17,B17) -> 0.087624757 | S17: =AVERAGE(T17:X17) -> 0.11613206 | T17: =(+B17-C17)/C17 -> -0.13134978 | U17: =(+C17-D17)/D17 -> 0.15993266 | V17: =(+D17-E17)/E17 -> 0.13142857 | W17: =(+E17-F17)/F17 -> 0.57068063 | X17: =(+F17-G17)/G17 -> -0.15003179
A18: Total Assets | B18: =SUM(B13:B17) -> 90513 | C18: =SUM(C13:C17) -> 93394 | D18: =SUM(D13:D17) -> 99830 | E18: =SUM(E13:E17) -> 101450 | F18: =SUM(F13:F17) -> 103461 | G18: =SUM(G13:G17) -> 120092 | H18: =SUM(H13:H17) -> 120480 | I18: =SUM(I13:I17) -> 122973 | K18: =+B18/B$18 -> 1 | L18: =+C18/C$18 -> 1 | M18: =+D18/D$18 -> 1 | N18: =+E18/E$18 -> 1 | O18: =+F18/F$18 -> 1 | P18: =+G18/G$18 -> 1 | R18: =RATE(5,0,-G18,B18) -> -0.054983533 | S18: =AVERAGE(T18:X18) -> -0.053841726 | T18: =(+B18-C18)/C18 -> -0.030847806 | U18: =(+C18-D18)/D18 -> -0.064469598 | V18: =(+D18-E18)/E18 -> -0.015968457 | W18: =(+E18-F18)/F18 -> -0.019437276 | X18: =(+F18-G18)/G18 -> -0.13848549
A19: Liabilities and Equity
A20: Short-term Debt | B20: 6 | C20: 14 | D20: 6 | E20: 6 | F20: 21 | G20: 462 | K20: =+B20/B$18 -> 6.628882e-05 | L20: =+C20/C$18 -> 0.00014990256 | M20: =+D20/D$18 -> 6.0102174e-05 | N20: =+E20/E$18 -> 5.9142435e-05 | O20: =+F20/F$18 -> 0.00020297503 | P20: =+G20/G$18 -> 0.0038470506 | R20: =RATE(5,0,-G20,B20) -> -0.58052908 | S20: =AVERAGE(T20:X20) -> -0.18138528 | T20: =(+B20-C20)/C20 -> -0.57142857 | U20: =(+C20-D20)/D20 -> 1.3333333 | V20: =(+D20-E20)/E20 -> 0 | W20: =(+E20-F20)/F20 -> -0.71428571 | X20: =(+F20-G20)/G20 -> -0.95454545
A21: Current portion of LT Debt | B21: 831 | C21: 740 | D21: 230 | E21: 1022 | F21: 377 | G21: 2733 | K21: =+B21/B$18 -> 0.0091810016 | L21: =+C21/C$18 -> 0.0079234212 | M21: =+D21/D$18 -> 0.0023039167 | N21: =+E21/E$18 -> 0.010073928 | O21: =+F21/F$18 -> 0.0036438851 | P21: =+G21/G$18 -> 0.022757553 | R21: =RATE(5,0,-G21,B21) -> -0.21188013 | S21: =AVERAGE(T21:X21) -> 0.48284644 | T21: =(+B21-C21)/C21 -> 0.12297297 | U21: =(+C21-D21)/D21 -> 2.2173913 | V21: =(+D21-E21)/E21 -> -0.77495108 | W21: =(+E21-F21)/F21 -> 1.7108753 | X21: =(+F21-G21)/G21 -> -0.86205635
A22: Trade payables | B22: 4848 | C22: 4753 | D22: 4304 | E22: 4003 | F22: 4153 | G22: 4362 | K22: =+B22/B$18 -> 0.053561367 | L22: =+C22/C$18 -> 0.05089192 | M22: =+D22/D$18 -> 0.043113293 | N22: =+E22/E$18 -> 0.039457861 | O22: =+F22/F$18 -> 0.040140729 | P22: =+G22/G$18 -> 0.036322153 | R22: =RATE(5,0,-G22,B22) -> 0.021351874 | S22: =AVERAGE(T22:X22) -> 0.023094055 | T22: =(+B22-C22)/C22 -> 0.019987376 | U22: =(+C22-D22)/D22 -> 0.10432156 | V22: =(+D22-E22)/E22 -> 0.075193605 | W22: =(+E22-F22)/F22 -> -0.036118469 | X22: =(+F22-G22)/G22 -> -0.047913801
A23: Accrued marketing | B23: 749 | C23: 804 | D23: 946 | E23: 647 | F23: 722 | G23: 689 | K23: =+B23/B$18 -> 0.0082750544 | L23: =+C23/C$18 -> 0.0086086901 | M23: =+D23/D$18 -> 0.0094761094 | N23: =+E23/E$18 -> 0.0063775259 | O23: =+F23/F$18 -> 0.006978475 | P23: =+G23/G$18 -> 0.0057372681 | R23: =RATE(5,0,-G23,B23) -> 0.016839759 | S23: =AVERAGE(T23:X23) -> 0.037527327 | T23: =(+B23-C23)/C23 -> -0.06840796 | U23: =(+C23-D23)/D23 -> -0.15010571 | V23: =(+D23-E23)/E23 -> 0.46213292 | W23: =(+E23-F23)/F23 -> -0.10387812 | X23: =(+F23-G23)/G23 -> 0.047895501
A24: Interest payable | B24: 264 | C24: 268 | D24: 358 | E24: 384 | F24: 408 | G24: 419 | K24: =+B24/B$18 -> 0.0029167081 | L24: =+C24/C$18 -> 0.0028695634 | M24: =+D24/D$18 -> 0.0035860964 | N24: =+E24/E$18 -> 0.0037851158 | O24: =+F24/F$18 -> 0.0039435149 | P24: =+G24/G$18 -> 0.0034889918 | R24: =RATE(5,0,-G24,B24) -> -0.088245363 | S24: =AVERAGE(T24:X24) -> -0.083821373 | T24: =(+B24-C24)/C24 -> -0.014925373 | U24: =(+C24-D24)/D24 -> -0.25139665 | V24: =(+D24-E24)/E24 -> -0.067708333 | W24: =(+E24-F24)/F24 -> -0.058823529 | X24: =(+F24-G24)/G24 -> -0.026252983
A25: Income tax payable | B25: 136 | C25: 541 | D25: 0 | E25: 0 | F25: 0 | G25: 0 | K25: =+B25/B$18 -> 0.0015025466 | L25: =+C25/C$18 -> 0.0057926633 | M25: =+D25/D$18 -> 0 | N25: =+E25/E$18 -> 0 | O25: =+F25/F$18 -> 0 | P25: =+G25/G$18 -> 0 | S25: =AVERAGE(T25:X25) -> -0.74861368 | T25: =(+B25-C25)/C25 -> -0.74861368
A26: Liabilities held for sale | B26: 0 | C26: 0 | D26: 17 | E26: 9 | F26: 55 | G26: 0 | K26: =+B26/B$18 -> 0 | L26: =+C26/C$18 -> 0 | M26: =+D26/D$18 -> 0.00017028949 | N26: =+E26/E$18 -> 8.8713652e-05 | O26: =+F26/F$18 -> 0.00053160128 | P26: =+G26/G$18 -> 0 | S26: =AVERAGE(T26:X26) -> -0.31582492 | U26: =(+C26-D26)/D26 -> -1 | V26: =(+D26-E26)/E26 -> 0.88888889 | W26: =(+E26-F26)/F26 -> -0.83636364
A27: Other current liabilities | B27: 2194 | C27: 1944 | D27: 2200 | E27: 1804 | F27: 1767 | G27: 1489 | K27: =+B27/B$18 -> 0.024239612 | L27: =+C27/C$18 -> 0.020815042 | M27: =+D27/D$18 -> 0.022037464 | N27: =+E27/E$18 -> 0.017782159 | O27: =+F27/F$18 -> 0.017078899 | P27: =+G27/G$18 -> 0.012398828 | R27: =RATE(5,0,-G27,B27) -> 0.080608514 | S27: =AVERAGE(T27:X27) -> 0.087878262 | T27: =(+B27-C27)/C27 -> 0.12860082 | U27: =(+C27-D27)/D27 -> -0.11636364 | V27: =(+D27-E27)/E27 -> 0.2195122 | W27: =(+E27-F27)/F27 -> 0.020939445 | X27: =(+F27-G27)/G27 -> 0.18670248
A28: Total current liabilities | B28: =SUM(B20:B27) -> 9028 | C28: =SUM(C20:C27) -> 9064 | D28: =SUM(D20:D27) -> 8061 | E28: =SUM(E20:E27) -> 7875 | F28: =SUM(F20:F27) -> 7503 | G28: =SUM(G20:G27) -> 10154 | H28: 9501 | I28: 6932 | K28: =+B28/B$18 -> 0.099742578 | L28: =+C28/C$18 -> 0.097051202 | M28: =+D28/D$18 -> 0.08074727 | N28: =+E28/E$18 -> 0.077624446 | O28: =+F28/F$18 -> 0.07252008 | P28: =+G28/G$18 -> 0.084551844 | R28: =RATE(5,0,-G28,B28) -> -0.023233226 | S28: =AVERAGE(T28:X28) -> -0.013485134 | T28: =(+B28-C28)/C28 -> -0.0039717564 | U28: =(+C28-D28)/D28 -> 0.12442625 | V28: =(+D28-E28)/E28 -> 0.023619048 | W28: =(+E28-F28)/F28 -> 0.049580168 | X28: =(+F28-G28)/G28 -> -0.26107938
A29: Long-term debt | B29: 19233 | C29: 21061 | D29: 28070 | E29: 28216 | F29: 30770 | G29: 28308 | H29: 29713 | I29: 25151 | K29: =+B29/B$18 -> 0.21248881 | L29: =+C29/C$18 -> 0.22550699 | M29: =+D29/D$18 -> 0.281178 | N29: =+E29/E$18 -> 0.27812716 | O29: =+F29/F$18 -> 0.29740675 | P29: =+G29/G$18 -> 0.23571928 | R29: =RATE(5,0,-G29,B29) -> -0.074391 | S29: =AVERAGE(T29:X29) -> -0.06753962 | T29: =(+B29-C29)/C29 -> -0.086795499 | U29: =(+C29-D29)/D29 -> -0.24969719 | V29: =(+D29-E29)/E29 -> -0.0051743692 | W29: =(+E29-F29)/F29 -> -0.083002925 | X29: =(+F29-G29)/G29 -> 0.086971881
A30: Deferred income taxes | B30: 10152 | C30: 10536 | D30: 11462 | E30: 11878 | F30: 12202 | G30: 14039 | H30: 20848 | I30: 21497 | K30: =+B30/B$18 -> 0.11216068 | L30: =+C30/C$18 -> 0.11281239 | M30: =+D30/D$18 -> 0.11481519 | N30: =+E30/E$18 -> 0.11708231 | O30: =+F30/F$18 -> 0.11793816 | P30: =+G30/G$18 -> 0.11690204 | R30: =RATE(5,0,-G30,B30) -> -0.062776678 | S30: =AVERAGE(T30:X30) -> -0.061932139 | T30: =(+B30-C30)/C30 -> -0.036446469 | U30: =(+C30-D30)/D30 -> -0.080788693 | V30: =(+D30-E30)/E30 -> -0.035022731 | W30: =(+E30-F30)/F30 -> -0.026553024 | X30: =(+F30-G30)/G30 -> -0.13084978
A31: Accrued PRB costs | B31: 144 | C31: 205 | D31: 243 | E31: 273 | F31: 306 | G31: 427 | H31: 2038 | I31: 2405 | K31: =+B31/B$18 -> 0.0015909317 | L31: =+C31/C$18 -> 0.0021950018 | M31: =+D31/D$18 -> 0.002434138 | N31: =+E31/E$18 -> 0.0026909808 | O31: =+F31/F$18 -> 0.0029576362 | P31: =+G31/G$18 -> 0.0035556074 | R31: =RATE(5,0,-G31,B31) -> -0.19538723 | S31: =AVERAGE(T31:X31) -> -0.19100904 | T31: =(+B31-C31)/C31 -> -0.29756098 | U31: =(+C31-D31)/D31 -> -0.1563786 | V31: =(+D31-E31)/E31 -> -0.10989011 | W31: =(+E31-F31)/F31 -> -0.10784314 | X31: =(+F31-G31)/G31 -> -0.28337237
A32: LT deferred income | B32: 1477 | C32: 1534 | D32: 0 | E32: 0 | F32: 0 | G32: 0 | H32: 0 | I32: 0 | K32: =+B32/B$18 -> 0.016318098 | L32: =+C32/C$18 -> 0.016425038 | M32: =+D32/D$18 -> 0 | N32: =+E32/E$18 -> 0 | O32: =+F32/F$18 -> 0 | P32: =+G32/G$18 -> 0 | S32: =AVERAGE(T32:X32) -> -0.037157757 | T32: =(+B32-C32)/C32 -> -0.037157757
A33: Other non-current liabilities | B33: 1609 | C33: 1542 | D33: 1751 | E33: 1459 | F33: 902 | G33: 1088 | H33: 806 | I33: 752 | K33: =+B33/B$18 -> 0.017776452 | L33: =+C33/C$18 -> 0.016510697 | M33: =+D33/D$18 -> 0.017539818 | N33: =+E33/E$18 -> 0.014381469 | O33: =+F33/F$18 -> 0.008718261 | P33: =+G33/G$18 -> 0.0090597209 | R33: =RATE(5,0,-G33,B33) -> 0.081397671 | S33: =AVERAGE(T33:X33) -> 0.11415751 | T33: =(+B33-C33)/C33 -> 0.043450065 | U33: =(+C33-D33)/D33 -> -0.11936037 | V33: =(+D33-E33)/E33 -> 0.20013708 | W33: =(+E33-F33)/F33 -> 0.61751663 | X33: =(+F33-G33)/G33 -> -0.17095588
A34: Total liabilities | B34: =SUM(B28:B33) -> 41643 | C34: =SUM(C28:C33) -> 43942 | D34: =SUM(D28:D33) -> 49587 | E34: =SUM(E28:E33) -> 49701 | F34: =SUM(F28:F33) -> 51683 | G34: =SUM(G28:G33) -> 54016 | H34: =SUM(H28:H33) -> 62906 | I34: =SUM(I28:I33) -> 56737 | K34: =+B34/B$18 -> 0.46007756 | L34: =+C34/C$18 -> 0.47050132 | M34: =+D34/D$18 -> 0.49671441 | N34: =+E34/E$18 -> 0.48990636 | O34: =+F34/F$18 -> 0.49954089 | P34: =+G34/G$18 -> 0.4497885 | R34: =RATE(5,0,-G34,B34) -> -0.050699045 | S34: =AVERAGE(T34:X34) -> -0.049998615 | T34: =(+B34-C34)/C34 -> -0.052318966 | U34: =(+C34-D34)/D34 -> -0.11384032 | V34: =(+D34-E34)/E34 -> -0.0022937164 | W34: =(+E34-F34)/F34 -> -0.038349167 | X34: =(+F34-G34)/G34 -> -0.043190906
A35: Redeemable Non-controlling interest | B35: 40 | C35: 4 | D35: 0 | E35: 0 | F35: 3 | G35: 6 | H35: 0 | I35: 23 | K35: =+B35/B$18 -> 0.00044192547 | L35: =+C35/C$18 -> 4.2829304e-05 | M35: =+D35/D$18 -> 0 | N35: =+E35/E$18 -> 0 | O35: =+F35/F$18 -> 2.8996433e-05 | P35: =+G35/G$18 -> 4.9961696e-05 | R35: =RATE(5,0,-G35,B35) -> 0.46144255 | S35: =AVERAGE(T35:X35) -> 2.5 | T35: =(+B35-C35)/C35 -> 9 | W35: =(+E35-F35)/F35 -> -1 | X35: =(+F35-G35)/G35 -> -0.5
A36: Preferred stock - cumulative compounding | B36: 0 | C36: 0 | D36: 0 | E36: 0 | F36: 0 | G36: 0 | H36: 0 | I36: 8320 | K36: =+B36/B$18 -> 0 | L36: =+C36/C$18 -> 0 | M36: =+D36/D$18 -> 0 | N36: =+E36/E$18 -> 0 | O36: =+F36/F$18 -> 0 | P36: =+G36/G$18 -> 0
A37: Common stock | B37: 12 | C37: 12 | D37: 12 | E37: 12 | F37: 12 | G37: 12 | H37: 12 | I37: 12 | K37: =+B37/B$18 -> 0.00013257764 | L37: =+C37/C$18 -> 0.00012848791 | M37: =+D37/D$18 -> 0.00012020435 | N37: =+E37/E$18 -> 0.00011828487 | O37: =+F37/F$18 -> 0.00011598573 | P37: =+G37/G$18 -> 9.9923392e-05 | R37: =RATE(5,0,-G37,B37) -> 1.1505115e-16 | S37: =AVERAGE(T37:X37) -> 0 | T37: =(+B37-C37)/C37 -> 0 | U37: =(+C37-D37)/D37 -> 0 | V37: =(+D37-E37)/E37 -> 0 | W37: =(+E37-F37)/F37 -> 0 | X37: =(+F37-G37)/G37 -> 0
A38: Additional PIC | B38: 51834 | C38: 53379 | D38: 55096 | E38: 56828 | F38: 58723 | G38: 58634 | H38: 58593 | I38: 58375 | K38: =+B38/B$18 -> 0.57266912 | L38: =+C38/C$18 -> 0.57154635 | M38: =+D38/D$18 -> 0.55189823 | N38: =+E38/E$18 -> 0.56015771 | O38: =+F38/F$18 -> 0.56758585 | P38: =+G38/G$18 -> 0.48824235 | R38: =RATE(5,0,-G38,B38) -> -0.024352266 | S38: =AVERAGE(T38:X38) -> -0.024267589 | T38: =(+B38-C38)/C38 -> -0.028943967 | U38: =(+C38-D38)/D38 -> -0.031163787 | V38: =(+D38-E38)/E38 -> -0.030477933 | W38: =(+E38-F38)/F38 -> -0.03227015 | X38: =(+F38-G38)/G38 -> 0.0015178906
A39: Retained earnings (deficit) | B39: 489 | C39: -1682 | D39: -2694 | E39: -3060 | F39: -4853 | G39: 8495 | H39: 588 | I39: 0 | K39: =+B39/B$18 -> 0.0054025389 | L39: =+C39/C$18 -> -0.018009722 | M39: =+D39/D$18 -> -0.026985876 | N39: =+E39/E$18 -> -0.030162642 | O39: =+F39/F$18 -> -0.046906564 | P39: =+G39/G$18 -> 0.070737435 | R39: =RATE(5,0,-G39,B39) -> -0.43502518 | S39: =AVERAGE(T39:X39) -> -0.74534443 | T39: =(+B39-C39)/C39 -> -1.2907253 | U39: =(+C39-D39)/D39 -> -0.37564959 | V39: =(+D39-E39)/E39 -> -0.11960784 | W39: =(+E39-F39)/F39 -> -0.36946219 | X39: =(+F39-G39)/G39 -> -1.5712772
A40: Accum. OCI | B40: -2810 | C40: -1824 | D40: -1967 | E40: -1886 | F40: -1943 | G40: -1054 | H40: -1628 | I40: -671 | K40: =+B40/B$18 -> -0.031045264 | L40: =+C40/C$18 -> -0.019530163 | M40: =+D40/D$18 -> -0.019703496 | N40: =+E40/E$18 -> -0.018590439 | O40: =+F40/F$18 -> -0.018780023 | P40: =+G40/G$18 -> -0.0087766046 | R40: =RATE(5,0,-G40,B40) -> 0.21667096 | S40: =AVERAGE(T40:X40) -> 0.26498722 | T40: =(+B40-C40)/C40 -> 0.54057018 | U40: =(+C40-D40)/D40 -> -0.072699542 | V40: =(+D40-E40)/E40 -> 0.042948038 | W40: =(+E40-F40)/F40 -> -0.029336078 | X40: =(+F40-G40)/G40 -> 0.84345351
A41: Treasury stock | B41: -847 | C41: -587 | D41: -344 | E41: -271 | F41: -282 | G41: -224 | H41: -207 | I41: -31 | K41: =+B41/B$18 -> -0.0093577718 | L41: =+C41/C$18 -> -0.0062852003 | M41: =+D41/D$18 -> -0.003445858 | N41: =+E41/E$18 -> -0.0026712666 | O41: =+F41/F$18 -> -0.0027256647 | P41: =+G41/G$18 -> -0.0018652367 | R41: =RATE(5,0,-G41,B41) -> 0.30474932 | S41: =AVERAGE(T41:X41) -> 0.32772394 | T41: =(+B41-C41)/C41 -> 0.44293015 | U41: =(+C41-D41)/D41 -> 0.70639535 | V41: =(+D41-E41)/E41 -> 0.26937269 | W41: =(+E41-F41)/F41 -> -0.039007092 | X41: =(+F41-G41)/G41 -> 0.25892857
A42: Noncontrolling interest | B42: 152 | C42: 150 | D42: 140 | E42: 126 | F42: 118 | G42: 207 | H42: 216 | I42: 208 | K42: =+B42/B$18 -> 0.0016793168 | L42: =+C42/C$18 -> 0.0016060989 | M42: =+D42/D$18 -> 0.0014023841 | N42: =+E42/E$18 -> 0.0012419911 | O42: =+F42/F$18 -> 0.0011405264 | P42: =+G42/G$18 -> 0.0017236785 | R42: =RATE(5,0,-G42,B42) -> -0.05989871 | S42: =AVERAGE(T42:X42) -> -0.033256413 | T42: =(+B42-C42)/C42 -> 0.013333333 | U42: =(+C42-D42)/D42 -> 0.071428571 | V42: =(+D42-E42)/E42 -> 0.11111111 | W42: =(+E42-F42)/F42 -> 0.06779661 | X42: =(+F42-G42)/G42 -> -0.42995169
A43: Total Equity | B43: =SUM(B37:B42) -> 48830 | C43: =SUM(C37:C42) -> 49448 | D43: =SUM(D37:D42) -> 50243 | E43: =SUM(E37:E42) -> 51749 | F43: =SUM(F37:F42) -> 51775 | G43: =SUM(G37:G42) -> 66070 | H43: =SUM(H37:H42) -> 57574 | I43: =SUM(I37:I42) -> 57893 | K43: =+B43/B$18 -> 0.53948052 | L43: =+C43/C$18 -> 0.52945585 | M43: =+D43/D$18 -> 0.50328559 | N43: =+E43/E$18 -> 0.51009364 | O43: =+F43/F$18 -> 0.50043011 | P43: =+G43/G$18 -> 0.55016154 | R43: =RATE(5,0,-G43,B43) -> -0.05868174 | S43: =AVERAGE(T43:X43) -> -0.054857339 | T43: =(+B43-C43)/C43 -> -0.012497978 | U43: =(+C43-D43)/D43 -> -0.0158231 | V43: =(+D43-E43)/E43 -> -0.029102012 | W43: =(+E43-F43)/F43 -> -0.00050217286 | X43: =(+F43-G43)/G43 -> -0.21636143
A44: Total Liabilities and Equity | B44: =+B43+B35+B34 -> 90513 | C44: =+C43+C35+C34 -> 93394 | D44: =+D43+D35+D34 -> 99830 | E44: =+E43+E35+E34 -> 101450 | F44: =+F43+F35+F34 -> 103461 | G44: =+G43+G35+G34 -> 120092 | H44: =+H43+H35+H34 -> 120480 | I44: =+I43+I35+I34+I36 -> 122973 | K44: =+B44/B$18 -> 1 | L44: =+C44/C$18 -> 1 | M44: =+D44/D$18 -> 1 | N44: =+E44/E$18 -> 1 | O44: =+F44/F$18 -> 1 | P44: =+G44/G$18 -> 1 | R44: =RATE(5,0,-G44,B44) -> -0.054983533 | S44: =AVERAGE(T44:X44) -> -0.053841726 | T44: =(+B44-C44)/C44 -> -0.030847806 | U44: =(+C44-D44)/D44 -> -0.064469598 | V44: =(+D44-E44)/E44 -> -0.015968457 | W44: =(+E44-F44)/F44 -> -0.019437276 | X44: =(+F44-G44)/G44 -> -0.13848549
B45: =+B44-B18 -> 0 | C45: =+C44-C18 -> 0 | D45: =+D44-D18 -> 0 | E45: =+E44-E18 -> 0 | F45: =+F44-F18 -> 0 | G45: =+G44-G18 -> 0 | H45: =+H44-H18 -> 0 | I45: =+I44-I18 -> 0
A46: Shares issued | B46: 1243 | C46: 1235 | D46: 1228 | E46: 1224 | F46: 1224 | G46: 1221 | H46: 1218.9471 | I46: 1216.4757
A47: Treasury Shares | B47: -18 | C47: -11 | D47: -5 | E47: -3 | F47: -4 | G47: -2 | H47: =+H48-H46 -> -2.471348 | I47: =+I48-I46 -> -2.496988
A48: Shares Outstanding | B48: =+B46+B47 -> 1225 | C48: =+C46+C47 -> 1224 | D48: =+D46+D47 -> 1223 | E48: =+E46+E47 -> 1221 | F48: =+F46+F47 -> 1220 | G48: =+G46+G47 -> 1219 | H48: 1216.4757 | I48: 1213.9788
A52: =+A1 -> Kraft Heinz Company | B52: =+B1 -> As reported | K52: =+B52 -> As reported | R52: =+B52 -> As reported
A53: Consolidated Income Statements | K53: Common Size on Net Sales | R53: Horizontal(Growth) Analysis
A54: =+A3 -> in millions except per share data | F54: Late Filing | G54: Restated | I54: Partial | P54: Restated | R54: 5 Year | S54: Annual | T54: 2021 to | U54: 2020 to | V54: 2019 to | W54: 2018 to | X54: 2017 to
A55: =+A4 -> Fiscal year ended 12/31 | B55: 2022 | C55: 2021 | D55: 2020 | E55: 2019 | F55: 2018 | G55: 2017 | H55: 2016 | I55: 2015 | K55: 2022 | L55: 2021 | M55: 2020 | N55: 2019 | O55: 2018 | P55: 2017 | R55: CAGR | S55: Average | T55: 2022 | U55: 2021 | V55: 2020 | W55: 2019 | X55: 2018
A56: Net sales | B56: 26485 | C56: 26042 | D56: 26185 | E56: 24977 | F56: 26268 | G56: 26076 | H56: 26487 | I56: 18338 | K56: =+B56/B$56 -> 1 | L56: =+C56/C$56 -> 1 | M56: =+D56/D$56 -> 1 | N56: =+E56/E$56 -> 1 | O56: =+F56/F$56 -> 1 | P56: =+G56/G$56 -> 1 | R56: =RATE(5,0,-G56,B56) -> 0.0031174861 | S56: =AVERAGE(T56:X56) -> 0.0036260354 | T56: =(+B56-C56)/C56 -> 0.017010982 | U56: =(+C56-D56)/D56 -> -0.0054611419 | V56: =(+D56-E56)/E56 -> 0.048364495 | W56: =(+E56-F56)/F56 -> -0.049147251 | X56: =(+F56-G56)/G56 -> 0.0073630925
A57: Cost of goods sold | B57: 18363 | C57: 17360 | D57: 17008 | E57: 16830 | F57: 17347 | G57: 17043 | H57: 16901 | I57: 12577 | K57: =+B57/B$56 -> 0.69333585 | L57: =+C57/C$56 -> 0.66661547 | M57: =+D57/D$56 -> 0.64953217 | N57: =+E57/E$56 -> 0.67381991 | O57: =+F57/F$56 -> 0.66038526 | P57: =+G57/G$56 -> 0.65358951 | R57: =RATE(5,0,-G57,B57) -> 0.015031495 | S57: =AVERAGE(T57:X57) -> 0.015416561 | T57: =(+B57-C57)/C57 -> 0.057776498 | U57: =(+C57-D57)/D57 -> 0.020696143 | V57: =(+D57-E57)/E57 -> 0.010576352 | W57: =(+E57-F57)/F57 -> -0.029803424 | X57: =(+F57-G57)/G57 -> 0.017837235
A58: Gross profit | B58: =+B56-B57 -> 8122 | C58: =+C56-C57 -> 8682 | D58: =+D56-D57 -> 9177 | E58: =+E56-E57 -> 8147 | F58: =+F56-F57 -> 8921 | G58: =+G56-G57 -> 9033 | H58: =+H56-H57 -> 9586 | I58: =+I56-I57 -> 5761 | K58: =+B58/B$56 -> 0.30666415 | L58: =+C58/C$56 -> 0.33338453 | M58: =+D58/D$56 -> 0.35046783 | N58: =+E58/E$56 -> 0.32618009 | O58: =+F58/F$56 -> 0.33961474 | P58: =+G58/G$56 -> 0.34641049 | R58: =RATE(5,0,-G58,B58) -> -0.021037187 | S58: =AVERAGE(T58:X58) -> -0.018234823 | T58: =(+B58-C58)/C58 -> -0.064501267 | U58: =(+C58-D58)/D58 -> -0.053939196 | V58: =(+D58-E58)/E58 -> 0.12642691 | W58: =(+E58-F58)/F58 -> -0.086761574 | X58: =(+F58-G58)/G58 -> -0.012398982
A59: SG&A | B59: 3575 | C59: 3588 | D59: 3650 | E59: 3178 | F59: 3190 | G59: 2927 | H59: 3444 | I59: 3122 | K59: =+B59/B$56 -> 0.13498207 | L59: =+C59/C$56 -> 0.13777744 | M59: =+D59/D$56 -> 0.13939278 | N59: =+E59/E$56 -> 0.12723706 | O59: =+F59/F$56 -> 0.12144054 | P59: =+G59/G$56 -> 0.11224881 | R59: =RATE(5,0,-G59,B59) -> 0.040808103 | S59: =AVERAGE(T59:X59) -> 0.042800586 | T59: =(+B59-C59)/C59 -> -0.0036231884 | U59: =(+C59-D59)/D59 -> -0.016986301 | V59: =(+D59-E59)/E59 -> 0.14852108 | W59: =(+E59-F59)/F59 -> -0.0037617555 | X59: =(+F59-G59)/G59 -> 0.089853092
A60: Goodwill impairment | B60: 444 | C60: 318 | D60: 2343 | E60: 1197 | F60: 7008 | G60: 0 | H60: 0 | I60: 0 | K60: =+B60/B$56 -> 0.016764206 | L60: =+C60/C$56 -> 0.012211044 | M60: =+D60/D$56 -> 0.089478709 | N60: =+E60/E$56 -> 0.04792409 | O60: =+F60/F$56 -> 0.26678849 | P60: =+G60/G$56 -> 0 | S60: =AVERAGE(T60:X60) -> -0.084962969 | T60: =(+B60-C60)/C60 -> 0.39622642 | U60: =(+C60-D60)/D60 -> -0.86427657 | V60: =(+D60-E60)/E60 -> 0.95739348 | W60: =(+E60-F60)/F60 -> -0.82919521
A61: Intangible impairment | B61: 469 | C61: 1316 | D61: 1056 | E61: 702 | F61: 8928 | G61: 49 | H61: 0 | I61: 0 | K61: =+B61/B$56 -> 0.017708137 | L61: =+C61/C$56 -> 0.050533753 | M61: =+D61/D$56 -> 0.040328432 | N61: =+E61/E$56 -> 0.028105857 | O61: =+F61/F$56 -> 0.33988122 | P61: =+G61/G$56 -> 0.0018791226 | R61: =RATE(5,0,-G61,B61) -> 0.57106934 | S61: =AVERAGE(T61:X61) -> 36.077916 | T61: =(+B61-C61)/C61 -> -0.64361702 | U61: =(+C61-D61)/D61 -> 0.24621212 | V61: =(+D61-E61)/E61 -> 0.5042735 | W61: =(+E61-F61)/F61 -> -0.92137097 | X61: =(+F61-G61)/G61 -> 181.20408
A62: Operating expenses | B62: =SUM(B59:B61) -> 4488 | C62: =SUM(C59:C61) -> 5222 | D62: =SUM(D59:D61) -> 7049 | E62: =SUM(E59:E61) -> 5077 | F62: =SUM(F59:F61) -> 19126 | G62: =SUM(G59:G61) -> 2976 | H62: =SUM(H59:H61) -> 3444 | I62: =SUM(I59:I61) -> 3122 | K62: =+B62/B$56 -> 0.16945441 | L62: =+C62/C$56 -> 0.20052223 | M62: =+D62/D$56 -> 0.26919992 | N62: =+E62/E$56 -> 0.20326701 | O62: =+F62/F$56 -> 0.72811025 | P62: =+G62/G$56 -> 0.11412793 | R62: =RATE(5,0,-G62,B62) -> 0.08563537 | S62: =AVERAGE(T62:X62) -> 0.93617419 | T62: =(+B62-C62)/C62 -> -0.14055917 | U62: =(+C62-D62)/D62 -> -0.2591857 | V62: =(+D62-E62)/E62 -> 0.38841836 | W62: =(+E62-F62)/F62 -> -0.73454983 | X62: =(+F62-G62)/G62 -> 5.4267473
A63: Operating income (loss) | B63: =+B58-B62 -> 3634 | C63: =+C58-C62 -> 3460 | D63: =+D58-D62 -> 2128 | E63: =+E58-E62 -> 3070 | F63: =+F58-F62 -> -10205 | G63: =+G58-G62 -> 6057 | H63: =+H58-H62 -> 6142 | I63: =+I58-I62 -> 2639 | K63: =+B63/B$56 -> 0.13720974 | L63: =+C63/C$56 -> 0.1328623 | M63: =+D63/D$56 -> 0.081267901 | N63: =+E63/E$56 -> 0.12291308 | O63: =+F63/F$56 -> -0.38849551 | P63: =+G63/G$56 -> 0.23228256 | R63: =RATE(5,0,-G63,B63) -> -0.097129486 | S63: =AVERAGE(T63:X63) -> -0.72325438 | T63: =(+B63-C63)/C63 -> 0.050289017 | U63: =(+C63-D63)/D63 -> 0.62593985 | V63: =(+D63-E63)/E63 -> -0.30684039 | W63: =(+E63-F63)/F63 -> -1.3008329 | X63: =(+F63-G63)/G63 -> -2.6848275
A64: Interest expense | B64: 921 | C64: 2047 | D64: 1394 | E64: 1361 | F64: 1284 | G64: 1234 | H64: 1134 | I64: 1321 | K64: =+B64/B$56 -> 0.034774401 | L64: =+C64/C$56 -> 0.078603794 | M64: =+D64/D$56 -> 0.053236586 | N64: =+E64/E$56 -> 0.054490131 | O64: =+F64/F$56 -> 0.048880767 | P64: =+G64/G$56 -> 0.047323209 | R64: =RATE(5,0,-G64,B64) -> -0.056832355 | S64: =AVERAGE(T64:X64) -> 0.008619448 | T64: =(+B64-C64)/C64 -> -0.55007328 | U64: =(+C64-D64)/D64 -> 0.46843615 | V64: =(+D64-E64)/E64 -> 0.024246877 | W64: =(+E64-F64)/F64 -> 0.059968847 | X64: =(+F64-G64)/G64 -> 0.040518639
A65: Other expense (income) | B65: -253 | C65: -295 | D65: -296 | E65: -952 | F65: -168 | G65: -627 | H65: -15 | I65: 305 | K65: =+B65/B$56 -> -0.0095525769 | L65: =+C65/C$56 -> -0.011327855 | M65: =+D65/D$56 -> -0.011304182 | N65: =+E65/E$56 -> -0.038115066 | O65: =+F65/F$56 -> -0.0063956144 | P65: =+G65/G$56 -> -0.024045099 | R65: =RATE(5,0,-G65,B65) -> -0.16599127 | S65: =AVERAGE(T65:X65) -> 0.61995647 | T65: =(+B65-C65)/C65 -> -0.14237288 | U65: =(+C65-D65)/D65 -> -0.0033783784 | V65: =(+D65-E65)/E65 -> -0.68907563 | W65: =(+E65-F65)/F65 -> 4.6666667 | X65: =(+F65-G65)/G65 -> -0.73205742
A66: Pretax Income | B66: =+B63-B64-B65 -> 2966 | C66: =+C63-C64-C65 -> 1708 | D66: =+D63-D64-D65 -> 1030 | E66: =+E63-E64-E65 -> 2661 | F66: =+F63-F64-F65 -> -11321 | G66: =+G63-G64-G65 -> 5450 | H66: =+H63-H64-H65 -> 5023 | I66: =+I63-I64-I65 -> 1013 | K66: =+B66/B$56 -> 0.11198792 | L66: =+C66/C$56 -> 0.06558636 | M66: =+D66/D$56 -> 0.039335497 | N66: =+E66/E$56 -> 0.10653801 | O66: =+F66/F$56 -> -0.43098066 | P66: =+G66/G$56 -> 0.20900445 | R66: =RATE(5,0,-G66,B66) -> -0.11456858 | S66: =AVERAGE(T66:X66) -> -0.70608774 | T66: =(+B66-C66)/C66 -> 0.73653396 | U66: =(+C66-D66)/D66 -> 0.65825243 | V66: =(+D66-E66)/E66 -> -0.61292747 | W66: =(+E66-F66)/F66 -> -1.2350499 | X66: =(+F66-G66)/G66 -> -3.0772477
A67: Tax provision | B67: 598 | C67: 684 | D67: 669 | E67: 728 | F67: -1067 | G67: -5482 | H67: 1381 | I67: 366 | K67: =+B67/B$56 -> 0.022578818 | L67: =+C67/C$56 -> 0.026265264 | M67: =+D67/D$56 -> 0.025548978 | N67: =+E67/E$56 -> 0.029146815 | O67: =+F67/F$56 -> -0.040619765 | P67: =+G67/G$56 -> -0.21023163 | R67: =RATE(5,0,G67,B67) -> -0.35797427 | S67: =AVERAGE(T67:X67) -> -0.53440064 | T67: =(+B67-C67)/C67 -> -0.12573099 | U67: =(+C67-D67)/D67 -> 0.022421525 | V67: =(+D67-E67)/E67 -> -0.081043956 | W67: =(+E67-F67)/F67 -> -1.6822868 | X67: =(+F67-G67)/G67 -> -0.80536301
A68: Net Income (loss) | B68: =+B66-B67 -> 2368 | C68: =+C66-C67 -> 1024 | D68: =+D66-D67 -> 361 | E68: =+E66-E67 -> 1933 | F68: =+F66-F67 -> -10254 | G68: =+G66-G67 -> 10932 | H68: =+H66-H67 -> 3642 | I68: =+I66-I67 -> 647 | K68: =+B68/B$56 -> 0.089409099 | L68: =+C68/C$56 -> 0.039321097 | M68: =+D68/D$56 -> 0.013786519 | N68: =+E68/E$56 -> 0.0773912 | O68: =+F68/F$56 -> -0.3903609 | P68: =+G68/G$56 -> 0.41923608 | R68: =RATE(5,0,-G68,B68) -> -0.26356162 | S68: =AVERAGE(T68:X68) -> -0.15813412 | T68: =(+B68-C68)/C68 -> 1.3125 | U68: =(+C68-D68)/D68 -> 1.8365651 | V68: =(+D68-E68)/E68 -> -0.81324366 | W68: =(+E68-F68)/F68 -> -1.1885118 | X68: =(+F68-G68)/G68 -> -1.9379802
A69: Noncontrolling interest | B69: 5 | C69: 12 | D69: 5 | E69: -2 | F69: -62 | G69: -9 | H69: 10 | I69: 13 | K69: =+B69/B$56 -> 0.00018878611 | L69: =+C69/C$56 -> 0.0004607941 | M69: =+D69/D$56 -> 0.00019094902 | N69: =+E69/E$56 -> -8.0073668e-05 | O69: =+F69/F$56 -> -0.0023602863 | P69: =+G69/G$56 -> -0.00034514496 | R69: =RATE(5,0,G69,B69) -> -0.11091046 | S69: =AVERAGE(T69:X69) -> 0.44756272 | T69: =(+B69-C69)/C69 -> -0.58333333 | U69: =(+C69-D69)/D69 -> 1.4 | V69: =(+D69-E69)/E69 -> -3.5 | W69: =(+E69-F69)/F69 -> -0.96774194 | X69: =(+F69-G69)/G69 -> 5.8888889
A70: Net income (Loss)-Kraft Heinz | B70: =+B68-B69 -> 2363 | C70: =+C68-C69 -> 1012 | D70: =+D68-D69 -> 356 | E70: =+E68-E69 -> 1935 | F70: =+F68-F69 -> -10192 | G70: =+G68-G69 -> 10941 | H70: =+H68-H69 -> 3632 | I70: =+I68-I69 -> 634 | K70: =+B70/B$56 -> 0.089220313 | L70: =+C70/C$56 -> 0.038860303 | M70: =+D70/D$56 -> 0.01359557 | N70: =+E70/E$56 -> 0.077471274 | O70: =+F70/F$56 -> -0.38800061 | P70: =+G70/G$56 -> 0.41958122 | R70: =RATE(5,0,-G70,B70) -> -0.26399402 | S70: =AVERAGE(T70:X70) -> -0.1519481 | T70: =(+B70-C70)/C70 -> 1.3349802 | U70: =(+C70-D70)/D70 -> 1.8426966 | V70: =(+D70-E70)/E70 -> -0.81602067 | W70: =(+E70-F70)/F70 -> -1.1898548 | X70: =(+F70-G70)/G70 -> -1.9315419
A71: Preferred dividend | B71: 0 | C71: 0 | D71: 0 | E71: 0 | F71: 0 | G71: 0 | H71: 180 | I71: 900
A72: Net income (loss) for Common shareholders | B72: =+B70-B71 -> 2363 | C72: =+C70-C71 -> 1012 | D72: =+D70-D71 -> 356 | E72: =+E70-E71 -> 1935 | F72: =+F70-F71 -> -10192 | G72: =+G70-G71 -> 10941 | H72: =+H70-H71 -> 3452 | I72: =+I70-I71 -> -266
A74: Diluted W. Ave shares outstanding (notes) | B74: 1235 | C74: 1236 | D74: 1228 | E74: 1224 | F74: 1219 | G74: 1228 | H74: =3452/2.81 -> 1228.4698 | I74: =-266/-0.34 -> 782.35294 | R74: =RATE(5,0,-G74,B74) -> 0.0011374745 | S74: =AVERAGE(T74:X74) -> 0.0011492606 | T74: =(+B74-C74)/C74 -> -0.00080906149 | U74: =(+C74-D74)/D74 -> 0.006514658 | V74: =(+D74-E74)/E74 -> 0.0032679739 | W74: =(+E74-F74)/F74 -> 0.0041017227 | X74: =(+F74-G74)/G74 -> -0.0073289902
A75: Diluted EPS | B75: =+B70/B74 -> 1.9133603 | C75: =+C70/C74 -> 0.81877023 | D75: =+D70/D74 -> 0.28990228 | E75: =+E70/E74 -> 1.5808824 | F75: =+F70/F74 -> -8.3609516 | G75: =+G70/G74 -> 8.9096091 | H75: =+H72/H74 -> 2.81 | I75: =+I72/I74 -> -0.34 | R75: =RATE(5,0,-G75,B75) -> -0.26483026 | S75: =AVERAGE(T75:X75) -> -0.15659011 | T75: =(+B75-C75)/C75 -> 1.3368709 | U75: =(+C75-D75)/D75 -> 1.8242973 | V75: =(+D75-E75)/E75 -> -0.81661995 | W75: =(+E75-F75)/F75 -> -1.1890792 | X75: =(+F75-G75)/G75 -> -1.9384196
A76: Dividends per share (Equity Stmt)) | B76: 1.6 | C76: 1.6 | D76: 1.6 | E76: 1.6 | F76: 2.5 | G76: 2.45 | H76: 2.35 | I76: 1.7 | R76: =RATE(5,0,-G76,B76) -> -0.0816869 | S76: =AVERAGE(T76:X76) -> -0.067918367 | T76: =(+B76-C76)/C76 -> 0 | U76: =(+C76-D76)/D76 -> 0 | V76: =(+D76-E76)/E76 -> 0 | W76: =(+E76-F76)/F76 -> -0.36 | X76: =(+F76-G76)/G76 -> 0.020408163
A79: =+A1 -> Kraft Heinz Company | B79: =+B1 -> As reported | K79: =+B79 -> As reported | R79: =+B79 -> As reported
A80: Consolidated Cash Flows | K80: Common Size on Operating Cash Flows | R80: Horizontal(Growth) Analysis
A81: =+A3 -> in millions except per share data | F81: Late Filing | G81: Restated | I81: Partial | P81: Restated | R81: 5 Year | S81: Annual | T81: 2021 to | U81: 2020 to | V81: 2019 to | W81: 2018 to | X81: 2017 to
A82: =+A4 -> Fiscal year ended 12/31 | B82: 2022 | C82: 2021 | D82: 2020 | E82: 2019 | F82: 2018 | G82: 2017 | H82: 2016 | I82: 2015 | K82: 2022 | L82: 2021 | M82: 2020 | N82: 2019 | O82: 2018 | P82: 2017 | R82: CAGR | S82: Average | T82: 2022 | U82: 2021 | V82: 2020 | W82: 2019 | X82: 2018
A83: Net income (loss) | B83: =+B68 -> 2368 | C83: =+C68 -> 1024 | D83: =+D68 -> 361 | E83: =+E68 -> 1933 | F83: =+F68 -> -10254 | G83: =+G68 -> 10932 | H83: =+H68 -> 3642 | I83: =+I68 -> 647 | R83: =RATE(5,0,-G83,B83) -> -0.26356162 | S83: =AVERAGE(T83:X83) -> -0.15813412 | T83: =(+B83-C83)/C83 -> 1.3125 | U83: =(+C83-D83)/D83 -> 1.8365651 | V83: =(+D83-E83)/E83 -> -0.81324366 | W83: =(+E83-F83)/F83 -> -1.1885118 | X83: =(+F83-G83)/G83 -> -1.9379802
A84: Depreciation & amortization | B84: 933 | C84: 910 | D84: 969 | E84: 994 | F84: 983 | G84: 1031 | H84: 1337 | I84: 740 | R84: =RATE(5,0,-G84,B84) -> -0.019777661 | S84: =AVERAGE(T84:X84) -> -0.01922604 | T84: =(+B84-C84)/C84 -> 0.025274725 | U84: =(+C84-D84)/D84 -> -0.060887513 | V84: =(+D84-E84)/E84 -> -0.025150905 | W84: =(+E84-F84)/F84 -> 0.011190234 | X84: =(+F84-G84)/G84 -> -0.046556741
A85: Amortization of PRB | B85: -14 | C85: -7 | D85: -122 | E85: -306 | F85: -339 | G85: -328 | H85: -333 | I85: -112 | R85: =RATE(5,0,-G85,B85) -> -0.46782945 | S85: =AVERAGE(T85:X85) -> -0.12154774 | T85: =(+B85-C85)/C85 -> 1 | U85: =(+C85-D85)/D85 -> -0.94262295 | V85: =(+D85-E85)/E85 -> -0.60130719 | W85: =(+E85-F85)/F85 -> -0.097345133 | X85: =(+F85-G85)/G85 -> 0.033536585
A86: Amortization of inventory step-up | B86: 0 | C86: 0 | D86: 0 | E86: 0 | F86: 0 | G86: 0 | H86: 0 | I86: 347
A87: Divestiture-rel;ate license income | B87: -56 | C87: -4 | D87: 0 | E87: 0 | F87: 0 | G87: 0 | H87: 0 | I87: 0 | S87: =AVERAGE(T87:X87) -> 13 | T87: =(+B87-C87)/C87 -> 13
A88: Impairment losses | B88: 0 | C88: 0 | D88: 0 | E88: 0 | F88: 0 | G88: 0 | H88: 0 | I88: 58
A89: Stock-based compensation | B89: 148 | C89: 197 | D89: 156 | E89: 46 | F89: 33 | G89: 46 | H89: 46 | I89: 133 | R89: =RATE(5,0,-G89,B89) -> 0.26328336 | S89: =AVERAGE(T89:X89) -> 0.50334492 | T89: =(+B89-C89)/C89 -> -0.24873096 | U89: =(+C89-D89)/D89 -> 0.26282051 | V89: =(+D89-E89)/E89 -> 2.3913043 | W89: =(+E89-F89)/F89 -> 0.39393939 | X89: =(+F89-G89)/G89 -> -0.2826087
A90: Deferred income taxes | B90: -278 | C90: -1042 | D90: -343 | E90: -293 | F90: -1967 | G90: -6495 | H90: -29 | I90: -317 | R90: =RATE(5,0,-G90,B90) -> -0.46753247 | S90: =AVERAGE(T90:X90) -> -0.014569977 | T90: =(+B90-C90)/C90 -> -0.73320537 | U90: =(+C90-D90)/D90 -> 2.0379009 | V90: =(+D90-E90)/E90 -> 0.17064846 | W90: =(+E90-F90)/F90 -> -0.8510422 | X90: =(+F90-G90)/G90 -> -0.69715166
A91: PRB Contributions | B91: -23 | C91: -27 | D91: -27 | E91: -32 | F91: -76 | G91: -1659 | H91: -344 | I91: -286 | R91: =RATE(5,0,-G91,B91) -> -0.57501237 | S91: =AVERAGE(T91:X91) -> -0.36750696 | T91: =(+B91-C91)/C91 -> -0.14814815 | U91: =(+C91-D91)/D91 -> 0 | V91: =(+D91-E91)/E91 -> -0.15625 | W91: =(+E91-F91)/F91 -> -0.57894737 | X91: =(+F91-G91)/G91 -> -0.95418927
A92: Goodwill and intangible impairment | B92: 913 | C92: 1634 | D92: 3399 | E92: 1899 | F92: 15936 | G92: 49 | H92: 0 | I92: 0 | R92: =RATE(5,0,-G92,B92) -> 0.79496068 | S92: =AVERAGE(T92:X92) -> 64.634605 | T92: =(+B92-C92)/C92 -> -0.44124847 | U92: =(+C92-D92)/D92 -> -0.51927037 | V92: =(+D92-E92)/E92 -> 0.78988942 | W92: =(+E92-F92)/F92 -> -0.88083584 | X92: =(+F92-G92)/G92 -> 324.22449
A93: Nonmonetary currency devaluation | B93: 17 | C93: 0 | D93: 6 | E93: 10 | F93: 146 | G93: 36 | H93: 24 | I93: 234 | R93: =RATE(5,0,-G93,B93) -> -0.13934463 | S93: =AVERAGE(T93:X93) -> 0.18101218 | U93: =(+C93-D93)/D93 -> -1 | V93: =(+D93-E93)/E93 -> -0.4 | W93: =(+E93-F93)/F93 -> -0.93150685 | X93: =(+F93-G93)/G93 -> 3.0555556
A94: Write-off of debt issuance costs | B94: 0 | C94: 0 | D94: 0 | E94: 0 | F94: 0 | G94: 0 | H94: 0 | I94: 236
A95: Loss/(gain) on sale of business | B95: -25 | C95: -44 | D95: 2 | E95: -420 | F95: 15 | G95: 0 | H95: 0 | I95: 0 | S95: =AVERAGE(T95:X95) -> -13.359145 | T95: =(+B95-C95)/C95 -> -0.43181818 | U95: =(+C95-D95)/D95 -> -23 | V95: =(+D95-E95)/E95 -> -1.0047619 | W95: =(+E95-F95)/F95 -> -29
A96: Proceeds from sale of licence | B96: 0 | C96: 1587 | D96: 0 | E96: 0 | F96: 0 | G96: 0 | H96: 0 | I96: 0 | S96: =AVERAGE(T96:X96) -> -1 | T96: =(+B96-C96)/C96 -> -1
A97: Loss (gain) on exstinguishment of debt | B97: -38 | C97: 917 | D97: 124 | E97: 0 | F97: 0 | G97: 0 | H97: 0 | I97: 0 | S97: =AVERAGE(T97:X97) -> 2.6768609 | T97: =(+B97-C97)/C97 -> -1.0414395 | U97: =(+C97-D97)/D97 -> 6.3951613
A98: Other items | B98: 7 | C98: -187 | D98: -54 | E98: -46 | F98: 160 | G98: 253 | H98: -134 | I98: 120 | R98: =RATE(5,0,-G98,B98) -> -0.51202732 | S98: =AVERAGE(T98:X98) -> -0.011129216 | T98: =(+B98-C98)/C98 -> -1.0374332 | U98: =(+C98-D98)/D98 -> 2.462963 | V98: =(+D98-E98)/E98 -> 0.17391304 | W98: =(+E98-F98)/F98 -> -1.2875 | X98: =(+F98-G98)/G98 -> -0.36758893
A99: Operating Cash flow earned | B99: =SUM(B83:B98) -> 3952 | C99: =SUM(C83:C98) -> 4958 | D99: =SUM(D83:D98) -> 4471 | E99: =SUM(E83:E98) -> 3785 | F99: =SUM(F83:F98) -> 4637 | G99: =SUM(G83:G98) -> 3865 | H99: =SUM(H83:H98) -> 4209 | I99: =SUM(I83:I98) -> 1800 | R99: =RATE(5,0,-G99,B99) -> 0.0044619445 | S99: =AVERAGE(T99:X99) -> 0.020652661 | T99: =(+B99-C99)/C99 -> -0.2029044 | U99: =(+C99-D99)/D99 -> 0.10892418 | V99: =(+D99-E99)/E99 -> 0.18124174 | W99: =(+E99-F99)/F99 -> -0.18373949 | X99: =(+F99-G99)/G99 -> 0.19974127
A100: Change in Net Operating Assets:
A101: Trade receivables | B101: -228 | C101: 87 | D101: -26 | E101: 140 | F101: -2280 | G101: -2629 | H101: 80 | I101: 838 | R101: =RATE(5,0,-G101,B101) -> -0.38676229 | S101: =AVERAGE(T101:X101) -> -2.0693423 | T101: =(+B101-C101)/C101 -> -3.6206897 | U101: =(+C101-D101)/D101 -> -4.3461538 | V101: =(+D101-E101)/E101 -> -1.1857143 | W101: =(+E101-F101)/F101 -> -1.0614035 | X101: =(+F101-G101)/G101 -> -0.1327501
A102: Inventories | B102: -1121 | C102: -144 | D102: -249 | E102: -277 | F102: -251 | G102: -236 | H102: -130 | I102: 25 | R102: =RATE(5,0,-G102,B102) -> 0.36564784 | S102: =AVERAGE(T102:X102) -> 1.2858195 | T102: =(+B102-C102)/C102 -> 6.7847222 | U102: =(+C102-D102)/D102 -> -0.42168675 | V102: =(+D102-E102)/E102 -> -0.10108303 | W102: =(+E102-F102)/F102 -> 0.10358566 | X102: =(+F102-G102)/G102 -> 0.063559322
A103: Accounts payable | B103: 152 | C103: 408 | D103: 207 | E103: -58 | F103: -23 | G103: 441 | H103: 943 | I103: -119 | R103: =RATE(5,0,-G103,B103) -> -0.19187043 | S103: =AVERAGE(T103:X103) -> -0.75116341 | T103: =(+B103-C103)/C103 -> -0.62745098 | U103: =(+C103-D103)/D103 -> 0.97101449 | V103: =(+D103-E103)/E103 -> -4.5689655 | W103: =(+E103-F103)/F103 -> 1.5217391 | X103: =(+F103-G103)/G103 -> -1.0521542
A104: Other current assets | B104: -314 | C104: -32 | D104: 40 | E104: 52 | F104: -146 | G104: -64 | H104: =454-42 -> 412 | I104: =-422+114 -> -308 | R104: =RATE(5,0,-G104,B104) -> 0.37451643 | S104: =AVERAGE(T104:X104) -> 1.3413633 | T104: =(+B104-C104)/C104 -> 8.8125 | U104: =(+C104-D104)/D104 -> -1.8 | V104: =(+D104-E104)/E104 -> -0.23076923 | W104: =(+E104-F104)/F104 -> -1.3561644 | X104: =(+F104-G104)/G104 -> 1.28125
A105: Other current liabilities | B105: 28 | C105: 87 | D105: 486 | E105: -90 | F105: 637 | G105: -876 | H105: -276 | I105: 231 | R105: =RATE(5,0,G105,B105) -> -0.49773746 | S105: =AVERAGE(T105:X105) -> -2.153521 | T105: =(+B105-C105)/C105 -> -0.67816092 | U105: =(+C105-D105)/D105 -> -0.82098765 | V105: =(+D105-E105)/E105 -> -6.4 | W105: =(+E105-F105)/F105 -> -1.1412873 | X105: =(+F105-G105)/G105 -> -1.7271689
A106: Operating cash flows | B106: =SUM(B99:B105) -> 2469 | C106: =SUM(C99:C105) -> 5364 | D106: =SUM(D99:D105) -> 4929 | E106: =SUM(E99:E105) -> 3552 | F106: =SUM(F99:F105) -> 2574 | G106: =SUM(G99:G105) -> 501 | H106: =SUM(H99:H105) -> 5238 | I106: =SUM(I99:I105) -> 2467 | K106: =+B106/B$106 -> 1 | L106: =+C106/C$106 -> 1 | M106: =+D106/D$106 -> 1 | N106: =+E106/E$106 -> 1 | O106: =+F106/F$106 -> 1 | P106: =+G106/G$106 -> 1 | R106: =RATE(5,0,-G106,B106) -> 0.37574098 | S106: =AVERAGE(T106:X106) -> 0.89077817 | T106: =(+B106-C106)/C106 -> -0.53970917 | U106: =(+C106-D106)/D106 -> 0.088253195 | V106: =(+D106-E106)/E106 -> 0.38766892 | W106: =(+E106-F106)/F106 -> 0.37995338 | X106: =(+F106-G106)/G106 -> 4.1377246
...

Sheet Reclassified
A1: Kraft Heinz Company | B1: Reclassified | J1: =+B1 -> Reclassified | R1: =+B1 -> Reclassified
A2: Consolidated Balance Sheets | J2: Common Size on Total Assets | R2: Horizontal(Growth) Analysis
A3: in millions except per share data | F3: Late filing | G3: Restated | O3: Restated | R3: 5 Year | S3: Annual | T3: 2021 to | U3: 2020 to | V3: 2019 to | W3: 2018 to | X3: 2017 to
A4: Fiscal Year ended 12/31: | B4: 2022 | C4: 2021 | D4: 2020 | E4: 2019 | F4: 2018 | G4: 2017 | J4: 2022 | K4: 2021 | L4: 2020 | M4: 2019 | N4: 2018 | O4: 2017 | R4: CAGR | S4: Average | T4: 2022 | U4: 2021 | V4: 2020 | W4: 2019 | X4: 2018
A5: Assets:
A6: Cash and equivalents | B6: 1040 | C6: 3445 | D6: 3417 | E6: 2279 | F6: 1130 | G6: 1629 | J6: =+B6/B$21 -> 0.011490062 | K6: =+C6/C$21 -> 0.036886738 | L6: =+D6/D$21 -> 0.034228188 | M6: =+E6/E$21 -> 0.022464268 | N6: =+F6/F$21 -> 0.01092199 | O6: =+G6/G$21 -> 0.0135646 | R6: =RATE(5,0,-G6,B6) -> -0.085839502 | S6: =AVERAGE(T6:X6) -> 0.10398284 | T6: =(+B6-C6)/C6 -> -0.69811321 | U6: =(+C6-D6)/D6 -> 0.0081943225 | V6: =(+D6-E6)/E6 -> 0.49934182 | W6: =(+E6-F6)/F6 -> 1.0168142 | X6: =(+F6-G6)/G6 -> -0.3063229
A7: Marketable Securities | B7: 0 | C7: 0 | D7: 0 | E7: 0 | F7: 0 | G7: 0
A8: Trade receivables | B8: 2120 | C8: 1957 | D8: 2063 | E8: 1973 | F8: 2129 | G8: 921 | J8: =+B8/B$21 -> 0.02342205 | K8: =+C8/C$21 -> 0.020954237 | L8: =+D8/D$21 -> 0.020665131 | M8: =+E8/E$21 -> 0.019448004 | N8: =+F8/F$21 -> 0.020577802 | O8: =+G8/G$21 -> 0.0076691203 | R8: =RATE(5,0,-G8,B8) -> 0.18144973 | S8: =AVERAGE(T8:X8) -> 0.26317381 | T8: =(+B8-C8)/C8 -> 0.083290751 | U8: =(+C8-D8)/D8 -> -0.051381483 | V8: =(+D8-E8)/E8 -> 0.045615813 | W8: =(+E8-F8)/F8 -> -0.073273837 | X8: =(+F8-G8)/G8 -> 1.3116178
A9: Inventories | B9: 3651 | C9: 2729 | D9: 2554 | E9: 2721 | F9: 2667 | G9: 2760 | J9: =+B9/B$21 -> 0.040336747 | K9: =+C9/C$21 -> 0.029220293 | L9: =+D9/D$21 -> 0.025583492 | M9: =+E9/E$21 -> 0.026821094 | N9: =+F9/F$21 -> 0.025777829 | O9: =+G9/G$21 -> 0.02298238 | R9: =RATE(5,0,-G9,B9) -> 0.057549125 | S9: =AVERAGE(T9:X9) -> 0.066309997 | T9: =(+B9-C9)/C9 -> 0.33785269 | U9: =(+C9-D9)/D9 -> 0.068519969 | V9: =(+D9-E9)/E9 -> -0.061374495 | W9: =(+E9-F9)/F9 -> 0.020247469 | X9: =(+F9-G9)/G9 -> -0.033695652
A10: Other current assets | B10: =+B192 -> 1086 | C10: =+C192 -> 863 | D10: =+D192 -> 2788 | E10: =+E192 -> 1124 | F10: =+F192 -> 3149 | G10: =+G192 -> 1891 | J10: =+B10/B$21 -> 0.011998276 | K10: =+C10/C$21 -> 0.0092404223 | L10: =+D10/D$21 -> 0.027927477 | M10: =+E10/E$21 -> 0.011079349 | N10: =+F10/F$21 -> 0.03043659 | O10: =+G10/G$21 -> 0.015746261 | R10: =RATE(5,0,-G10,B10) -> -0.10499047 | S10: =AVERAGE(T10:X10) -> 0.21411281 | T10: =(+B10-C10)/C10 -> 0.25840093 | U10: =(+C10-D10)/D10 -> -0.69045911 | V10: =(+D10-E10)/E10 -> 1.480427 | W10: =(+E10-F10)/F10 -> -0.64306129 | X10: =(+F10-G10)/G10 -> 0.66525648
A11: Total current assets | B11: =SUM(B6:B10) -> 7897 | C11: =SUM(C6:C10) -> 8994 | D11: =SUM(D6:D10) -> 10822 | E11: =SUM(E6:E10) -> 8097 | F11: =SUM(F6:F10) -> 9075 | G11: =SUM(G6:G10) -> 7201 | J11: =+B11/B$21 -> 0.087247136 | K11: =+C11/C$21 -> 0.09630169 | L11: =+D11/D$21 -> 0.10840429 | M11: =+E11/E$21 -> 0.079812716 | N11: =+F11/F$21 -> 0.087714211 | O11: =+G11/G$21 -> 0.059962362 | R11: =RATE(5,0,-G11,B11) -> 0.018623908 | S11: =AVERAGE(T11:X11) -> 0.039626412 | T11: =(+B11-C11)/C11 -> -0.1219702 | U11: =(+C11-D11)/D11 -> -0.16891517 | V11: =(+D11-E11)/E11 -> 0.3365444 | W11: =(+E11-F11)/F11 -> -0.1077686 | X11: =(+F11-G11)/G11 -> 0.26024163
A12: Land | B12: =+B170 -> 200 | C12: =+C170 -> 207 | D12: =+D170 -> 219 | E12: =+E170 -> 210 | F12: =+F170 -> 218 | G12: =+G170 -> 250 | J12: =+B12/B$21 -> 0.0022096273 | K12: =+C12/C$21 -> 0.0022164165 | L12: =+D12/D$21 -> 0.0021937293 | M12: =+E12/E$21 -> 0.0020699852 | N12: =+F12/F$21 -> 0.0021070742 | O12: =+G12/G$21 -> 0.0020817373 | R12: =RATE(5,0,-G12,B12) -> -0.0436475 | S12: =AVERAGE(T12:X12) -> -0.04209021 | T12: =(+B12-C12)/C12 -> -0.033816425 | U12: =(+C12-D12)/D12 -> -0.054794521 | V12: =(+D12-E12)/E12 -> 0.042857143 | W12: =(+E12-F12)/F12 -> -0.036697248 | X12: =(+F12-G12)/G12 -> -0.128
A13: Construction in progress | B13: =+B171 -> 1161 | C13: =+C171 -> 1002 | D13: =+D171 -> 792 | E13: =+E171 -> 1033 | F13: =+F171 -> 1165 | G13: =+G171 -> 1345 | J13: =+B13/B$21 -> 0.012826887 | K13: =+C13/C$21 -> 0.010728741 | L13: =+D13/D$21 -> 0.0079334869 | M13: =+E13/E$21 -> 0.010182356 | N13: =+F13/F$21 -> 0.011260282 | O13: =+G13/G$21 -> 0.011199747 | R13: =RATE(5,0,-G13,B13) -> -0.028993835 | S13: =AVERAGE(T13:X13) -> -0.011320126 | T13: =(+B13-C13)/C13 -> 0.15868263 | U13: =(+C13-D13)/D13 -> 0.26515152 | V13: =(+D13-E13)/E13 -> -0.23330106 | W13: =(+E13-F13)/F13 -> -0.11330472 | X13: =(+F13-G13)/G13 -> -0.133829
A14: Depreciable assets | B14: =+B172 -> 9591 | C14: =+C172 -> 9465 | D14: =+D172 -> 9428 | E14: =+E172 -> 8999 | F14: =+F172 -> 8279 | G14: =+G172 -> 7555 | J14: =+B14/B$21 -> 0.10596268 | K14: =+C14/C$21 -> 0.10134484 | L14: =+D14/D$21 -> 0.094440549 | M14: =+E14/E$21 -> 0.088703795 | N14: =+F14/F$21 -> 0.080020491 | O14: =+G14/G$21 -> 0.062910102 | R14: =RATE(5,0,-G14,B14) -> 0.048880193 | S14: =AVERAGE(T14:X14) -> 0.049541249 | T14: =(+B14-C14)/C14 -> 0.013312203 | U14: =(+C14-D14)/D14 -> 0.0039244803 | V14: =(+D14-E14)/E14 -> 0.047671964 | W14: =(+E14-F14)/F14 -> 0.086967025 | X14: =(+F14-G14)/G14 -> 0.095830576
A15: PP&E - at cost | B15: =+B173 -> 10952 | C15: =+C173 -> 10674 | D15: =+D173 -> 10439 | E15: =+E173 -> 10242 | F15: =+F173 -> 9662 | G15: =+G173 -> 9150 | J15: =+B15/B$21 -> 0.12099919 | K15: =+C15/C$21 -> 0.11429 | L15: =+D15/D$21 -> 0.10456777 | M15: =+E15/E$21 -> 0.10095614 | N15: =+F15/F$21 -> 0.093387847 | O15: =+G15/G$21 -> 0.076191586 | R15: =RATE(5,0,-G15,B15) -> 0.03660779 | S15: =AVERAGE(T15:X15) -> 0.036755223 | T15: =(+B15-C15)/C15 -> 0.026044594 | U15: =(+C15-D15)/D15 -> 0.022511735 | V15: =(+D15-E15)/E15 -> 0.019234525 | W15: =(+E15-F15)/F15 -> 0.06002898 | X15: =(+F15-G15)/G15 -> 0.055956284
A16: Accumulated depreciation | B16: =+B174 -> -4212 | C16: =+C174 -> -3868 | D16: =+D174 -> -3563 | E16: =+E174 -> -3187 | F16: =+F174 -> -2584 | G16: =+G174 -> -2089 | J16: =+B16/B$21 -> -0.046534752 | K16: =+C16/C$21 -> -0.041415937 | L16: =+D16/D$21 -> -0.035690674 | M16: =+E16/E$21 -> -0.03141449 | N16: =+F16/F$21 -> -0.024975595 | O16: =+G16/G$21 -> -0.017394997 | R16: =RATE(5,0,-G16,B16) -> 0.15056189 | S16: =AVERAGE(T16:X16) -> 0.15256616 | T16: =(+B16-C16)/C16 -> 0.08893485 | U16: =(+C16-D16)/D16 -> 0.085602021 | V16: =(+D16-E16)/E16 -> 0.11797929 | W16: =(+E16-F16)/F16 -> 0.23335913 | X16: =(+F16-G16)/G16 -> 0.23695548
A17: Property, plant & equipment - net | B17: 6740 | C17: 6806 | D17: 6876 | E17: 7055 | F17: 7078 | G17: 7061 | J17: =+B17/B$21 -> 0.074464442 | K17: =+C17/C$21 -> 0.07287406 | L17: =+D17/D$21 -> 0.068877091 | M17: =+E17/E$21 -> 0.069541646 | N17: =+F17/F$21 -> 0.068412252 | O17: =+G17/G$21 -> 0.058796589 | R17: =RATE(5,0,-G17,B17) -> -0.0092621911 | S17: =AVERAGE(T17:X17) -> -0.0092183309 | T17: =(+B17-C17)/C17 -> -0.0096973259 | U17: =(+C17-D17)/D17 -> -0.010180337 | V17: =(+D17-E17)/E17 -> -0.025372077 | W17: =(+E17-F17)/F17 -> -0.0032495055 | X17: =(+F17-G17)/G17 -> 0.002407591
A18: Right of Use assets | B18: =+B179 -> 668 | C18: =+C179 -> 569 | D18: =+D179 -> 562 | E18: =+E179 -> 542 | F18: =+F179 -> 0 | G18: =+G179 -> 0
A19: Goodwill and Intangibles (see detail) | B19: =+B196 -> 73482 | C19: =+C196 -> 74838 | D19: =+D196 -> 79756 | E19: =+E196 -> 84198 | F19: =+F196 -> 85971 | G19: =+G196 -> 104257 | J19: =+B19/B$21 -> 0.81183918 | K19: =+C19/C$21 -> 0.80131486 | L19: =+D19/D$21 -> 0.79891816 | M19: =+E19/E$21 -> 0.82994579 | N19: =+F19/F$21 -> 0.83095079 | O19: =+G19/G$21 -> 0.86814276 | R19: =RATE(5,0,-G19,B19) -> -0.067572339 | S19: =AVERAGE(T19:X19) -> -0.065711108 | T19: =(+B19-C19)/C19 -> -0.018119137 | U19: =(+C19-D19)/D19 -> -0.061663072 | V19: =(+D19-E19)/E19 -> -0.052756598 | W19: =(+E19-F19)/F19 -> -0.020623233 | X19: =(+F19-G19)/G19 -> -0.1753935
A20: Other assets | B20: =+B200 -> 1726 | C20: =+C200 -> 2187 | D20: =+D200 -> 1814 | E20: =+E200 -> 1558 | F20: =+F200 -> 1337 | G20: =+G200 -> 1573 | J20: =+B20/B$21 -> 0.019069084 | K20: =+C20/C$21 -> 0.023416922 | L20: =+D20/D$21 -> 0.018170891 | M20: =+E20/E$21 -> 0.015357319 | N20: =+F20/F$21 -> 0.012922744 | O20: =+G20/G$21 -> 0.013098291 | R20: =RATE(5,0,-G20,B20) -> 0.018737783 | S20: =AVERAGE(T20:X20) -> 0.034881754 | T20: =(+B20-C20)/C20 -> -0.21079104 | U20: =(+C20-D20)/D20 -> 0.20562293 | V20: =(+D20-E20)/E20 -> 0.16431322 | W20: =(+E20-F20)/F20 -> 0.16529544 | X20: =(+F20-G20)/G20 -> -0.15003179
A21: Total Assets | B21: =+B11+SUM(B17:B20) -> 90513 | C21: =+C11+SUM(C17:C20) -> 93394 | D21: =+D11+SUM(D17:D20) -> 99830 | E21: =+E11+SUM(E17:E20) -> 101450 | F21: =+F11+SUM(F17:F20) -> 103461 | G21: =+G11+SUM(G17:G20) -> 120092 | J21: =+B21/B$21 -> 1 | K21: =+C21/C$21 -> 1 | L21: =+D21/D$21 -> 1 | M21: =+E21/E$21 -> 1 | N21: =+F21/F$21 -> 1 | O21: =+G21/G$21 -> 1 | R21: =RATE(5,0,-G21,B21) -> -0.054983533 | S21: =AVERAGE(T21:X21) -> -0.053841726 | T21: =(+B21-C21)/C21 -> -0.030847806 | U21: =(+C21-D21)/D21 -> -0.064469598 | V21: =(+D21-E21)/E21 -> -0.015968457 | W21: =(+E21-F21)/F21 -> -0.019437276 | X21: =(+F21-G21)/G21 -> -0.13848549
A22: Liabilities and Equity
A23: Current Debt (see detail) | B23: =+B204 -> 837 | C23: =+C204 -> 754 | D23: =+D204 -> 236 | E23: =+E204 -> 1028 | F23: =+F204 -> 398 | G23: =+G204 -> 3195 | J23: =+B23/B$21 -> 0.0092472904 | K23: =+C23/C$21 -> 0.0080733238 | L23: =+D23/D$21 -> 0.0023640188 | M23: =+E23/E$21 -> 0.01013307 | N23: =+F23/F$21 -> 0.0038468602 | O23: =+G23/G$21 -> 0.026604603 | R23: =RATE(5,0,-G23,B23) -> -0.23501852 | S23: =AVERAGE(T23:X23) -> 0.44841021 | T23: =(+B23-C23)/C23 -> 0.11007958 | U23: =(+C23-D23)/D23 -> 2.1949153 | V23: =(+D23-E23)/E23 -> -0.77042802 | W23: =(+E23-F23)/F23 -> 1.5829146 | X23: =(+F23-G23)/G23 -> -0.87543036
A24: Trade payables | B24: 4848 | C24: 4753 | D24: 4304 | E24: 4003 | F24: 4153 | G24: 4362 | J24: =+B24/B$21 -> 0.053561367 | K24: =+C24/C$21 -> 0.05089192 | L24: =+D24/D$21 -> 0.043113293 | M24: =+E24/E$21 -> 0.039457861 | N24: =+F24/F$21 -> 0.040140729 | O24: =+G24/G$21 -> 0.036322153 | R24: =RATE(5,0,-G24,B24) -> 0.021351874 | S24: =AVERAGE(T24:X24) -> 0.023094055 | T24: =(+B24-C24)/C24 -> 0.019987376 | U24: =(+C24-D24)/D24 -> 0.10432156 | V24: =(+D24-E24)/E24 -> 0.075193605 | W24: =(+E24-F24)/F24 -> -0.036118469 | X24: =(+F24-G24)/G24 -> -0.047913801
A25: Deferred revenue | B25: 0 | C25: 0 | D25: 0 | E25: 0 | F25: 0 | G25: 0
A26: Current portion of operating lease liabilities | B26: =+B180 -> 125 | C26: =+C180 -> 133 | D26: =+D180 -> 135 | E26: =+E180 -> 147 | F26: =+F180 -> 0 | G26: =+G180 -> 0
A27: Other current liabilities (see detail) | B27: =+B212 -> 3218 | C27: =+C212 -> 3424 | D27: =+D212 -> 3386 | E27: =+E212 -> 2697 | F27: =+F212 -> 2952 | G27: =+G212 -> 2597 | J27: =+B27/B$21 -> 0.035552904 | K27: =+C27/C$21 -> 0.036661884 | L27: =+D27/D$21 -> 0.03391766 | M27: =+E27/E$21 -> 0.026584524 | N27: =+F27/F$21 -> 0.028532491 | O27: =+G27/G$21 -> 0.021625087 | R27: =RATE(5,0,-G27,B27) -> 0.04381328 | S27: =AVERAGE(T27:X27) -> 0.051368449 | T27: =(+B27-C27)/C27 -> -0.060163551 | U27: =(+C27-D27)/D27 -> 0.011222682 | V27: =(+D27-E27)/E27 -> 0.25546904 | W27: =(+E27-F27)/F27 -> -0.086382114 | X27: =(+F27-G27)/G27 -> 0.13669619
A28: Total current liabilities | B28: =SUM(B23:B27) -> 9028 | C28: =SUM(C23:C27) -> 9064 | D28: =SUM(D23:D27) -> 8061 | E28: =SUM(E23:E27) -> 7875 | F28: =SUM(F23:F27) -> 7503 | G28: =SUM(G23:G27) -> 10154 | J28: =+B28/B$21 -> 0.099742578 | K28: =+C28/C$21 -> 0.097051202 | L28: =+D28/D$21 -> 0.08074727 | M28: =+E28/E$21 -> 0.077624446 | N28: =+F28/F$21 -> 0.07252008 | O28: =+G28/G$21 -> 0.084551844 | R28: =RATE(5,0,-G28,B28) -> -0.023233226 | S28: =AVERAGE(T28:X28) -> -0.013485134 | T28: =(+B28-C28)/C28 -> -0.0039717564 | U28: =(+C28-D28)/D28 -> 0.12442625 | V28: =(+D28-E28)/E28 -> 0.023619048 | W28: =(+E28-F28)/F28 -> 0.049580168 | X28: =(+F28-G28)/G28 -> -0.26107938
A29: Long-term debt | B29: 19233 | C29: 21061 | D29: 28070 | E29: 28216 | F29: 30770 | G29: 28308 | J29: =+B29/B$21 -> 0.21248881 | K29: =+C29/C$21 -> 0.22550699 | L29: =+D29/D$21 -> 0.281178 | M29: =+E29/E$21 -> 0.27812716 | N29: =+F29/F$21 -> 0.29740675 | O29: =+G29/G$21 -> 0.23571928 | R29: =RATE(5,0,-G29,B29) -> -0.074391 | S29: =AVERAGE(T29:X29) -> -0.06753962 | T29: =(+B29-C29)/C29 -> -0.086795499 | U29: =(+C29-D29)/D29 -> -0.24969719 | V29: =(+D29-E29)/E29 -> -0.0051743692 | W29: =(+E29-F29)/F29 -> -0.083002925 | X29: =(+F29-G29)/G29 -> 0.086971881
A30: LT operating lease liabilities | B30: =+B181 -> 585 | C30: =+C181 -> 484 | D30: =+D181 -> 475 | E30: =+E181 -> 454 | F30: =+F181 -> 0 | G30: =+G181 -> 0
A31: Other non-current liabilities (see detail) | B31: =+B219 -> 12797 | C31: =+C219 -> 13333 | D31: =+D219 -> 12981 | E31: =+E219 -> 13156 | F31: =+F219 -> 13410 | G31: =+G219 -> 15554 | J31: =+B31/B$21 -> 0.14138301 | K31: =+C31/C$21 -> 0.14276078 | L31: =+D31/D$21 -> 0.13003105 | M31: =+E31/E$21 -> 0.12967965 | N31: =+F31/F$21 -> 0.12961406 | O31: =+G31/G$21 -> 0.12951737 | R31: =RATE(5,0,-G31,B31) -> -0.038269886 | S31: =AVERAGE(T31:X31) -> -0.036633962 | T31: =(+B31-C31)/C31 -> -0.040201005 | U31: =(+C31-D31)/D31 -> 0.027116555 | V31: =(+D31-E31)/E31 -> -0.013301915 | W31: =(+E31-F31)/F31 -> -0.018941089 | X31: =(+F31-G31)/G31 -> -0.13784236
A32: Total liabilities | B32: =SUM(B28:B31) -> 41643 | C32: =SUM(C28:C31) -> 43942 | D32: =SUM(D28:D31) -> 49587 | E32: =SUM(E28:E31) -> 49701 | F32: =SUM(F28:F31) -> 51683 | G32: =SUM(G28:G31) -> 54016 | J32: =+B32/B$21 -> 0.46007756 | K32: =+C32/C$21 -> 0.47050132 | L32: =+D32/D$21 -> 0.49671441 | M32: =+E32/E$21 -> 0.48990636 | N32: =+F32/F$21 -> 0.49954089 | O32: =+G32/G$21 -> 0.4497885 | R32: =RATE(5,0,-G32,B32) -> -0.050699045 | S32: =AVERAGE(T32:X32) -> -0.049998615 | T32: =(+B32-C32)/C32 -> -0.052318966 | U32: =(+C32-D32)/D32 -> -0.11384032 | V32: =(+D32-E32)/E32 -> -0.0022937164 | W32: =(+E32-F32)/F32 -> -0.038349167 | X32: =(+F32-G32)/G32 -> -0.043190906
A33: Redeemable Non-controlling interest | B33: 40 | C33: 4 | D33: 0 | E33: 0 | F33: 3 | G33: 6 | J33: =+B33/B$21 -> 0.00044192547 | K33: =+C33/C$21 -> 4.2829304e-05 | L33: =+D33/D$21 -> 0 | M33: =+E33/E$21 -> 0 | N33: =+F33/F$21 -> 2.8996433e-05 | O33: =+G33/G$21 -> 4.9961696e-05 | R33: =RATE(5,0,-G33,B33) -> 0.46144255 | S33: =AVERAGE(T33:X33) -> 2.5 | T33: =(+B33-C33)/C33 -> 9 | W33: =(+E33-F33)/F33 -> -1 | X33: =(+F33-G33)/G33 -> -0.5
A34: Total Equity | B34: =+B227 -> 48830 | C34: =+C227 -> 49448 | D34: =+D227 -> 50243 | E34: =+E227 -> 51749 | F34: =+F227 -> 51775 | G34: =+G227 -> 66070 | J34: =+B34/B$21 -> 0.53948052 | K34: =+C34/C$21 -> 0.52945585 | L34: =+D34/D$21 -> 0.50328559 | M34: =+E34/E$21 -> 0.51009364 | N34: =+F34/F$21 -> 0.50043011 | O34: =+G34/G$21 -> 0.55016154 | R34: =RATE(5,0,-G34,B34) -> -0.05868174 | S34: =AVERAGE(T34:X34) -> -0.054857339 | T34: =(+B34-C34)/C34 -> -0.012497978 | U34: =(+C34-D34)/D34 -> -0.0158231 | V34: =(+D34-E34)/E34 -> -0.029102012 | W34: =(+E34-F34)/F34 -> -0.00050217286 | X34: =(+F34-G34)/G34 -> -0.21636143
A35: Total Liabilities and Equity | B35: =+B34+B33+B32 -> 90513 | C35: =+C34+C33+C32 -> 93394 | D35: =+D34+D33+D32 -> 99830 | E35: =+E34+E33+E32 -> 101450 | F35: =+F34+F33+F32 -> 103461 | G35: =+G34+G33+G32 -> 120092 | J35: =+B35/B$21 -> 1 | K35: =+C35/C$21 -> 1 | L35: =+D35/D$21 -> 1 | M35: =+E35/E$21 -> 1 | N35: =+F35/F$21 -> 1 | O35: =+G35/G$21 -> 1 | R35: =RATE(5,0,-G35,B35) -> -0.054983533 | S35: =AVERAGE(T35:X35) -> -0.053841726 | T35: =(+B35-C35)/C35 -> -0.030847806 | U35: =(+C35-D35)/D35 -> -0.064469598 | V35: =(+D35-E35)/E35 -> -0.015968457 | W35: =(+E35-F35)/F35 -> -0.019437276 | X35: =(+F35-G35)/G35 -> -0.13848549
B36: =+B35-B21 -> 0 | C36: =+C35-C21 -> 0 | D36: =+D35-D21 -> 0 | E36: =+E35-E21 -> 0 | F36: =+F35-F21 -> 0 | G36: =+G35-G21 -> 0
A37: Shares issued | B37: 1243 | C37: 1235 | D37: 1228 | E37: 1224 | F37: 1224 | G37: 1221
A38: Treasury Shares | B38: -18 | C38: -11 | D38: -5 | E38: -3 | F38: -4 | G38: -2
A39: Shares Outstanding | B39: =+B37+B38 -> 1225 | C39: =+C37+C38 -> 1224 | D39: =+D37+D38 -> 1223 | E39: =+E37+E38 -> 1221 | F39: =+F37+F38 -> 1220 | G39: =+G37+G38 -> 1219
A40: Stock price at next 2/28 (60 days after FYE) | B40: 38.13 | C40: 39.22 | D40: 36.38 | E40: 24.77 | F40: 33.19 | G40: 67.14
A41: Market Value of Equity | B41: =+B39*B40 -> 46709.25 | C41: =+C39*C40 -> 48005.28 | D41: =+D39*D40 -> 44492.74 | E41: =+E39*E40 -> 30244.17 | F41: =+F39*F40 -> 40491.8 | G41: =+G39*G40 -> 81843.66
A43: =+A1 -> Kraft Heinz Company | B43: Reclassified
A44: Summary Changes in Equity
A45: =+A3 -> in millions except per share data | F45: Late filing | G45: Restated
A46: =+A4 -> Fiscal Year ended 12/31: | B46: 2022 | C46: 2021 | D46: 2020 | E46: 2019 | F46: 2018 | G46: 2017 | H46: Aggregate
A47: Net Income - As Reported | B47: =+'As Reported'!B68 -> 2368 | C47: =+'As Reported'!C68 -> 1024 | D47: =+'As Reported'!D68 -> 361 | E47: =+'As Reported'!E68 -> 1933 | F47: =+'As Reported'!F68 -> -10254 | G47: =+'As Reported'!G68 -> 10932 | H47: =SUM(B47:G47) -> 6364
A48: Other comprehensive income | B48: -993 | C48: 149 | D48: -78 | E48: -72 | F48: -903 | G48: 581 | H48: =SUM(B48:G48) -> -1316
A49: Comprehensive Income affecting equity | B49: =SUM(B47:B48) -> 1375 | C49: =SUM(C47:C48) -> 1173 | D49: =SUM(D47:D48) -> 283 | E49: =SUM(E47:E48) -> 1861 | F49: =SUM(F47:F48) -> -11157 | G49: =SUM(G47:G48) -> 11513 | H49: =SUM(B49:G49) -> 5048
A50: Dividends | B50: -1972 | C50: -1979 | D50: -1973 | E50: -1959 | F50: -3048 | G50: -2988 | H50: =SUM(B50:G50) -> -13919
A51: Other activity (squeeze) | B51: =+B52-SUM(B49:B50) -> -21 | C51: =+C52-SUM(C49:C50) -> 11 | D51: =+D52-SUM(D49:D50) -> 184 | E51: =+E52-SUM(E49:E50) -> 72 | F51: =+F52-SUM(F49:F50) -> -90 | G51: =+G52-SUM(G49:G50) -> 85 | H51: =SUM(B51:G51) -> 241
A52: Change in equity | B52: =+B54-B53 -> -618 | C52: =+C54-C53 -> -795 | D52: =+D54-D53 -> -1506 | E52: =+E54-E53 -> -26 | F52: =+F54-F53 -> -14295 | G52: =+G54-G53 -> 8610 | H52: =SUM(B52:G52) -> -8630
A53: Beginning Equity | B53: =+C54 -> 49448 | C53: =+D54 -> 50243 | D53: =+E54 -> 51749 | E53: =+F54 -> 51775 | F53: =+G54 -> 66070 | G53: 57460 | H53: =+G53 -> 57460
A54: Ending Equity | B54: =+B34 -> 48830 | C54: =+C34 -> 49448 | D54: =+D34 -> 50243 | E54: =+E34 -> 51749 | F54: =+F34 -> 51775 | G54: =+G34 -> 66070 | H54: =++H52+H53 -> 48830
A56: =+A1 -> Kraft Heinz Company | B56: =+B1 -> Reclassified | J56: =+B56 -> Reclassified | R56: =+B56 -> Reclassified
A57: Consolidated Income Statements | J57: Common Size on Net Sales | R57: Horizontal(Growth) Analysis
A58: =+A3 -> in millions except per share data | F58: Late filing | G58: Restated | O58: Restated | R58: 5 Year | S58: Annual | T58: 2021 to | U58: 2020 to | V58: 2019 to | W58: 2018 to | X58: 2017 to
A59: =+A4 -> Fiscal Year ended 12/31: | B59: 2022 | C59: 2021 | D59: 2020 | E59: 2019 | F59: 2018 | G59: 2017 | H59: Aggregate | J59: 2022 | K59: 2021 | L59: 2020 | M59: 2019 | N59: 2018 | O59: 2017 | P59: Aggregate | R59: CAGR | S59: Average | T59: 2022 | U59: 2021 | V59: 2020 | W59: 2019 | X59: 2018
A60: Net sales | B60: 26485 | C60: 26042 | D60: 26185 | E60: 24977 | F60: 26268 | G60: 26076 | H60: =SUM(B60:G60) -> 156033 | J60: =+B60/B$60 -> 1 | K60: =+C60/C$60 -> 1 | L60: =+D60/D$60 -> 1 | M60: =+E60/E$60 -> 1 | N60: =+F60/F$60 -> 1 | O60: =+G60/G$60 -> 1 | P60: =+H60/H$60 -> 1 | R60: =RATE(5,0,-G60,B60) -> 0.0031174861 | S60: =AVERAGE(T60:X60) -> 0.0036260354 | T60: =(+B60-C60)/C60 -> 0.017010982 | U60: =(+C60-D60)/D60 -> -0.0054611419 | V60: =(+D60-E60)/E60 -> 0.048364495 | W60: =(+E60-F60)/F60 -> -0.049147251 | X60: =(+F60-G60)/G60 -> 0.0073630925
A61: Cost of goods sold | B61: 18363 | C61: 17360 | D61: 17008 | E61: 16830 | F61: 17347 | G61: 17043 | H61: =SUM(B61:G61) -> 103951 | J61: =+B61/B$60 -> 0.69333585 | K61: =+C61/C$60 -> 0.66661547 | L61: =+D61/D$60 -> 0.64953217 | M61: =+E61/E$60 -> 0.67381991 | N61: =+F61/F$60 -> 0.66038526 | O61: =+G61/G$60 -> 0.65358951 | P61: =+H61/H$60 -> 0.66621163 | R61: =RATE(5,0,-G61,B61) -> 0.015031495 | S61: =AVERAGE(T61:X61) -> 0.015416561 | T61: =(+B61-C61)/C61 -> 0.057776498 | U61: =(+C61-D61)/D61 -> 0.020696143 | V61: =(+D61-E61)/E61 -> 0.010576352 | W61: =(+E61-F61)/F61 -> -0.029803424 | X61: =(+F61-G61)/G61 -> 0.017837235
A62: Gross profit | B62: =+B60-B61 -> 8122 | C62: =+C60-C61 -> 8682 | D62: =+D60-D61 -> 9177 | E62: =+E60-E61 -> 8147 | F62: =+F60-F61 -> 8921 | G62: =+G60-G61 -> 9033 | H62: =SUM(B62:G62) -> 52082 | J62: =+B62/B$60 -> 0.30666415 | K62: =+C62/C$60 -> 0.33338453 | L62: =+D62/D$60 -> 0.35046783 | M62: =+E62/E$60 -> 0.32618009 | N62: =+F62/F$60 -> 0.33961474 | O62: =+G62/G$60 -> 0.34641049 | P62: =+H62/H$60 -> 0.33378837 | R62: =RATE(5,0,-G62,B62) -> -0.021037187 | S62: =AVERAGE(T62:X62) -> -0.018234823 | T62: =(+B62-C62)/C62 -> -0.064501267 | U62: =(+C62-D62)/D62 -> -0.053939196 | V62: =(+D62-E62)/E62 -> 0.12642691 | W62: =(+E62-F62)/F62 -> -0.086761574 | X62: =(+F62-G62)/G62 -> -0.012398982
A63: SG&A (see detail) | B63: =+B232 -> 2503 | C63: =+C232 -> 2409 | D63: =+D232 -> 2461 | E63: =+E232 -> 1966 | F63: =+F232 -> 1941 | G63: =+G232 -> 1719 | H63: =SUM(B63:G63) -> 12999 | J63: =+B63/B$60 -> 0.094506324 | K63: =+C63/C$60 -> 0.092504416 | L63: =+D63/D$60 -> 0.093985106 | M63: =+E63/E$60 -> 0.078712415 | N63: =+F63/F$60 -> 0.073892188 | O63: =+G63/G$60 -> 0.065922688 | P63: =+H63/H$60 -> 0.0833093 | R63: =RATE(5,0,-G63,B63) -> 0.07804526 | S63: =AVERAGE(T63:X63) -> 0.082339159 | T63: =(+B63-C63)/C63 -> 0.03902034 | U63: =(+C63-D63)/D63 -> -0.021129622 | V63: =(+D63-E63)/E63 -> 0.25178026 | W63: =(+E63-F63)/F63 -> 0.012879959 | X63: =(+F63-G63)/G63 -> 0.12914485
A64: Advertising & Promotion | B64: =+B167 -> 945 | C64: =+C167 -> 1039 | D64: =+D167 -> 1070 | E64: =+E167 -> 1100 | F64: =+F167 -> 1140 | G64: =+G167 -> 1115 | H64: =SUM(B64:G64) -> 6409 | J64: =+B64/B$60 -> 0.035680574 | K64: =+C64/C$60 -> 0.039897089 | L64: =+D64/D$60 -> 0.04086309 | M64: =+E64/E$60 -> 0.044040517 | N64: =+F64/F$60 -> 0.043398812 | O64: =+G64/G$60 -> 0.042759626 | P64: =+H64/H$60 -> 0.041074644
A65: Research & Devlopment | B65: =+B168 -> 127 | C65: =+C168 -> 140 | D65: =+D168 -> 119 | E65: =+E168 -> 112 | F65: =+F168 -> 109 | G65: =+G168 -> 93 | H65: =SUM(B65:G65) -> 700 | J65: =+B65/B$60 -> 0.0047951671 | K65: =+C65/C$60 -> 0.0053759312 | L65: =+D65/D$60 -> 0.0045445866 | M65: =+E65/E$60 -> 0.0044841254 | N65: =+F65/F$60 -> 0.0041495356 | O65: =+G65/G$60 -> 0.0035664979 | P65: =+H65/H$60 -> 0.0044862305
A66: Goodwill impairment | B66: 444 | C66: 318 | D66: 2343 | E66: 1197 | F66: 7008 | G66: 0 | H66: =SUM(B66:G66) -> 11310 | J66: =+B66/B$60 -> 0.016764206 | K66: =+C66/C$60 -> 0.012211044 | L66: =+D66/D$60 -> 0.089478709 | M66: =+E66/E$60 -> 0.04792409 | N66: =+F66/F$60 -> 0.26678849 | O66: =+G66/G$60 -> 0 | P66: =+H66/H$60 -> 0.072484667 | S66: =AVERAGE(T66:X66) -> -0.084962969 | T66: =(+B66-C66)/C66 -> 0.39622642 | U66: =(+C66-D66)/D66 -> -0.86427657 | V66: =(+D66-E66)/E66 -> 0.95739348 | W66: =(+E66-F66)/F66 -> -0.82919521
A67: Intangible impairment | B67: 469 | C67: 1316 | D67: 1056 | E67: 702 | F67: 8928 | G67: 49 | H67: =SUM(B67:G67) -> 12520 | J67: =+B67/B$60 -> 0.017708137 | K67: =+C67/C$60 -> 0.050533753 | L67: =+D67/D$60 -> 0.040328432 | M67: =+E67/E$60 -> 0.028105857 | N67: =+F67/F$60 -> 0.33988122 | O67: =+G67/G$60 -> 0.0018791226 | P67: =+H67/H$60 -> 0.080239437 | R67: =RATE(5,0,-G67,B67) -> 0.57106934 | S67: =AVERAGE(T67:X67) -> 36.077916 | T67: =(+B67-C67)/C67 -> -0.64361702 | U67: =(+C67-D67)/D67 -> 0.24621212 | V67: =(+D67-E67)/E67 -> 0.5042735 | W67: =(+E67-F67)/F67 -> -0.92137097 | X67: =(+F67-G67)/G67 -> 181.20408
A68: Operating expenses | B68: =SUM(B63:B67) -> 4488 | C68: =SUM(C63:C67) -> 5222 | D68: =SUM(D63:D67) -> 7049 | E68: =SUM(E63:E67) -> 5077 | F68: =SUM(F63:F67) -> 19126 | G68: =SUM(G63:G67) -> 2976 | H68: =SUM(B68:G68) -> 43938 | J68: =+B68/B$60 -> 0.16945441 | K68: =+C68/C$60 -> 0.20052223 | L68: =+D68/D$60 -> 0.26919992 | M68: =+E68/E$60 -> 0.20326701 | N68: =+F68/F$60 -> 0.72811025 | O68: =+G68/G$60 -> 0.11412793 | P68: =+H68/H$60 -> 0.28159428 | R68: =RATE(5,0,-G68,B68) -> 0.08563537 | S68: =AVERAGE(T68:X68) -> 0.93617419 | T68: =(+B68-C68)/C68 -> -0.14055917 | U68: =(+C68-D68)/D68 -> -0.2591857 | V68: =(+D68-E68)/E68 -> 0.38841836 | W68: =(+E68-F68)/F68 -> -0.73454983 | X68: =(+F68-G68)/G68 -> 5.4267473
A69: Operating income (loss) | B69: =+B62-B68 -> 3634 | C69: =+C62-C68 -> 3460 | D69: =+D62-D68 -> 2128 | E69: =+E62-E68 -> 3070 | F69: =+F62-F68 -> -10205 | G69: =+G62-G68 -> 6057 | H69: =SUM(B69:G69) -> 8144 | J69: =+B69/B$60 -> 0.13720974 | K69: =+C69/C$60 -> 0.1328623 | L69: =+D69/D$60 -> 0.081267901 | M69: =+E69/E$60 -> 0.12291308 | N69: =+F69/F$60 -> -0.38849551 | O69: =+G69/G$60 -> 0.23228256 | P69: =+H69/H$60 -> 0.052194087 | R69: =RATE(5,0,-G69,B69) -> -0.097129486 | S69: =AVERAGE(T69:X69) -> -0.72325438 | T69: =(+B69-C69)/C69 -> 0.050289017 | U69: =(+C69-D69)/D69 -> 0.62593985 | V69: =(+D69-E69)/E69 -> -0.30684039 | W69: =(+E69-F69)/F69 -> -1.3008329 | X69: =(+F69-G69)/G69 -> -2.6848275
A70: Interest expense | B70: 921 | C70: 2047 | D70: 1394 | E70: 1361 | F70: 1284 | G70: 1234 | H70: =SUM(B70:G70) -> 8241 | J70: =+B70/B$60 -> 0.034774401 | K70: =+C70/C$60 -> 0.078603794 | L70: =+D70/D$60 -> 0.053236586 | M70: =+E70/E$60 -> 0.054490131 | N70: =+F70/F$60 -> 0.048880767 | O70: =+G70/G$60 -> 0.047323209 | P70: =+H70/H$60 -> 0.052815751 | R70: =RATE(5,0,-G70,B70) -> -0.056832355 | S70: =AVERAGE(T70:X70) -> 0.008619448 | T70: =(+B70-C70)/C70 -> -0.55007328 | U70: =(+C70-D70)/D70 -> 0.46843615 | V70: =(+D70-E70)/E70 -> 0.024246877 | W70: =(+E70-F70)/F70 -> 0.059968847 | X70: =(+F70-G70)/G70 -> 0.040518639
A71: Other expense (income) | B71: -253 | C71: -295 | D71: -296 | E71: -952 | F71: -168 | G71: -627 | H71: =SUM(B71:G71) -> -2591 | J71: =+B71/B$60 -> -0.0095525769 | K71: =+C71/C$60 -> -0.011327855 | L71: =+D71/D$60 -> -0.011304182 | M71: =+E71/E$60 -> -0.038115066 | N71: =+F71/F$60 -> -0.0063956144 | O71: =+G71/G$60 -> -0.024045099 | P71: =+H71/H$60 -> -0.016605462 | R71: =RATE(5,0,-G71,B71) -> -0.16599127 | S71: =AVERAGE(T71:X71) -> 0.61995647 | T71: =(+B71-C71)/C71 -> -0.14237288 | U71: =(+C71-D71)/D71 -> -0.0033783784 | V71: =(+D71-E71)/E71 -> -0.68907563 | W71: =(+E71-F71)/F71 -> 4.6666667 | X71: =(+F71-G71)/G71 -> -0.73205742
A72: Pretax Income | B72: =+B69-B70-B71 -> 2966 | C72: =+C69-C70-C71 -> 1708 | D72: =+D69-D70-D71 -> 1030 | E72: =+E69-E70-E71 -> 2661 | F72: =+F69-F70-F71 -> -11321 | G72: =+G69-G70-G71 -> 5450 | H72: =SUM(B72:G72) -> 2494 | J72: =+B72/B$60 -> 0.11198792 | K72: =+C72/C$60 -> 0.06558636 | L72: =+D72/D$60 -> 0.039335497 | M72: =+E72/E$60 -> 0.10653801 | N72: =+F72/F$60 -> -0.43098066 | O72: =+G72/G$60 -> 0.20900445 | P72: =+H72/H$60 -> 0.015983798 | R72: =RATE(5,0,-G72,B72) -> -0.11456858 | S72: =AVERAGE(T72:X72) -> -0.70608774 | T72: =(+B72-C72)/C72 -> 0.73653396 | U72: =(+C72-D72)/D72 -> 0.65825243 | V72: =(+D72-E72)/E72 -> -0.61292747 | W72: =(+E72-F72)/F72 -> -1.2350499 | X72: =(+F72-G72)/G72 -> -3.0772477
A73: Tax provision | B73: 598 | C73: 684 | D73: 669 | E73: 728 | F73: -1067 | G73: -5482 | H73: =SUM(B73:G73) -> -3870 | J73: =+B73/B$60 -> 0.022578818 | K73: =+C73/C$60 -> 0.026265264 | L73: =+D73/D$60 -> 0.025548978 | M73: =+E73/E$60 -> 0.029146815 | N73: =+F73/F$60 -> -0.040619765 | O73: =+G73/G$60 -> -0.21023163 | P73: =+H73/H$60 -> -0.024802446 | R73: =RATE(5,0,G73,B73) -> -0.35797427 | S73: =AVERAGE(T73:X73) -> -0.53440064 | T73: =(+B73-C73)/C73 -> -0.12573099 | U73: =(+C73-D73)/D73 -> 0.022421525 | V73: =(+D73-E73)/E73 -> -0.081043956 | W73: =(+E73-F73)/F73 -> -1.6822868 | X73: =(+F73-G73)/G73 -> -0.80536301
A74: Net Income (loss) | B74: =+B72-B73 -> 2368 | C74: =+C72-C73 -> 1024 | D74: =+D72-D73 -> 361 | E74: =+E72-E73 -> 1933 | F74: =+F72-F73 -> -10254 | G74: =+G72-G73 -> 10932 | H74: =SUM(B74:G74) -> 6364 | J74: =+B74/B$60 -> 0.089409099 | K74: =+C74/C$60 -> 0.039321097 | L74: =+D74/D$60 -> 0.013786519 | M74: =+E74/E$60 -> 0.0773912 | N74: =+F74/F$60 -> -0.3903609 | O74: =+G74/G$60 -> 0.41923608 | P74: =+H74/H$60 -> 0.040786244 | R74: =RATE(5,0,-G74,B74) -> -0.26356162 | S74: =AVERAGE(T74:X74) -> -0.15813412 | T74: =(+B74-C74)/C74 -> 1.3125 | U74: =(+C74-D74)/D74 -> 1.8365651 | V74: =(+D74-E74)/E74 -> -0.81324366 | W74: =(+E74-F74)/F74 -> -1.1885118 | X74: =(+F74-G74)/G74 -> -1.9379802
A75: Noncontrolling interest | B75: 5 | C75: 12 | D75: 5 | E75: -2 | F75: -62 | G75: -9 | H75: =SUM(B75:G75) -> -51 | J75: =+B75/B$60 -> 0.00018878611 | K75: =+C75/C$60 -> 0.0004607941 | L75: =+D75/D$60 -> 0.00019094902 | M75: =+E75/E$60 -> -8.0073668e-05 | N75: =+F75/F$60 -> -0.0023602863 | O75: =+G75/G$60 -> -0.00034514496 | P75: =+H75/H$60 -> -0.00032685393 | R75: =RATE(5,0,G75,B75) -> -0.11091046 | S75: =AVERAGE(T75:X75) -> 0.44756272 | T75: =(+B75-C75)/C75 -> -0.58333333 | U75: =(+C75-D75)/D75 -> 1.4 | V75: =(+D75-E75)/E75 -> -3.5 | W75: =(+E75-F75)/F75 -> -0.96774194 | X75: =(+F75-G75)/G75 -> 5.8888889
A76: Net income (Loss)-Kraft Heinz | B76: =+B74-B75 -> 2363 | C76: =+C74-C75 -> 1012 | D76: =+D74-D75 -> 356 | E76: =+E74-E75 -> 1935 | F76: =+F74-F75 -> -10192 | G76: =+G74-G75 -> 10941 | H76: =SUM(B76:G76) -> 6415 | J76: =+B76/B$60 -> 0.089220313 | K76: =+C76/C$60 -> 0.038860303 | L76: =+D76/D$60 -> 0.01359557 | M76: =+E76/E$60 -> 0.077471274 | N76: =+F76/F$60 -> -0.38800061 | O76: =+G76/G$60 -> 0.41958122 | P76: =+H76/H$60 -> 0.041113098 | R76: =RATE(5,0,-G76,B76) -> -0.26399402 | S76: =AVERAGE(T76:X76) -> -0.1519481 | T76: =(+B76-C76)/C76 -> 1.3349802 | U76: =(+C76-D76)/D76 -> 1.8426966 | V76: =(+D76-E76)/E76 -> -0.81602067 | W76: =(+E76-F76)/F76 -> -1.1898548 | X76: =(+F76-G76)/G76 -> -1.9315419
B77: =+B76-'As Reported'!B70 -> 0 | C77: =+C76-'As Reported'!C70 -> 0 | D77: =+D76-'As Reported'!D70 -> 0 | E77: =+E76-'As Reported'!E70 -> 0 | F77: =+F76-'As Reported'!F70 -> 0 | G77: =+G76-'As Reported'!G70 -> 0
A78: Diluted W. Ave shares outstanding (notes) | B78: 1235 | C78: 1236 | D78: 1228 | E78: 1224 | F78: 1219 | G78: 1228 | R78: =RATE(5,0,-G78,B78) -> 0.0011374745 | S78: =AVERAGE(T78:X78) -> 0.0011492606 | T78: =(+B78-C78)/C78 -> -0.00080906149 | U78: =(+C78-D78)/D78 -> 0.006514658 | V78: =(+D78-E78)/E78 -> 0.0032679739 | W78: =(+E78-F78)/F78 -> 0.0041017227 | X78: =(+F78-G78)/G78 -> -0.0073289902
A79: Diluted EPS | B79: =+B76/B78 -> 1.9133603 | C79: =+C76/C78 -> 0.81877023 | D79: =+D76/D78 -> 0.28990228 | E79: =+E76/E78 -> 1.5808824 | F79: =+F76/F78 -> -8.3609516 | G79: =+G76/G78 -> 8.9096091 | R79: =RATE(5,0,-G79,B79) -> -0.26483026 | S79: =AVERAGE(T79:X79) -> -0.15659011 | T79: =(+B79-C79)/C79 -> 1.3368709 | U79: =(+C79-D79)/D79 -> 1.8242973 | V79: =(+D79-E79)/E79 -> -0.81661995 | W79: =(+E79-F79)/F79 -> -1.1890792 | X79: =(+F79-G79)/G79 -> -1.9384196
A80: Dividends per share (Equity Stmt)) | B80: 1.6 | C80: 1.6 | D80: 1.6 | E80: 1.6 | F80: 2.5 | G80: 2.45 | R80: =RATE(5,0,-G80,B80) -> -0.0816869 | S80: =AVERAGE(T80:X80) -> -0.067918367 | T80: =(+B80-C80)/C80 -> 0 | U80: =(+C80-D80)/D80 -> 0 | V80: =(+D80-E80)/E80 -> 0 | W80: =(+E80-F80)/F80 -> -0.36 | X80: =(+F80-G80)/G80 -> 0.020408163
A82: Effective Tax Rate | B82: =+B73/B72 -> 0.20161834 | C82: =+C73/C72 -> 0.40046838 | D82: =+D73/D72 -> 0.64951456 | E82: =+E73/E72 -> 0.27358136 | F82: =+F73/F72 -> 0.094249625 | G82: =+G73/G72 -> -1.0058716 | H82: =+H73/H72 -> -1.5517241
A84: Non-GAAP Measurements:
A85: Net Income | B85: =+B76 -> 2363 | C85: =+C76 -> 1012 | D85: =+D76 -> 356 | E85: =+E76 -> 1935 | F85: =+F76 -> -10192 | G85: =+G76 -> 10941
A86: Add back Income Taxes | B86: =+B73 -> 598 | C86: =+C73 -> 684 | D86: =+D73 -> 669 | E86: =+E73 -> 728 | F86: =+F73 -> -1067 | G86: =+G73 -> -5482
A87: Add back Interest Expense | B87: =+B70 -> 921 | C87: =+C70 -> 2047 | D87: =+D70 -> 1394 | E87: =+E70 -> 1361 | F87: =+F70 -> 1284 | G87: =+G70 -> 1234
A88: EBIT | B88: =SUM(B85:B87) -> 3882 | C88: =SUM(C85:C87) -> 3743 | D88: =SUM(D85:D87) -> 2419 | E88: =SUM(E85:E87) -> 4024 | F88: =SUM(F85:F87) -> -9975 | G88: =SUM(G85:G87) -> 6693
A89: Depreciation and amortization | B89: =+B102 -> 933 | C89: =+C102 -> 910 | D89: =+D102 -> 969 | E89: =+E102 -> 994 | F89: =+F102 -> 983 | G89: =+G102 -> 1031
A90: EBITDA | B90: =+B89+B88 -> 4815 | C90: =+C89+C88 -> 4653 | D90: =+D89+D88 -> 3388 | E90: =+E89+E88 -> 5018 | F90: =+F89+F88 -> -8992 | G90: =+G89+G88 -> 7724
A92: Operating Income | B92: =+B69 -> 3634 | C92: =+C69 -> 3460 | D92: =+D69 -> 2128 | E92: =+E69 -> 3070 | F92: =+F69 -> -10205 | G92: =+G69 -> 6057
A93: Other Income | B93: =-B71 -> 253 | C93: =-C71 -> 295 | D93: =-D71 -> 296 | E93: =-E71 -> 952 | F93: =-F71 -> 168 | G93: =-G71 -> 627
A94: Noncontrolling interest | B94: =-B75 -> -5 | C94: =-C75 -> -12 | D94: =-D75 -> -5 | E94: =-E75 -> 2 | F94: =-F75 -> 62 | G94: =-G75 -> 9
A95: EBIT | B95: =+SUM(B92:B94) -> 3882 | C95: =+SUM(C92:C94) -> 3743 | D95: =+SUM(D92:D94) -> 2419 | E95: =+SUM(E92:E94) -> 4024 | F95: =+SUM(F92:F94) -> -9975 | G95: =+SUM(G92:G94) -> 6693
A97: =+A1 -> Kraft Heinz Company | B97: =+B1 -> Reclassified | J97: =+B97 -> Reclassified | R97: =+B97 -> Reclassified
A98: Consolidated Cash Flows | J98: Common Size on Operating Cash Flows | R98: Horizontal(Growth) Analysis
A99: =+A3 -> in millions except per share data | F99: Late filing | G99: Restated | O99: Restated | R99: 5 Year | S99: Annual | T99: 2021 to | U99: 2020 to | V99: 2019 to | W99: 2018 to | X99: 2017 to
A100: =+A4 -> Fiscal Year ended 12/31: | B100: 2022 | C100: 2021 | D100: 2020 | E100: 2019 | F100: 2018 | G100: 2017 | H100: Aggregate | J100: 2022 | K100: 2021 | L100: 2020 | M100: 2019 | N100: 2018 | O100: 2017 | R100: CAGR | S100: Average | T100: 2022 | U100: 2021 | V100: 2020 | W100: 2019 | X100: 2018
A101: Net income (loss) - as reported | B101: =+'As Reported'!B68 -> 2368 | C101: =+'As Reported'!C68 -> 1024 | D101: =+'As Reported'!D68 -> 361 | E101: =+'As Reported'!E68 -> 1933 | F101: =+'As Reported'!F68 -> -10254 | G101: =+'As Reported'!G68 -> 10932 | H101: =SUM(B101:G101) -> 6364 | R101: =RATE(5,0,-G101,B101) -> -0.26356162 | S101: =AVERAGE(T101:X101) -> -0.15813412 | T101: =(+B101-C101)/C101 -> 1.3125 | U101: =(+C101-D101)/D101 -> 1.8365651 | V101: =(+D101-E101)/E101 -> -0.81324366 | W101: =(+E101-F101)/F101 -> -1.1885118 | X101: =(+F101-G101)/G101 -> -1.9379802
A102: Depreciation & amortization | B102: 933 | C102: 910 | D102: 969 | E102: 994 | F102: 983 | G102: 1031 | H102: =SUM(B102:G102) -> 5820 | R102: =RATE(5,0,-G102,B102) -> -0.019777661 | S102: =AVERAGE(T102:X102) -> -0.01922604 | T102: =(+B102-C102)/C102 -> 0.025274725 | U102: =(+C102-D102)/D102 -> -0.060887513 | V102: =(+D102-E102)/E102 -> -0.025150905 | W102: =(+E102-F102)/F102 -> 0.011190234 | X102: =(+F102-G102)/G102 -> -0.046556741
A103: Amortization of PRB | B103: -14 | C103: -7 | D103: -122 | E103: -306 | F103: -339 | G103: -328 | H103: =SUM(B103:G103) -> -1116 | R103: =RATE(5,0,-G103,B103) -> -0.46782945 | S103: =AVERAGE(T103:X103) -> -0.12154774 | T103: =(+B103-C103)/C103 -> 1 | U103: =(+C103-D103)/D103 -> -0.94262295 | V103: =(+D103-E103)/E103 -> -0.60130719 | W103: =(+E103-F103)/F103 -> -0.097345133 | X103: =(+F103-G103)/G103 -> 0.033536585
A104: Divestiture-related license income | B104: -56 | C104: -4 | D104: 0 | E104: 0 | F104: 0 | G104: 0 | H104: =SUM(B104:G104) -> -60 | R104: =RATE(5,0,-G104,B104) -> #NUM! | S104: =AVERAGE(T104:X104) -> #DIV/0! | T104: =(+B104-C104)/C104 -> 13 | U104: =(+C104-D104)/D104 -> #DIV/0! | V104: =(+D104-E104)/E104 -> #DIV/0! | W104: =(+E104-F104)/F104 -> #DIV/0! | X104: =(+F104-G104)/G104 -> #DIV/0!
A105: Stock-based compensation | B105: 148 | C105: 197 | D105: 156 | E105: 46 | F105: 33 | G105: 46 | H105: =SUM(B105:G105) -> 626 | R105: =RATE(5,0,-G105,B105) -> 0.26328336 | S105: =AVERAGE(T105:X105) -> 0.50334492 | T105: =(+B105-C105)/C105 -> -0.24873096 | U105: =(+C105-D105)/D105 -> 0.26282051 | V105: =(+D105-E105)/E105 -> 2.3913043 | W105: =(+E105-F105)/F105 -> 0.39393939 | X105: =(+F105-G105)/G105 -> -0.2826087
A106: Deferred income taxes | B106: -278 | C106: -1042 | D106: -343 | E106: -293 | F106: -1967 | G106: -6495 | H106: =SUM(B106:G106) -> -10418 | R106: =RATE(5,0,-G106,B106) -> -0.46753247 | S106: =AVERAGE(T106:X106) -> -0.014569977 | T106: =(+B106-C106)/C106 -> -0.73320537 | U106: =(+C106-D106)/D106 -> 2.0379009 | V106: =(+D106-E106)/E106 -> 0.17064846 | W106: =(+E106-F106)/F106 -> -0.8510422 | X106: =(+F106-G106)/G106 -> -0.69715166
...

Sheet Cash flow profile
A1: Kraft Heinz Company | B1: Reclassified | J1: =+B1 -> Reclassified | R1: =+B1 -> Reclassified
A2: Consolidated Balance Sheets | J2: Common Size on Total Assets | R2: Horizontal(Growth) Analysis
A3: in millions except per share data | F3: Late filing | G3: Restated | O3: Restated | R3: 5 Year | S3: Annual | T3: 2021 to | U3: 2020 to | V3: 2019 to | W3: 2018 to | X3: 2017 to
A4: Fiscal year ended 12/31: | B4: 2022 | C4: 2021 | D4: 2020 | E4: 2019 | F4: 2018 | G4: 2017 | J4: 2022 | K4: 2021 | L4: 2020 | M4: 2019 | N4: 2018 | O4: 2017 | R4: CAGR | S4: Average | T4: 2022 | U4: 2021 | V4: 2020 | W4: 2019 | X4: 2018
A5: Assets:
A6: Cash and equivalents | B6: 1040 | C6: 3445 | D6: 3417 | E6: 2279 | F6: 1130 | G6: 1629 | J6: =+B6/B$21 -> 0.011490062 | K6: =+C6/C$21 -> 0.036886738 | L6: =+D6/D$21 -> 0.034228188 | M6: =+E6/E$21 -> 0.022464268 | N6: =+F6/F$21 -> 0.01092199 | O6: =+G6/G$21 -> 0.0135646 | R6: =RATE(5,0,-G6,B6) -> -0.085839502 | S6: =AVERAGE(T6:X6) -> 0.10398284 | T6: =(+B6-C6)/C6 -> -0.69811321 | U6: =(+C6-D6)/D6 -> 0.0081943225 | V6: =(+D6-E6)/E6 -> 0.49934182 | W6: =(+E6-F6)/F6 -> 1.0168142 | X6: =(+F6-G6)/G6 -> -0.3063229
A7: Marketable Securities | B7: 0 | C7: 0 | D7: 0 | E7: 0 | F7: 0 | G7: 0
A8: Trade receivables | B8: 2120 | C8: 1957 | D8: 2063 | E8: 1973 | F8: 2129 | G8: 921 | J8: =+B8/B$21 -> 0.02342205 | K8: =+C8/C$21 -> 0.020954237 | L8: =+D8/D$21 -> 0.020665131 | M8: =+E8/E$21 -> 0.019448004 | N8: =+F8/F$21 -> 0.020577802 | O8: =+G8/G$21 -> 0.0076691203 | R8: =RATE(5,0,-G8,B8) -> 0.18144973 | S8: =AVERAGE(T8:X8) -> 0.26317381 | T8: =(+B8-C8)/C8 -> 0.083290751 | U8: =(+C8-D8)/D8 -> -0.051381483 | V8: =(+D8-E8)/E8 -> 0.045615813 | W8: =(+E8-F8)/F8 -> -0.073273837 | X8: =(+F8-G8)/G8 -> 1.3116178
A9: Inventories | B9: 3651 | C9: 2729 | D9: 2554 | E9: 2721 | F9: 2667 | G9: 2760 | J9: =+B9/B$21 -> 0.040336747 | K9: =+C9/C$21 -> 0.029220293 | L9: =+D9/D$21 -> 0.025583492 | M9: =+E9/E$21 -> 0.026821094 | N9: =+F9/F$21 -> 0.025777829 | O9: =+G9/G$21 -> 0.02298238 | R9: =RATE(5,0,-G9,B9) -> 0.057549125 | S9: =AVERAGE(T9:X9) -> 0.066309997 | T9: =(+B9-C9)/C9 -> 0.33785269 | U9: =(+C9-D9)/D9 -> 0.068519969 | V9: =(+D9-E9)/E9 -> -0.061374495 | W9: =(+E9-F9)/F9 -> 0.020247469 | X9: =(+F9-G9)/G9 -> -0.033695652
A10: Other current assets | B10: =+B240 -> 1086 | C10: =+C240 -> 863 | D10: =+D240 -> 2788 | E10: =+E240 -> 1124 | F10: =+F240 -> 3149 | G10: =+G240 -> 1891 | J10: =+B10/B$21 -> 0.011998276 | K10: =+C10/C$21 -> 0.0092404223 | L10: =+D10/D$21 -> 0.027927477 | M10: =+E10/E$21 -> 0.011079349 | N10: =+F10/F$21 -> 0.03043659 | O10: =+G10/G$21 -> 0.015746261 | R10: =RATE(5,0,-G10,B10) -> -0.10499047 | S10: =AVERAGE(T10:X10) -> 0.21411281 | T10: =(+B10-C10)/C10 -> 0.25840093 | U10: =(+C10-D10)/D10 -> -0.69045911 | V10: =(+D10-E10)/E10 -> 1.480427 | W10: =(+E10-F10)/F10 -> -0.64306129 | X10: =(+F10-G10)/G10 -> 0.66525648
A11: Total current assets | B11: =SUM(B6:B10) -> 7897 | C11: =SUM(C6:C10) -> 8994 | D11: =SUM(D6:D10) -> 10822 | E11: =SUM(E6:E10) -> 8097 | F11: =SUM(F6:F10) -> 9075 | G11: =SUM(G6:G10) -> 7201 | J11: =+B11/B$21 -> 0.087247136 | K11: =+C11/C$21 -> 0.09630169 | L11: =+D11/D$21 -> 0.10840429 | M11: =+E11/E$21 -> 0.079812716 | N11: =+F11/F$21 -> 0.087714211 | O11: =+G11/G$21 -> 0.059962362 | R11: =RATE(5,0,-G11,B11) -> 0.018623908 | S11: =AVERAGE(T11:X11) -> 0.039626412 | T11: =(+B11-C11)/C11 -> -0.1219702 | U11: =(+C11-D11)/D11 -> -0.16891517 | V11: =(+D11-E11)/E11 -> 0.3365444 | W11: =(+E11-F11)/F11 -> -0.1077686 | X11: =(+F11-G11)/G11 -> 0.26024163
A12: Land | B12: =+B218 -> 200 | C12: =+C218 -> 207 | D12: =+D218 -> 219 | E12: =+E218 -> 210 | F12: =+F218 -> 218 | G12: =+G218 -> 250 | J12: =+B12/B$21 -> 0.0022096273 | K12: =+C12/C$21 -> 0.0022164165 | L12: =+D12/D$21 -> 0.0021937293 | M12: =+E12/E$21 -> 0.0020699852 | N12: =+F12/F$21 -> 0.0021070742 | O12: =+G12/G$21 -> 0.0020817373 | R12: =RATE(5,0,-G12,B12) -> -0.0436475 | S12: =AVERAGE(T12:X12) -> -0.04209021 | T12: =(+B12-C12)/C12 -> -0.033816425 | U12: =(+C12-D12)/D12 -> -0.054794521 | V12: =(+D12-E12)/E12 -> 0.042857143 | W12: =(+E12-F12)/F12 -> -0.036697248 | X12: =(+F12-G12)/G12 -> -0.128
A13: Construction in progress | B13: =+B219 -> 1161 | C13: =+C219 -> 1002 | D13: =+D219 -> 792 | E13: =+E219 -> 1033 | F13: =+F219 -> 1165 | G13: =+G219 -> 1345 | J13: =+B13/B$21 -> 0.012826887 | K13: =+C13/C$21 -> 0.010728741 | L13: =+D13/D$21 -> 0.0079334869 | M13: =+E13/E$21 -> 0.010182356 | N13: =+F13/F$21 -> 0.011260282 | O13: =+G13/G$21 -> 0.011199747 | R13: =RATE(5,0,-G13,B13) -> -0.028993835 | S13: =AVERAGE(T13:X13) -> -0.011320126 | T13: =(+B13-C13)/C13 -> 0.15868263 | U13: =(+C13-D13)/D13 -> 0.26515152 | V13: =(+D13-E13)/E13 -> -0.23330106 | W13: =(+E13-F13)/F13 -> -0.11330472 | X13: =(+F13-G13)/G13 -> -0.133829
A14: Depreciable assets | B14: =+B220 -> 9591 | C14: =+C220 -> 9465 | D14: =+D220 -> 9428 | E14: =+E220 -> 8999 | F14: =+F220 -> 8279 | G14: =+G220 -> 7555 | J14: =+B14/B$21 -> 0.10596268 | K14: =+C14/C$21 -> 0.10134484 | L14: =+D14/D$21 -> 0.094440549 | M14: =+E14/E$21 -> 0.088703795 | N14: =+F14/F$21 -> 0.080020491 | O14: =+G14/G$21 -> 0.062910102 | R14: =RATE(5,0,-G14,B14) -> 0.048880193 | S14: =AVERAGE(T14:X14) -> 0.049541249 | T14: =(+B14-C14)/C14 -> 0.013312203 | U14: =(+C14-D14)/D14 -> 0.0039244803 | V14: =(+D14-E14)/E14 -> 0.047671964 | W14: =(+E14-F14)/F14 -> 0.086967025 | X14: =(+F14-G14)/G14 -> 0.095830576
A15: PP&E - at cost | B15: =+B221 -> 10952 | C15: =+C221 -> 10674 | D15: =+D221 -> 10439 | E15: =+E221 -> 10242 | F15: =+F221 -> 9662 | G15: =+G221 -> 9150 | J15: =+B15/B$21 -> 0.12099919 | K15: =+C15/C$21 -> 0.11429 | L15: =+D15/D$21 -> 0.10456777 | M15: =+E15/E$21 -> 0.10095614 | N15: =+F15/F$21 -> 0.093387847 | O15: =+G15/G$21 -> 0.076191586 | R15: =RATE(5,0,-G15,B15) -> 0.03660779 | S15: =AVERAGE(T15:X15) -> 0.036755223 | T15: =(+B15-C15)/C15 -> 0.026044594 | U15: =(+C15-D15)/D15 -> 0.022511735 | V15: =(+D15-E15)/E15 -> 0.019234525 | W15: =(+E15-F15)/F15 -> 0.06002898 | X15: =(+F15-G15)/G15 -> 0.055956284
A16: Accumulated depreciation | B16: =+B222 -> -4212 | C16: =+C222 -> -3868 | D16: =+D222 -> -3563 | E16: =+E222 -> -3187 | F16: =+F222 -> -2584 | G16: =+G222 -> -2089 | J16: =+B16/B$21 -> -0.046534752 | K16: =+C16/C$21 -> -0.041415937 | L16: =+D16/D$21 -> -0.035690674 | M16: =+E16/E$21 -> -0.03141449 | N16: =+F16/F$21 -> -0.024975595 | O16: =+G16/G$21 -> -0.017394997 | R16: =RATE(5,0,-G16,B16) -> 0.15056189 | S16: =AVERAGE(T16:X16) -> 0.15256616 | T16: =(+B16-C16)/C16 -> 0.08893485 | U16: =(+C16-D16)/D16 -> 0.085602021 | V16: =(+D16-E16)/E16 -> 0.11797929 | W16: =(+E16-F16)/F16 -> 0.23335913 | X16: =(+F16-G16)/G16 -> 0.23695548
A17: Property, plant & equipment - net | B17: 6740 | C17: 6806 | D17: 6876 | E17: 7055 | F17: 7078 | G17: 7061 | J17: =+B17/B$21 -> 0.074464442 | K17: =+C17/C$21 -> 0.07287406 | L17: =+D17/D$21 -> 0.068877091 | M17: =+E17/E$21 -> 0.069541646 | N17: =+F17/F$21 -> 0.068412252 | O17: =+G17/G$21 -> 0.058796589 | R17: =RATE(5,0,-G17,B17) -> -0.0092621911 | S17: =AVERAGE(T17:X17) -> -0.0092183309 | T17: =(+B17-C17)/C17 -> -0.0096973259 | U17: =(+C17-D17)/D17 -> -0.010180337 | V17: =(+D17-E17)/E17 -> -0.025372077 | W17: =(+E17-F17)/F17 -> -0.0032495055 | X17: =(+F17-G17)/G17 -> 0.002407591
A18: Right of Use assets | B18: =+B227 -> 668 | C18: =+C227 -> 569 | D18: =+D227 -> 562 | E18: =+E227 -> 542 | F18: =+F227 -> 0 | G18: =+G227 -> 0
A19: Goodwill and Intangibles (see detail) | B19: =+B244 -> 73482 | C19: =+C244 -> 74838 | D19: =+D244 -> 79756 | E19: =+E244 -> 84198 | F19: =+F244 -> 85971 | G19: =+G244 -> 104257 | J19: =+B19/B$21 -> 0.81183918 | K19: =+C19/C$21 -> 0.80131486 | L19: =+D19/D$21 -> 0.79891816 | M19: =+E19/E$21 -> 0.82994579 | N19: =+F19/F$21 -> 0.83095079 | O19: =+G19/G$21 -> 0.86814276 | R19: =RATE(5,0,-G19,B19) -> -0.067572339 | S19: =AVERAGE(T19:X19) -> -0.065711108 | T19: =(+B19-C19)/C19 -> -0.018119137 | U19: =(+C19-D19)/D19 -> -0.061663072 | V19: =(+D19-E19)/E19 -> -0.052756598 | W19: =(+E19-F19)/F19 -> -0.020623233 | X19: =(+F19-G19)/G19 -> -0.1753935
A20: Other assets | B20: =+B248 -> 1726 | C20: =+C248 -> 2187 | D20: =+D248 -> 1814 | E20: =+E248 -> 1558 | F20: =+F248 -> 1337 | G20: =+G248 -> 1573 | J20: =+B20/B$21 -> 0.019069084 | K20: =+C20/C$21 -> 0.023416922 | L20: =+D20/D$21 -> 0.018170891 | M20: =+E20/E$21 -> 0.015357319 | N20: =+F20/F$21 -> 0.012922744 | O20: =+G20/G$21 -> 0.013098291 | R20: =RATE(5,0,-G20,B20) -> 0.018737783 | S20: =AVERAGE(T20:X20) -> 0.034881754 | T20: =(+B20-C20)/C20 -> -0.21079104 | U20: =(+C20-D20)/D20 -> 0.20562293 | V20: =(+D20-E20)/E20 -> 0.16431322 | W20: =(+E20-F20)/F20 -> 0.16529544 | X20: =(+F20-G20)/G20 -> -0.15003179
A21: Total Assets | B21: =+B11+SUM(B17:B20) -> 90513 | C21: =+C11+SUM(C17:C20) -> 93394 | D21: =+D11+SUM(D17:D20) -> 99830 | E21: =+E11+SUM(E17:E20) -> 101450 | F21: =+F11+SUM(F17:F20) -> 103461 | G21: =+G11+SUM(G17:G20) -> 120092 | J21: =+B21/B$21 -> 1 | K21: =+C21/C$21 -> 1 | L21: =+D21/D$21 -> 1 | M21: =+E21/E$21 -> 1 | N21: =+F21/F$21 -> 1 | O21: =+G21/G$21 -> 1 | R21: =RATE(5,0,-G21,B21) -> -0.054983533 | S21: =AVERAGE(T21:X21) -> -0.053841726 | T21: =(+B21-C21)/C21 -> -0.030847806 | U21: =(+C21-D21)/D21 -> -0.064469598 | V21: =(+D21-E21)/E21 -> -0.015968457 | W21: =(+E21-F21)/F21 -> -0.019437276 | X21: =(+F21-G21)/G21 -> -0.13848549
A22: Liabilities and Equity
A23: Current Debt (see detail) | B23: =+B252 -> 837 | C23: =+C252 -> 754 | D23: =+D252 -> 236 | E23: =+E252 -> 1028 | F23: =+F252 -> 398 | G23: =+G252 -> 3195 | J23: =+B23/B$21 -> 0.0092472904 | K23: =+C23/C$21 -> 0.0080733238 | L23: =+D23/D$21 -> 0.0023640188 | M23: =+E23/E$21 -> 0.01013307 | N23: =+F23/F$21 -> 0.0038468602 | O23: =+G23/G$21 -> 0.026604603 | R23: =RATE(5,0,-G23,B23) -> -0.23501852 | S23: =AVERAGE(T23:X23) -> 0.44841021 | T23: =(+B23-C23)/C23 -> 0.11007958 | U23: =(+C23-D23)/D23 -> 2.1949153 | V23: =(+D23-E23)/E23 -> -0.77042802 | W23: =(+E23-F23)/F23 -> 1.5829146 | X23: =(+F23-G23)/G23 -> -0.87543036
A24: Trade payables | B24: 4848 | C24: 4753 | D24: 4304 | E24: 4003 | F24: 4153 | G24: 4362 | J24: =+B24/B$21 -> 0.053561367 | K24: =+C24/C$21 -> 0.05089192 | L24: =+D24/D$21 -> 0.043113293 | M24: =+E24/E$21 -> 0.039457861 | N24: =+F24/F$21 -> 0.040140729 | O24: =+G24/G$21 -> 0.036322153 | R24: =RATE(5,0,-G24,B24) -> 0.021351874 | S24: =AVERAGE(T24:X24) -> 0.023094055 | T24: =(+B24-C24)/C24 -> 0.019987376 | U24: =(+C24-D24)/D24 -> 0.10432156 | V24: =(+D24-E24)/E24 -> 0.075193605 | W24: =(+E24-F24)/F24 -> -0.036118469 | X24: =(+F24-G24)/G24 -> -0.047913801
A25: Deferred revenue | B25: 0 | C25: 0 | D25: 0 | E25: 0 | F25: 0 | G25: 0 | J25: =+B25/B$21 -> 0 | K25: =+C25/C$21 -> 0 | L25: =+D25/D$21 -> 0 | M25: =+E25/E$21 -> 0 | N25: =+F25/F$21 -> 0 | O25: =+G25/G$21 -> 0
A26: Current portion of operating lease liabilities | B26: =+B228 -> 125 | C26: =+C228 -> 133 | D26: =+D228 -> 135 | E26: =+E228 -> 147 | F26: =+F228 -> 0 | G26: =+G228 -> 0
A27: Other current liabilities (see detail) | B27: =+B260 -> 3218 | C27: =+C260 -> 3424 | D27: =+D260 -> 3386 | E27: =+E260 -> 2697 | F27: =+F260 -> 2952 | G27: =+G260 -> 2597 | J27: =+B27/B$21 -> 0.035552904 | K27: =+C27/C$21 -> 0.036661884 | L27: =+D27/D$21 -> 0.03391766 | M27: =+E27/E$21 -> 0.026584524 | N27: =+F27/F$21 -> 0.028532491 | O27: =+G27/G$21 -> 0.021625087 | R27: =RATE(5,0,-G27,B27) -> 0.04381328 | S27: =AVERAGE(T27:X27) -> 0.051368449 | T27: =(+B27-C27)/C27 -> -0.060163551 | U27: =(+C27-D27)/D27 -> 0.011222682 | V27: =(+D27-E27)/E27 -> 0.25546904 | W27: =(+E27-F27)/F27 -> -0.086382114 | X27: =(+F27-G27)/G27 -> 0.13669619
A28: Total current liabilities | B28: =SUM(B23:B27) -> 9028 | C28: =SUM(C23:C27) -> 9064 | D28: =SUM(D23:D27) -> 8061 | E28: =SUM(E23:E27) -> 7875 | F28: =SUM(F23:F27) -> 7503 | G28: =SUM(G23:G27) -> 10154 | J28: =+B28/B$21 -> 0.099742578 | K28: =+C28/C$21 -> 0.097051202 | L28: =+D28/D$21 -> 0.08074727 | M28: =+E28/E$21 -> 0.077624446 | N28: =+F28/F$21 -> 0.07252008 | O28: =+G28/G$21 -> 0.084551844 | R28: =RATE(5,0,-G28,B28) -> -0.023233226 | S28: =AVERAGE(T28:X28) -> -0.013485134 | T28: =(+B28-C28)/C28 -> -0.0039717564 | U28: =(+C28-D28)/D28 -> 0.12442625 | V28: =(+D28-E28)/E28 -> 0.023619048 | W28: =(+E28-F28)/F28 -> 0.049580168 | X28: =(+F28-G28)/G28 -> -0.26107938
A29: Long-term debt | B29: 19233 | C29: 21061 | D29: 28070 | E29: 28216 | F29: 30770 | G29: 28308 | J29: =+B29/B$21 -> 0.21248881 | K29: =+C29/C$21 -> 0.22550699 | L29: =+D29/D$21 -> 0.281178 | M29: =+E29/E$21 -> 0.27812716 | N29: =+F29/F$21 -> 0.29740675 | O29: =+G29/G$21 -> 0.23571928 | R29: =RATE(5,0,-G29,B29) -> -0.074391 | S29: =AVERAGE(T29:X29) -> -0.06753962 | T29: =(+B29-C29)/C29 -> -0.086795499 | U29: =(+C29-D29)/D29 -> -0.24969719 | V29: =(+D29-E29)/E29 -> -0.0051743692 | W29: =(+E29-F29)/F29 -> -0.083002925 | X29: =(+F29-G29)/G29 -> 0.086971881
A30: LT operating lease liabilities | B30: =+B229 -> 585 | C30: =+C229 -> 484 | D30: =+D229 -> 475 | E30: =+E229 -> 454 | F30: =+F229 -> 0 | G30: =+G229 -> 0
A31: Other non-current liabilities (see detail) | B31: =+B267 -> 12797 | C31: =+C267 -> 13333 | D31: =+D267 -> 12981 | E31: =+E267 -> 13156 | F31: =+F267 -> 13410 | G31: =+G267 -> 15554 | J31: =+B31/B$21 -> 0.14138301 | K31: =+C31/C$21 -> 0.14276078 | L31: =+D31/D$21 -> 0.13003105 | M31: =+E31/E$21 -> 0.12967965 | N31: =+F31/F$21 -> 0.12961406 | O31: =+G31/G$21 -> 0.12951737 | R31: =RATE(5,0,-G31,B31) -> -0.038269886 | S31: =AVERAGE(T31:X31) -> -0.036633962 | T31: =(+B31-C31)/C31 -> -0.040201005 | U31: =(+C31-D31)/D31 -> 0.027116555 | V31: =(+D31-E31)/E31 -> -0.013301915 | W31: =(+E31-F31)/F31 -> -0.018941089 | X31: =(+F31-G31)/G31 -> -0.13784236
A32: Total liabilities | B32: =SUM(B28:B31) -> 41643 | C32: =SUM(C28:C31) -> 43942 | D32: =SUM(D28:D31) -> 49587 | E32: =SUM(E28:E31) -> 49701 | F32: =SUM(F28:F31) -> 51683 | G32: =SUM(G28:G31) -> 54016 | J32: =+B32/B$21 -> 0.46007756 | K32: =+C32/C$21 -> 0.47050132 | L32: =+D32/D$21 -> 0.49671441 | M32: =+E32/E$21 -> 0.48990636 | N32: =+F32/F$21 -> 0.49954089 | O32: =+G32/G$21 -> 0.4497885 | R32: =RATE(5,0,-G32,B32) -> -0.050699045 | S32: =AVERAGE(T32:X32) -> -0.049998615 | T32: =(+B32-C32)/C32 -> -0.052318966 | U32: =(+C32-D32)/D32 -> -0.11384032 | V32: =(+D32-E32)/E32 -> -0.0022937164 | W32: =(+E32-F32)/F32 -> -0.038349167 | X32: =(+F32-G32)/G32 -> -0.043190906
A33: Redeemable Non-controlling interest | B33: 40 | C33: 4 | D33: 0 | E33: 0 | F33: 3 | G33: 6 | J33: =+B33/B$21 -> 0.00044192547 | K33: =+C33/C$21 -> 4.2829304e-05 | L33: =+D33/D$21 -> 0 | M33: =+E33/E$21 -> 0 | N33: =+F33/F$21 -> 2.8996433e-05 | O33: =+G33/G$21 -> 4.9961696e-05 | R33: =RATE(5,0,-G33,B33) -> 0.46144255 | S33: =AVERAGE(T33:X33) -> 2.5 | T33: =(+B33-C33)/C33 -> 9 | W33: =(+E33-F33)/F33 -> -1 | X33: =(+F33-G33)/G33 -> -0.5
A34: Total Equity | B34: =+B275 -> 48830 | C34: =+C275 -> 49448 | D34: =+D275 -> 50243 | E34: =+E275 -> 51749 | F34: =+F275 -> 51775 | G34: =+G275 -> 66070 | J34: =+B34/B$21 -> 0.53948052 | K34: =+C34/C$21 -> 0.52945585 | L34: =+D34/D$21 -> 0.50328559 | M34: =+E34/E$21 -> 0.51009364 | N34: =+F34/F$21 -> 0.50043011 | O34: =+G34/G$21 -> 0.55016154 | R34: =RATE(5,0,-G34,B34) -> -0.05868174 | S34: =AVERAGE(T34:X34) -> -0.054857339 | T34: =(+B34-C34)/C34 -> -0.012497978 | U34: =(+C34-D34)/D34 -> -0.0158231 | V34: =(+D34-E34)/E34 -> -0.029102012 | W34: =(+E34-F34)/F34 -> -0.00050217286 | X34: =(+F34-G34)/G34 -> -0.21636143
A35: Total Liabilities and Equity | B35: =+B34+B33+B32 -> 90513 | C35: =+C34+C33+C32 -> 93394 | D35: =+D34+D33+D32 -> 99830 | E35: =+E34+E33+E32 -> 101450 | F35: =+F34+F33+F32 -> 103461 | G35: =+G34+G33+G32 -> 120092 | J35: =+B35/B$21 -> 1 | K35: =+C35/C$21 -> 1 | L35: =+D35/D$21 -> 1 | M35: =+E35/E$21 -> 1 | N35: =+F35/F$21 -> 1 | O35: =+G35/G$21 -> 1 | R35: =RATE(5,0,-G35,B35) -> -0.054983533 | S35: =AVERAGE(T35:X35) -> -0.053841726 | T35: =(+B35-C35)/C35 -> -0.030847806 | U35: =(+C35-D35)/D35 -> -0.064469598 | V35: =(+D35-E35)/E35 -> -0.015968457 | W35: =(+E35-F35)/F35 -> -0.019437276 | X35: =(+F35-G35)/G35 -> -0.13848549
B36: =+B35-B21 -> 0 | C36: =+C35-C21 -> 0 | D36: =+D35-D21 -> 0 | E36: =+E35-E21 -> 0 | F36: =+F35-F21 -> 0 | G36: =+G35-G21 -> 0
A37: Shares issued | B37: 1243 | C37: 1235 | D37: 1228 | E37: 1224 | F37: 1224 | G37: 1221
A38: Treasury Shares | B38: -18 | C38: -11 | D38: -5 | E38: -3 | F38: -4 | G38: -2
A39: Shares Outstanding | B39: =+B37+B38 -> 1225 | C39: =+C37+C38 -> 1224 | D39: =+D37+D38 -> 1223 | E39: =+E37+E38 -> 1221 | F39: =+F37+F38 -> 1220 | G39: =+G37+G38 -> 1219
A40: Stock price at next 2/28 (60 days after FYE) | B40: 38.13 | C40: 39.22 | D40: 36.38 | E40: 24.77 | F40: 33.19 | G40: 67.14
A41: Market Value of Equity | B41: =+B39*B40 -> 46709.25 | C41: =+C39*C40 -> 48005.28 | D41: =+D39*D40 -> 44492.74 | E41: =+E39*E40 -> 30244.17 | F41: =+F39*F40 -> 40491.8 | G41: =+G39*G40 -> 81843.66
A43: =+A1 -> Kraft Heinz Company | B43: Reclassified
A44: Summary Changes in Equity
A45: =+A3 -> in millions except per share data | F45: Late filing | G45: Restated
A46: =+A4 -> Fiscal year ended 12/31: | B46: 2022 | C46: 2021 | D46: 2020 | E46: 2019 | F46: 2018 | G46: 2017 | H46: Aggregate
A47: Net Income - As Reported | B47: =+'As Reported'!B68 -> 2368 | C47: =+'As Reported'!C68 -> 1024 | D47: =+'As Reported'!D68 -> 361 | E47: =+'As Reported'!E68 -> 1933 | F47: =+'As Reported'!F68 -> -10254 | G47: =+'As Reported'!G68 -> 10932 | H47: =SUM(B47:G47) -> 6364
A48: Other comprehensive income | B48: -993 | C48: 149 | D48: -78 | E48: -72 | F48: -903 | G48: 581 | H48: =SUM(B48:G48) -> -1316
A49: Comprehensive Income affecting equity | B49: =SUM(B47:B48) -> 1375 | C49: =SUM(C47:C48) -> 1173 | D49: =SUM(D47:D48) -> 283 | E49: =SUM(E47:E48) -> 1861 | F49: =SUM(F47:F48) -> -11157 | G49: =SUM(G47:G48) -> 11513 | H49: =SUM(B49:G49) -> 5048
A50: Dividends | B50: -1972 | C50: -1979 | D50: -1973 | E50: -1959 | F50: -3048 | G50: -2988 | H50: =SUM(B50:G50) -> -13919
A51: Other activity (squeeze) | B51: =+B52-SUM(B49:B50) -> -21 | C51: =+C52-SUM(C49:C50) -> 11 | D51: =+D52-SUM(D49:D50) -> 184 | E51: =+E52-SUM(E49:E50) -> 72 | F51: =+F52-SUM(F49:F50) -> -90 | G51: =+G52-SUM(G49:G50) -> 85 | H51: =SUM(B51:G51) -> 241
A52: Change in equity | B52: =+B54-B53 -> -618 | C52: =+C54-C53 -> -795 | D52: =+D54-D53 -> -1506 | E52: =+E54-E53 -> -26 | F52: =+F54-F53 -> -14295 | G52: =+G54-G53 -> 8610 | H52: =SUM(B52:G52) -> -8630
A53: Beginning Equity | B53: =+C54 -> 49448 | C53: =+D54 -> 50243 | D53: =+E54 -> 51749 | E53: =+F54 -> 51775 | F53: =+G54 -> 66070 | G53: 57460 | H53: =+G53 -> 57460
A54: Ending Equity | B54: =+B34 -> 48830 | C54: =+C34 -> 49448 | D54: =+D34 -> 50243 | E54: =+E34 -> 51749 | F54: =+F34 -> 51775 | G54: =+G34 -> 66070 | H54: =++H52+H53 -> 48830
A56: =+A1 -> Kraft Heinz Company | B56: =+B1 -> Reclassified | J56: =+B56 -> Reclassified | R56: =+B56 -> Reclassified
A57: Consolidated Income Statements | J57: Common Size on Net Sales | R57: Horizontal(Growth) Analysis
A58: =+A3 -> in millions except per share data | F58: Late filing | G58: Restated | O58: Restated | R58: 5 Year | S58: Annual | T58: 2021 to | U58: 2020 to | V58: 2019 to | W58: 2018 to | X58: 2017 to
A59: =+A4 -> Fiscal year ended 12/31: | B59: 2022 | C59: 2021 | D59: 2020 | E59: 2019 | F59: 2018 | G59: 2017 | H59: Aggregate | J59: 2022 | K59: 2021 | L59: 2020 | M59: 2019 | N59: 2018 | O59: 2017 | P59: Aggregate | R59: CAGR | S59: Average | T59: 2022 | U59: 2021 | V59: 2020 | W59: 2019 | X59: 2018
A60: Net sales | B60: 26485 | C60: 26042 | D60: 26185 | E60: 24977 | F60: 26268 | G60: 26076 | H60: =SUM(B60:G60) -> 156033 | J60: =+B60/B$60 -> 1 | K60: =+C60/C$60 -> 1 | L60: =+D60/D$60 -> 1 | M60: =+E60/E$60 -> 1 | N60: =+F60/F$60 -> 1 | O60: =+G60/G$60 -> 1 | P60: =+H60/H$60 -> 1 | R60: =RATE(5,0,-G60,B60) -> 0.0031174861 | S60: =AVERAGE(T60:X60) -> 0.0036260354 | T60: =(+B60-C60)/C60 -> 0.017010982 | U60: =(+C60-D60)/D60 -> -0.0054611419 | V60: =(+D60-E60)/E60 -> 0.048364495 | W60: =(+E60-F60)/F60 -> -0.049147251 | X60: =(+F60-G60)/G60 -> 0.0073630925
A61: Cost of goods sold | B61: 18363 | C61: 17360 | D61: 17008 | E61: 16830 | F61: 17347 | G61: 17043 | H61: =SUM(B61:G61) -> 103951 | J61: =+B61/B$60 -> 0.69333585 | K61: =+C61/C$60 -> 0.66661547 | L61: =+D61/D$60 -> 0.64953217 | M61: =+E61/E$60 -> 0.67381991 | N61: =+F61/F$60 -> 0.66038526 | O61: =+G61/G$60 -> 0.65358951 | P61: =+H61/H$60 -> 0.66621163 | R61: =RATE(5,0,-G61,B61) -> 0.015031495 | S61: =AVERAGE(T61:X61) -> 0.015416561 | T61: =(+B61-C61)/C61 -> 0.057776498 | U61: =(+C61-D61)/D61 -> 0.020696143 | V61: =(+D61-E61)/E61 -> 0.010576352 | W61: =(+E61-F61)/F61 -> -0.029803424 | X61: =(+F61-G61)/G61 -> 0.017837235
A62: Gross profit | B62: =+B60-B61 -> 8122 | C62: =+C60-C61 -> 8682 | D62: =+D60-D61 -> 9177 | E62: =+E60-E61 -> 8147 | F62: =+F60-F61 -> 8921 | G62: =+G60-G61 -> 9033 | H62: =SUM(B62:G62) -> 52082 | J62: =+B62/B$60 -> 0.30666415 | K62: =+C62/C$60 -> 0.33338453 | L62: =+D62/D$60 -> 0.35046783 | M62: =+E62/E$60 -> 0.32618009 | N62: =+F62/F$60 -> 0.33961474 | O62: =+G62/G$60 -> 0.34641049 | P62: =+H62/H$60 -> 0.33378837 | R62: =RATE(5,0,-G62,B62) -> -0.021037187 | S62: =AVERAGE(T62:X62) -> -0.018234823 | T62: =(+B62-C62)/C62 -> -0.064501267 | U62: =(+C62-D62)/D62 -> -0.053939196 | V62: =(+D62-E62)/E62 -> 0.12642691 | W62: =(+E62-F62)/F62 -> -0.086761574 | X62: =(+F62-G62)/G62 -> -0.012398982
A63: SG&A (see detail) | B63: =+B280 -> 2503 | C63: =+C280 -> 2409 | D63: =+D280 -> 2461 | E63: =+E280 -> 1966 | F63: =+F280 -> 1941 | G63: =+G280 -> 1719 | H63: =SUM(B63:G63) -> 12999 | J63: =+B63/B$60 -> 0.094506324 | K63: =+C63/C$60 -> 0.092504416 | L63: =+D63/D$60 -> 0.093985106 | M63: =+E63/E$60 -> 0.078712415 | N63: =+F63/F$60 -> 0.073892188 | O63: =+G63/G$60 -> 0.065922688 | P63: =+H63/H$60 -> 0.0833093 | R63: =RATE(5,0,-G63,B63) -> 0.07804526 | S63: =AVERAGE(T63:X63) -> 0.082339159 | T63: =(+B63-C63)/C63 -> 0.03902034 | U63: =(+C63-D63)/D63 -> -0.021129622 | V63: =(+D63-E63)/E63 -> 0.25178026 | W63: =(+E63-F63)/F63 -> 0.012879959 | X63: =(+F63-G63)/G63 -> 0.12914485
A64: Advertising & Promotion | B64: =+B215 -> 945 | C64: =+C215 -> 1039 | D64: =+D215 -> 1070 | E64: =+E215 -> 1100 | F64: =+F215 -> 1140 | G64: =+G215 -> 1115 | H64: =SUM(B64:G64) -> 6409 | J64: =+B64/B$60 -> 0.035680574 | K64: =+C64/C$60 -> 0.039897089 | L64: =+D64/D$60 -> 0.04086309 | M64: =+E64/E$60 -> 0.044040517 | N64: =+F64/F$60 -> 0.043398812 | O64: =+G64/G$60 -> 0.042759626 | P64: =+H64/H$60 -> 0.041074644
A65: Research & Devlopment | B65: =+B216 -> 127 | C65: =+C216 -> 140 | D65: =+D216 -> 119 | E65: =+E216 -> 112 | F65: =+F216 -> 109 | G65: =+G216 -> 93 | H65: =SUM(B65:G65) -> 700 | J65: =+B65/B$60 -> 0.0047951671 | K65: =+C65/C$60 -> 0.0053759312 | L65: =+D65/D$60 -> 0.0045445866 | M65: =+E65/E$60 -> 0.0044841254 | N65: =+F65/F$60 -> 0.0041495356 | O65: =+G65/G$60 -> 0.0035664979 | P65: =+H65/H$60 -> 0.0044862305
A66: Goodwill impairment | B66: 444 | C66: 318 | D66: 2343 | E66: 1197 | F66: 7008 | G66: 0 | H66: =SUM(B66:G66) -> 11310 | J66: =+B66/B$60 -> 0.016764206 | K66: =+C66/C$60 -> 0.012211044 | L66: =+D66/D$60 -> 0.089478709 | M66: =+E66/E$60 -> 0.04792409 | N66: =+F66/F$60 -> 0.26678849 | O66: =+G66/G$60 -> 0 | P66: =+H66/H$60 -> 0.072484667 | S66: =AVERAGE(T66:X66) -> -0.084962969 | T66: =(+B66-C66)/C66 -> 0.39622642 | U66: =(+C66-D66)/D66 -> -0.86427657 | V66: =(+D66-E66)/E66 -> 0.95739348 | W66: =(+E66-F66)/F66 -> -0.82919521
A67: Intangible impairment | B67: 469 | C67: 1316 | D67: 1056 | E67: 702 | F67: 8928 | G67: 49 | H67: =SUM(B67:G67) -> 12520 | J67: =+B67/B$60 -> 0.017708137 | K67: =+C67/C$60 -> 0.050533753 | L67: =+D67/D$60 -> 0.040328432 | M67: =+E67/E$60 -> 0.028105857 | N67: =+F67/F$60 -> 0.33988122 | O67: =+G67/G$60 -> 0.0018791226 | P67: =+H67/H$60 -> 0.080239437 | R67: =RATE(5,0,-G67,B67) -> 0.57106934 | S67: =AVERAGE(T67:X67) -> 36.077916 | T67: =(+B67-C67)/C67 -> -0.64361702 | U67: =(+C67-D67)/D67 -> 0.24621212 | V67: =(+D67-E67)/E67 -> 0.5042735 | W67: =(+E67-F67)/F67 -> -0.92137097 | X67: =(+F67-G67)/G67 -> 181.20408
A68: Operating expenses | B68: =SUM(B63:B67) -> 4488 | C68: =SUM(C63:C67) -> 5222 | D68: =SUM(D63:D67) -> 7049 | E68: =SUM(E63:E67) -> 5077 | F68: =SUM(F63:F67) -> 19126 | G68: =SUM(G63:G67) -> 2976 | H68: =SUM(B68:G68) -> 43938 | J68: =+B68/B$60 -> 0.16945441 | K68: =+C68/C$60 -> 0.20052223 | L68: =+D68/D$60 -> 0.26919992 | M68: =+E68/E$60 -> 0.20326701 | N68: =+F68/F$60 -> 0.72811025 | O68: =+G68/G$60 -> 0.11412793 | P68: =+H68/H$60 -> 0.28159428 | R68: =RATE(5,0,-G68,B68) -> 0.08563537 | S68: =AVERAGE(T68:X68) -> 0.93617419 | T68: =(+B68-C68)/C68 -> -0.14055917 | U68: =(+C68-D68)/D68 -> -0.2591857 | V68: =(+D68-E68)/E68 -> 0.38841836 | W68: =(+E68-F68)/F68 -> -0.73454983 | X68: =(+F68-G68)/G68 -> 5.4267473
A69: Operating income (loss) | B69: =+B62-B68 -> 3634 | C69: =+C62-C68 -> 3460 | D69: =+D62-D68 -> 2128 | E69: =+E62-E68 -> 3070 | F69: =+F62-F68 -> -10205 | G69: =+G62-G68 -> 6057 | H69: =SUM(B69:G69) -> 8144 | J69: =+B69/B$60 -> 0.13720974 | K69: =+C69/C$60 -> 0.1328623 | L69: =+D69/D$60 -> 0.081267901 | M69: =+E69/E$60 -> 0.12291308 | N69: =+F69/F$60 -> -0.38849551 | O69: =+G69/G$60 -> 0.23228256 | P69: =+H69/H$60 -> 0.052194087 | R69: =RATE(5,0,-G69,B69) -> -0.097129486 | S69: =AVERAGE(T69:X69) -> -0.72325438 | T69: =(+B69-C69)/C69 -> 0.050289017 | U69: =(+C69-D69)/D69 -> 0.62593985 | V69: =(+D69-E69)/E69 -> -0.30684039 | W69: =(+E69-F69)/F69 -> -1.3008329 | X69: =(+F69-G69)/G69 -> -2.6848275
A70: Interest expense | B70: 921 | C70: 2047 | D70: 1394 | E70: 1361 | F70: 1284 | G70: 1234 | H70: =SUM(B70:G70) -> 8241 | J70: =+B70/B$60 -> 0.034774401 | K70: =+C70/C$60 -> 0.078603794 | L70: =+D70/D$60 -> 0.053236586 | M70: =+E70/E$60 -> 0.054490131 | N70: =+F70/F$60 -> 0.048880767 | O70: =+G70/G$60 -> 0.047323209 | P70: =+H70/H$60 -> 0.052815751 | R70: =RATE(5,0,-G70,B70) -> -0.056832355 | S70: =AVERAGE(T70:X70) -> 0.008619448 | T70: =(+B70-C70)/C70 -> -0.55007328 | U70: =(+C70-D70)/D70 -> 0.46843615 | V70: =(+D70-E70)/E70 -> 0.024246877 | W70: =(+E70-F70)/F70 -> 0.059968847 | X70: =(+F70-G70)/G70 -> 0.040518639
A71: Other expense (income) | B71: -253 | C71: -295 | D71: -296 | E71: -952 | F71: -168 | G71: -627 | H71: =SUM(B71:G71) -> -2591 | J71: =+B71/B$60 -> -0.0095525769 | K71: =+C71/C$60 -> -0.011327855 | L71: =+D71/D$60 -> -0.011304182 | M71: =+E71/E$60 -> -0.038115066 | N71: =+F71/F$60 -> -0.0063956144 | O71: =+G71/G$60 -> -0.024045099 | P71: =+H71/H$60 -> -0.016605462 | R71: =RATE(5,0,-G71,B71) -> -0.16599127 | S71: =AVERAGE(T71:X71) -> 0.61995647 | T71: =(+B71-C71)/C71 -> -0.14237288 | U71: =(+C71-D71)/D71 -> -0.0033783784 | V71: =(+D71-E71)/E71 -> -0.68907563 | W71: =(+E71-F71)/F71 -> 4.6666667 | X71: =(+F71-G71)/G71 -> -0.73205742
A72: Pretax Income | B72: =+B69-B70-B71 -> 2966 | C72: =+C69-C70-C71 -> 1708 | D72: =+D69-D70-D71 -> 1030 | E72: =+E69-E70-E71 -> 2661 | F72: =+F69-F70-F71 -> -11321 | G72: =+G69-G70-G71 -> 5450 | H72: =SUM(B72:G72) -> 2494 | J72: =+B72/B$60 -> 0.11198792 | K72: =+C72/C$60 -> 0.06558636 | L72: =+D72/D$60 -> 0.039335497 | M72: =+E72/E$60 -> 0.10653801 | N72: =+F72/F$60 -> -0.43098066 | O72: =+G72/G$60 -> 0.20900445 | P72: =+H72/H$60 -> 0.015983798 | R72: =RATE(5,0,-G72,B72) -> -0.11456858 | S72: =AVERAGE(T72:X72) -> -0.70608774 | T72: =(+B72-C72)/C72 -> 0.73653396 | U72: =(+C72-D72)/D72 -> 0.65825243 | V72: =(+D72-E72)/E72 -> -0.61292747 | W72: =(+E72-F72)/F72 -> -1.2350499 | X72: =(+F72-G72)/G72 -> -3.0772477
A73: Tax provision | B73: 598 | C73: 684 | D73: 669 | E73: 728 | F73: -1067 | G73: -5482 | H73: =SUM(B73:G73) -> -3870 | J73: =+B73/B$60 -> 0.022578818 | K73: =+C73/C$60 -> 0.026265264 | L73: =+D73/D$60 -> 0.025548978 | M73: =+E73/E$60 -> 0.029146815 | N73: =+F73/F$60 -> -0.040619765 | O73: =+G73/G$60 -> -0.21023163 | P73: =+H73/H$60 -> -0.024802446 | R73: =RATE(5,0,G73,B73) -> -0.35797427 | S73: =AVERAGE(T73:X73) -> -0.53440064 | T73: =(+B73-C73)/C73 -> -0.12573099 | U73: =(+C73-D73)/D73 -> 0.022421525 | V73: =(+D73-E73)/E73 -> -0.081043956 | W73: =(+E73-F73)/F73 -> -1.6822868 | X73: =(+F73-G73)/G73 -> -0.80536301
A74: Net Income (loss) | B74: =+B72-B73 -> 2368 | C74: =+C72-C73 -> 1024 | D74: =+D72-D73 -> 361 | E74: =+E72-E73 -> 1933 | F74: =+F72-F73 -> -10254 | G74: =+G72-G73 -> 10932 | H74: =SUM(B74:G74) -> 6364 | J74: =+B74/B$60 -> 0.089409099 | K74: =+C74/C$60 -> 0.039321097 | L74: =+D74/D$60 -> 0.013786519 | M74: =+E74/E$60 -> 0.0773912 | N74: =+F74/F$60 -> -0.3903609 | O74: =+G74/G$60 -> 0.41923608 | P74: =+H74/H$60 -> 0.040786244 | R74: =RATE(5,0,-G74,B74) -> -0.26356162 | S74: =AVERAGE(T74:X74) -> -0.15813412 | T74: =(+B74-C74)/C74 -> 1.3125 | U74: =(+C74-D74)/D74 -> 1.8365651 | V74: =(+D74-E74)/E74 -> -0.81324366 | W74: =(+E74-F74)/F74 -> -1.1885118 | X74: =(+F74-G74)/G74 -> -1.9379802
A75: Noncontrolling interest | B75: 5 | C75: 12 | D75: 5 | E75: -2 | F75: -62 | G75: -9 | H75: =SUM(B75:G75) -> -51 | J75: =+B75/B$60 -> 0.00018878611 | K75: =+C75/C$60 -> 0.0004607941 | L75: =+D75/D$60 -> 0.00019094902 | M75: =+E75/E$60 -> -8.0073668e-05 | N75: =+F75/F$60 -> -0.0023602863 | O75: =+G75/G$60 -> -0.00034514496 | P75: =+H75/H$60 -> -0.00032685393 | R75: =RATE(5,0,G75,B75) -> -0.11091046 | S75: =AVERAGE(T75:X75) -> 0.44756272 | T75: =(+B75-C75)/C75 -> -0.58333333 | U75: =(+C75-D75)/D75 -> 1.4 | V75: =(+D75-E75)/E75 -> -3.5 | W75: =(+E75-F75)/F75 -> -0.96774194 | X75: =(+F75-G75)/G75 -> 5.8888889
A76: Net income (Loss)-Kraft Heinz | B76: =+B74-B75 -> 2363 | C76: =+C74-C75 -> 1012 | D76: =+D74-D75 -> 356 | E76: =+E74-E75 -> 1935 | F76: =+F74-F75 -> -10192 | G76: =+G74-G75 -> 10941 | H76: =SUM(B76:G76) -> 6415 | J76: =+B76/B$60 -> 0.089220313 | K76: =+C76/C$60 -> 0.038860303 | L76: =+D76/D$60 -> 0.01359557 | M76: =+E76/E$60 -> 0.077471274 | N76: =+F76/F$60 -> -0.38800061 | O76: =+G76/G$60 -> 0.41958122 | P76: =+H76/H$60 -> 0.041113098 | R76: =RATE(5,0,-G76,B76) -> -0.26399402 | S76: =AVERAGE(T76:X76) -> -0.1519481 | T76: =(+B76-C76)/C76 -> 1.3349802 | U76: =(+C76-D76)/D76 -> 1.8426966 | V76: =(+D76-E76)/E76 -> -0.81602067 | W76: =(+E76-F76)/F76 -> -1.1898548 | X76: =(+F76-G76)/G76 -> -1.9315419
B77: =+B76-'As Reported'!B70 -> 0 | C77: =+C76-'As Reported'!C70 -> 0 | D77: =+D76-'As Reported'!D70 -> 0 | E77: =+E76-'As Reported'!E70 -> 0 | F77: =+F76-'As Reported'!F70 -> 0 | G77: =+G76-'As Reported'!G70 -> 0
A78: Diluted W. Ave shares outstanding (notes) | B78: 1235 | C78: 1236 | D78: 1228 | E78: 1224 | F78: 1219 | G78: 1228 | R78: =RATE(5,0,-G78,B78) -> 0.0011374745 | S78: =AVERAGE(T78:X78) -> 0.0011492606 | T78: =(+B78-C78)/C78 -> -0.00080906149 | U78: =(+C78-D78)/D78 -> 0.006514658 | V78: =(+D78-E78)/E78 -> 0.0032679739 | W78: =(+E78-F78)/F78 -> 0.0041017227 | X78: =(+F78-G78)/G78 -> -0.0073289902
A79: Diluted EPS | B79: =+B76/B78 -> 1.9133603 | C79: =+C76/C78 -> 0.81877023 | D79: =+D76/D78 -> 0.28990228 | E79: =+E76/E78 -> 1.5808824 | F79: =+F76/F78 -> -8.3609516 | G79: =+G76/G78 -> 8.9096091 | R79: =RATE(5,0,-G79,B79) -> -0.26483026 | S79: =AVERAGE(T79:X79) -> -0.15659011 | T79: =(+B79-C79)/C79 -> 1.3368709 | U79: =(+C79-D79)/D79 -> 1.8242973 | V79: =(+D79-E79)/E79 -> -0.81661995 | W79: =(+E79-F79)/F79 -> -1.1890792 | X79: =(+F79-G79)/G79 -> -1.9384196
A80: Dividends per share (Equity Stmt)) | B80: 1.6 | C80: 1.6 | D80: 1.6 | E80: 1.6 | F80: 2.5 | G80: 2.45 | R80: =RATE(5,0,-G80,B80) -> -0.0816869 | S80: =AVERAGE(T80:X80) -> -0.067918367 | T80: =(+B80-C80)/C80 -> 0 | U80: =(+C80-D80)/D80 -> 0 | V80: =(+D80-E80)/E80 -> 0 | W80: =(+E80-F80)/F80 -> -0.36 | X80: =(+F80-G80)/G80 -> 0.020408163
A82: Effective Tax Rate | B82: =+B73/B72 -> 0.20161834 | C82: =+C73/C72 -> 0.40046838 | D82: =+D73/D72 -> 0.64951456 | E82: =+E73/E72 -> 0.27358136 | F82: =+F73/F72 -> 0.094249625 | G82: =+G73/G72 -> -1.0058716 | H82: =+H73/H72 -> -1.5517241
A84: Non-GAAP Measurements:
A85: Net Income | B85: =+B76 -> 2363 | C85: =+C76 -> 1012 | D85: =+D76 -> 356 | E85: =+E76 -> 1935 | F85: =+F76 -> -10192 | G85: =+G76 -> 10941
A86: Add back Income Taxes | B86: =+B73 -> 598 | C86: =+C73 -> 684 | D86: =+D73 -> 669 | E86: =+E73 -> 728 | F86: =+F73 -> -1067 | G86: =+G73 -> -5482
A87: Add back Interest Expense | B87: =+B70 -> 921 | C87: =+C70 -> 2047 | D87: =+D70 -> 1394 | E87: =+E70 -> 1361 | F87: =+F70 -> 1284 | G87: =+G70 -> 1234
A88: EBIT | B88: =SUM(B85:B87) -> 3882 | C88: =SUM(C85:C87) -> 3743 | D88: =SUM(D85:D87) -> 2419 | E88: =SUM(E85:E87) -> 4024 | F88: =SUM(F85:F87) -> -9975 | G88: =SUM(G85:G87) -> 6693
A89: Depreciation and amortization | B89: =+B102 -> 933 | C89: =+C102 -> 910 | D89: =+D102 -> 969 | E89: =+E102 -> 994 | F89: =+F102 -> 983 | G89: =+G102 -> 1031
A90: EBITDA | B90: =+B89+B88 -> 4815 | C90: =+C89+C88 -> 4653 | D90: =+D89+D88 -> 3388 | E90: =+E89+E88 -> 5018 | F90: =+F89+F88 -> -8992 | G90: =+G89+G88 -> 7724
A92: Operating Income | B92: =+B69 -> 3634 | C92: =+C69 -> 3460 | D92: =+D69 -> 2128 | E92: =+E69 -> 3070 | F92: =+F69 -> -10205 | G92: =+G69 -> 6057
A93: Other Income | B93: =-B71 -> 253 | C93: =-C71 -> 295 | D93: =-D71 -> 296 | E93: =-E71 -> 952 | F93: =-F71 -> 168 | G93: =-G71 -> 627
A94: Noncontrolling interest | B94: =-B75 -> -5 | C94: =-C75 -> -12 | D94: =-D75 -> -5 | E94: =-E75 -> 2 | F94: =-F75 -> 62 | G94: =-G75 -> 9
A95: EBIT | B95: =+SUM(B92:B94) -> 3882 | C95: =+SUM(C92:C94) -> 3743 | D95: =+SUM(D92:D94) -> 2419 | E95: =+SUM(E92:E94) -> 4024 | F95: =+SUM(F92:F94) -> -9975 | G95: =+SUM(G92:G94) -> 6693
A97: =+A1 -> Kraft Heinz Company | B97: =+B1 -> Reclassified | J97: =+B97 -> Reclassified | R97: =+B97 -> Reclassified
A98: Consolidated Cash Flows | J98: Common Size on Operating Cash Flows | R98: Horizontal(Growth) Analysis
A99: =+A3 -> in millions except per share data | F99: Late filing | G99: Restated | O99: Restated | R99: 5 Year | S99: Annual | T99: 2021 to | U99: 2020 to | V99: 2019 to | W99: 2018 to | X99: 2017 to
A100: =+A4 -> Fiscal year ended 12/31: | B100: 2022 | C100: 2021 | D100: 2020 | E100: 2019 | F100: 2018 | G100: 2017 | H100: Aggregate | J100: 2022 | K100: 2021 | L100: 2020 | M100: 2019 | N100: 2018 | O100: 2017 | R100: CAGR | S100: Average | T100: 2022 | U100: 2021 | V100: 2020 | W100: 2019 | X100: 2018
A101: Net income (loss) - as reported | B101: =+'As Reported'!B68 -> 2368 | C101: =+'As Reported'!C68 -> 1024 | D101: =+'As Reported'!D68 -> 361 | E101: =+'As Reported'!E68 -> 1933 | F101: =+'As Reported'!F68 -> -10254 | G101: =+'As Reported'!G68 -> 10932 | H101: =SUM(B101:G101) -> 6364 | R101: =RATE(5,0,-G101,B101) -> -0.26356162 | S101: =AVERAGE(T101:X101) -> -0.15813412 | T101: =(+B101-C101)/C101 -> 1.3125 | U101: =(+C101-D101)/D101 -> 1.8365651 | V101: =(+D101-E101)/E101 -> -0.81324366 | W101: =(+E101-F101)/F101 -> -1.1885118 | X101: =(+F101-G101)/G101 -> -1.9379802
A102: Depreciation & amortization | B102: 933 | C102: 910 | D102: 969 | E102: 994 | F102: 983 | G102: 1031 | H102: =SUM(B102:G102) -> 5820 | R102: =RATE(5,0,-G102,B102) -> -0.019777661 | S102: =AVERAGE(T102:X102) -> -0.01922604 | T102: =(+B102-C102)/C102 -> 0.025274725 | U102: =(+C102-D102)/D102 -> -0.060887513 | V102: =(+D102-E102)/E102 -> -0.025150905 | W102: =(+E102-F102)/F102 -> 0.011190234 | X102: =(+F102-G102)/G102 -> -0.046556741
A103: Amortization of PRB | B103: -14 | C103: -7 | D103: -122 | E103: -306 | F103: -339 | G103: -328 | H103: =SUM(B103:G103) -> -1116 | R103: =RATE(5,0,-G103,B103) -> -0.46782945 | S103: =AVERAGE(T103:X103) -> -0.12154774 | T103: =(+B103-C103)/C103 -> 1 | U103: =(+C103-D103)/D103 -> -0.94262295 | V103: =(+D103-E103)/E103 -> -0.60130719 | W103: =(+E103-F103)/F103 -> -0.097345133 | X103: =(+F103-G103)/G103 -> 0.033536585
A104: Divestiture-related license income | B104: -56 | C104: -4 | D104: 0 | E104: 0 | F104: 0 | G104: 0 | H104: =SUM(B104:G104) -> -60 | S104: =AVERAGE(T104:X104) -> 13 | T104: =(+B104-C104)/C104 -> 13
A105: Stock-based compensation | B105: 148 | C105: 197 | D105: 156 | E105: 46 | F105: 33 | G105: 46 | H105: =SUM(B105:G105) -> 626 | R105: =RATE(5,0,-G105,B105) -> 0.26328336 | S105: =AVERAGE(T105:X105) -> 0.50334492 | T105: =(+B105-C105)/C105 -> -0.24873096 | U105: =(+C105-D105)/D105 -> 0.26282051 | V105: =(+D105-E105)/E105 -> 2.3913043 | W105: =(+E105-F105)/F105 -> 0.39393939 | X105: =(+F105-G105)/G105 -> -0.2826087
A106: Deferred income taxes | B106: -278 | C106: -1042 | D106: -343 | E106: -293 | F106: -1967 | G106: -6495 | H106: =SUM(B106:G106) -> -10418 | R106: =RATE(5,0,-G106,B106) -> -0.46753247 | S106: =AVERAGE(T106:X106) -> -0.014569977 | T106: =(+B106-C106)/C106 -> -0.73320537 | U106: =(+C106-D106)/D106 -> 2.0379009 | V106: =(+D106-E106)/E106 -> 0.17064846 | W106: =(+E106-F106)/F106 -> -0.8510422 | X106: =(+F106-G106)/G106 -> -0.69715166
...

Sheet Liquidity
A1: Kraft Heinz Company | B1: Reclassified
A2: Consolidated Balance Sheets
A3: in millions except per share data | F3: Late filing | G3: Restated
A4: Fiscal year ended 12/31: | B4: 2022 | C4: 2021 | D4: 2020 | E4: 2019 | F4: 2018 | G4: 2017
A5: Assets:
A6: Cash and equivalents | B6: 1040 | C6: 3445 | D6: 3417 | E6: 2279 | F6: 1130 | G6: 1629
A7: Marketable Securities | B7: 0 | C7: 0 | D7: 0 | E7: 0 | F7: 0 | G7: 0
A8: Trade receivables | B8: 2120 | C8: 1957 | D8: 2063 | E8: 1973 | F8: 2129 | G8: 921
A9: Inventories | B9: 3651 | C9: 2729 | D9: 2554 | E9: 2721 | F9: 2667 | G9: 2760
A10: Other current assets | B10: =+B276 -> 1086 | C10: =+C276 -> 863 | D10: =+D276 -> 2788 | E10: =+E276 -> 1124 | F10: =+F276 -> 3149 | G10: =+G276 -> 1891
A11: Total current assets | B11: =SUM(B6:B10) -> 7897 | C11: =SUM(C6:C10) -> 8994 | D11: =SUM(D6:D10) -> 10822 | E11: =SUM(E6:E10) -> 8097 | F11: =SUM(F6:F10) -> 9075 | G11: =SUM(G6:G10) -> 7201
A12: Land | B12: =+B254 -> 200 | C12: =+C254 -> 207 | D12: =+D254 -> 219 | E12: =+E254 -> 210 | F12: =+F254 -> 218 | G12: =+G254 -> 250
A13: Construction in progress | B13: =+B255 -> 1161 | C13: =+C255 -> 1002 | D13: =+D255 -> 792 | E13: =+E255 -> 1033 | F13: =+F255 -> 1165 | G13: =+G255 -> 1345
A14: Depreciable assets | B14: =+B256 -> 9591 | C14: =+C256 -> 9465 | D14: =+D256 -> 9428 | E14: =+E256 -> 8999 | F14: =+F256 -> 8279 | G14: =+G256 -> 7555
A15: PP&E - at cost | B15: =+B257 -> 10952 | C15: =+C257 -> 10674 | D15: =+D257 -> 10439 | E15: =+E257 -> 10242 | F15: =+F257 -> 9662 | G15: =+G257 -> 9150
A16: Accumulated depreciation | B16: =+B258 -> -4212 | C16: =+C258 -> -3868 | D16: =+D258 -> -3563 | E16: =+E258 -> -3187 | F16: =+F258 -> -2584 | G16: =+G258 -> -2089
A17: Property, plant & equipment - net | B17: 6740 | C17: 6806 | D17: 6876 | E17: 7055 | F17: 7078 | G17: 7061
A18: Right of Use assets | B18: =+B263 -> 668 | C18: =+C263 -> 569 | D18: =+D263 -> 562 | E18: =+E263 -> 542 | F18: =+F263 -> 0 | G18: =+G263 -> 0
A19: Goodwill and Intangibles (see detail) | B19: =+B280 -> 73482 | C19: =+C280 -> 74838 | D19: =+D280 -> 79756 | E19: =+E280 -> 84198 | F19: =+F280 -> 85971 | G19: =+G280 -> 104257
A20: Other assets | B20: =+B284 -> 1726 | C20: =+C284 -> 2187 | D20: =+D284 -> 1814 | E20: =+E284 -> 1558 | F20: =+F284 -> 1337 | G20: =+G284 -> 1573
A21: Total Assets | B21: =+B11+SUM(B17:B20) -> 90513 | C21: =+C11+SUM(C17:C20) -> 93394 | D21: =+D11+SUM(D17:D20) -> 99830 | E21: =+E11+SUM(E17:E20) -> 101450 | F21: =+F11+SUM(F17:F20) -> 103461 | G21: =+G11+SUM(G17:G20) -> 120092
A22: Liabilities and Equity
A23: Current Debt (see detail) | B23: =+B288 -> 837 | C23: =+C288 -> 754 | D23: =+D288 -> 236 | E23: =+E288 -> 1028 | F23: =+F288 -> 398 | G23: =+G288 -> 3195
A24: Trade payables | B24: 4848 | C24: 4753 | D24: 4304 | E24: 4003 | F24: 4153 | G24: 4362
A25: Deferred revenue | B25: 0 | C25: 0 | D25: 0 | E25: 0 | F25: 0 | G25: 0
A26: Current portion of operating lease liabilities | B26: =+B264 -> 125 | C26: =+C264 -> 133 | D26: =+D264 -> 135 | E26: =+E264 -> 147 | F26: =+F264 -> 0 | G26: =+G264 -> 0
A27: Other current liabilities (see detail) | B27: =+B296 -> 3218 | C27: =+C296 -> 3424 | D27: =+D296 -> 3386 | E27: =+E296 -> 2697 | F27: =+F296 -> 2952 | G27: =+G296 -> 2597
A28: Total current liabilities | B28: =SUM(B23:B27) -> 9028 | C28: =SUM(C23:C27) -> 9064 | D28: =SUM(D23:D27) -> 8061 | E28: =SUM(E23:E27) -> 7875 | F28: =SUM(F23:F27) -> 7503 | G28: =SUM(G23:G27) -> 10154
A29: Long-term debt | B29: 19233 | C29: 21061 | D29: 28070 | E29: 28216 | F29: 30770 | G29: 28308
A30: LT operating lease liabilities | B30: =+B265 -> 585 | C30: =+C265 -> 484 | D30: =+D265 -> 475 | E30: =+E265 -> 454 | F30: =+F265 -> 0 | G30: =+G265 -> 0
A31: Other non-current liabilities (see detail) | B31: =+B303 -> 12797 | C31: =+C303 -> 13333 | D31: =+D303 -> 12981 | E31: =+E303 -> 13156 | F31: =+F303 -> 13410 | G31: =+G303 -> 15554
A32: Total liabilities | B32: =SUM(B28:B31) -> 41643 | C32: =SUM(C28:C31) -> 43942 | D32: =SUM(D28:D31) -> 49587 | E32: =SUM(E28:E31) -> 49701 | F32: =SUM(F28:F31) -> 51683 | G32: =SUM(G28:G31) -> 54016
A33: Redeemable Non-controlling interest | B33: 40 | C33: 4 | D33: 0 | E33: 0 | F33: 3 | G33: 6
A34: Total Equity | B34: =+B311 -> 48830 | C34: =+C311 -> 49448 | D34: =+D311 -> 50243 | E34: =+E311 -> 51749 | F34: =+F311 -> 51775 | G34: =+G311 -> 66070
A35: Total Liabilities and Equity | B35: =+B34+B33+B32 -> 90513 | C35: =+C34+C33+C32 -> 93394 | D35: =+D34+D33+D32 -> 99830 | E35: =+E34+E33+E32 -> 101450 | F35: =+F34+F33+F32 -> 103461 | G35: =+G34+G33+G32 -> 120092
B36: =+B35-B21 -> 0 | C36: =+C35-C21 -> 0 | D36: =+D35-D21 -> 0 | E36: =+E35-E21 -> 0 | F36: =+F35-F21 -> 0 | G36: =+G35-G21 -> 0
A37: Shares issued | B37: 1243 | C37: 1235 | D37: 1228 | E37: 1224 | F37: 1224 | G37: 1221
A38: Treasury Shares | B38: -18 | C38: -11 | D38: -5 | E38: -3 | F38: -4 | G38: -2
A39: Shares Outstanding | B39: =+B37+B38 -> 1225 | C39: =+C37+C38 -> 1224 | D39: =+D37+D38 -> 1223 | E39: =+E37+E38 -> 1221 | F39: =+F37+F38 -> 1220 | G39: =+G37+G38 -> 1219
A40: Stock price at next 2/28 (60 days after FYE) | B40: 38.13 | C40: 39.22 | D40: 36.38 | E40: 24.77 | F40: 33.19 | G40: 67.14
A41: Market Value of Equity | B41: =+B39*B40 -> 46709.25 | C41: =+C39*C40 -> 48005.28 | D41: =+D39*D40 -> 44492.74 | E41: =+E39*E40 -> 30244.17 | F41: =+F39*F40 -> 40491.8 | G41: =+G39*G40 -> 81843.66
A43: =+A1 -> Kraft Heinz Company | B43: Reclassified
A44: Summary Changes in Equity
A45: =+A3 -> in millions except per share data | F45: Late filing | G45: Restated
A46: =+A4 -> Fiscal year ended 12/31: | B46: 2022 | C46: 2021 | D46: 2020 | E46: 2019 | F46: 2018 | G46: 2017 | H46: Aggregate
A47: Net Income - As Reported | B47: =+'As Reported'!B68 -> 2368 | C47: =+'As Reported'!C68 -> 1024 | D47: =+'As Reported'!D68 -> 361 | E47: =+'As Reported'!E68 -> 1933 | F47: =+'As Reported'!F68 -> -10254 | G47: =+'As Reported'!G68 -> 10932 | H47: =SUM(B47:G47) -> 6364
A48: Other comprehensive income | B48: -993 | C48: 149 | D48: -78 | E48: -72 | F48: -903 | G48: 581 | H48: =SUM(B48:G48) -> -1316
A49: Comprehensive Income affecting equity | B49: =SUM(B47:B48) -> 1375 | C49: =SUM(C47:C48) -> 1173 | D49: =SUM(D47:D48) -> 283 | E49: =SUM(E47:E48) -> 1861 | F49: =SUM(F47:F48) -> -11157 | G49: =SUM(G47:G48) -> 11513 | H49: =SUM(B49:G49) -> 5048
A50: Dividends | B50: -1972 | C50: -1979 | D50: -1973 | E50: -1959 | F50: -3048 | G50: -2988 | H50: =SUM(B50:G50) -> -13919
A51: Other activity (squeeze) | B51: =+B52-SUM(B49:B50) -> -21 | C51: =+C52-SUM(C49:C50) -> 11 | D51: =+D52-SUM(D49:D50) -> 184 | E51: =+E52-SUM(E49:E50) -> 72 | F51: =+F52-SUM(F49:F50) -> -90 | G51: =+G52-SUM(G49:G50) -> 85 | H51: =SUM(B51:G51) -> 241
A52: Change in equity | B52: =+B54-B53 -> -618 | C52: =+C54-C53 -> -795 | D52: =+D54-D53 -> -1506 | E52: =+E54-E53 -> -26 | F52: =+F54-F53 -> -14295 | G52: =+G54-G53 -> 8610 | H52: =SUM(B52:G52) -> -8630
A53: Beginning Equity | B53: =+C54 -> 49448 | C53: =+D54 -> 50243 | D53: =+E54 -> 51749 | E53: =+F54 -> 51775 | F53: =+G54 -> 66070 | G53: 57460 | H53: =+G53 -> 57460
A54: Ending Equity | B54: =+B34 -> 48830 | C54: =+C34 -> 49448 | D54: =+D34 -> 50243 | E54: =+E34 -> 51749 | F54: =+F34 -> 51775 | G54: =+G34 -> 66070 | H54: =++H52+H53 -> 48830
A56: =+A1 -> Kraft Heinz Company | B56: =+B1 -> Reclassified
A57: Consolidated Income Statements
A58: =+A3 -> in millions except per share data | F58: Late filing | G58: Restated
A59: =+A4 -> Fiscal year ended 12/31: | B59: 2022 | C59: 2021 | D59: 2020 | E59: 2019 | F59: 2018 | G59: 2017 | H59: Aggregate
A60: Net sales | B60: 26485 | C60: 26042 | D60: 26185 | E60: 24977 | F60: 26268 | G60: 26076 | H60: =SUM(B60:G60) -> 156033
A61: Cost of goods sold | B61: 18363 | C61: 17360 | D61: 17008 | E61: 16830 | F61: 17347 | G61: 17043 | H61: =SUM(B61:G61) -> 103951
A62: Gross profit | B62: =+B60-B61 -> 8122 | C62: =+C60-C61 -> 8682 | D62: =+D60-D61 -> 9177 | E62: =+E60-E61 -> 8147 | F62: =+F60-F61 -> 8921 | G62: =+G60-G61 -> 9033 | H62: =SUM(B62:G62) -> 52082
A63: SG&A (see detail) | B63: =+B316 -> 2503 | C63: =+C316 -> 2409 | D63: =+D316 -> 2461 | E63: =+E316 -> 1966 | F63: =+F316 -> 1941 | G63: =+G316 -> 1719 | H63: =SUM(B63:G63) -> 12999
A64: Advertising & Promotion | B64: =+B251 -> 945 | C64: =+C251 -> 1039 | D64: =+D251 -> 1070 | E64: =+E251 -> 1100 | F64: =+F251 -> 1140 | G64: =+G251 -> 1115 | H64: =SUM(B64:G64) -> 6409
A65: Research & Devlopment | B65: =+B252 -> 127 | C65: =+C252 -> 140 | D65: =+D252 -> 119 | E65: =+E252 -> 112 | F65: =+F252 -> 109 | G65: =+G252 -> 93 | H65: =SUM(B65:G65) -> 700
A66: Goodwill impairment | B66: 444 | C66: 318 | D66: 2343 | E66: 1197 | F66: 7008 | G66: 0 | H66: =SUM(B66:G66) -> 11310
A67: Intangible impairment | B67: 469 | C67: 1316 | D67: 1056 | E67: 702 | F67: 8928 | G67: 49 | H67: =SUM(B67:G67) -> 12520
A68: Operating expenses | B68: =SUM(B63:B67) -> 4488 | C68: =SUM(C63:C67) -> 5222 | D68: =SUM(D63:D67) -> 7049 | E68: =SUM(E63:E67) -> 5077 | F68: =SUM(F63:F67) -> 19126 | G68: =SUM(G63:G67) -> 2976 | H68: =SUM(B68:G68) -> 43938
A69: Operating income (loss) | B69: =+B62-B68 -> 3634 | C69: =+C62-C68 -> 3460 | D69: =+D62-D68 -> 2128 | E69: =+E62-E68 -> 3070 | F69: =+F62-F68 -> -10205 | G69: =+G62-G68 -> 6057 | H69: =SUM(B69:G69) -> 8144
A70: Interest expense | B70: 921 | C70: 2047 | D70: 1394 | E70: 1361 | F70: 1284 | G70: 1234 | H70: =SUM(B70:G70) -> 8241
A71: Other expense (income) | B71: -253 | C71: -295 | D71: -296 | E71: -952 | F71: -168 | G71: -627 | H71: =SUM(B71:G71) -> -2591
A72: Pretax Income | B72: =+B69-B70-B71 -> 2966 | C72: =+C69-C70-C71 -> 1708 | D72: =+D69-D70-D71 -> 1030 | E72: =+E69-E70-E71 -> 2661 | F72: =+F69-F70-F71 -> -11321 | G72: =+G69-G70-G71 -> 5450 | H72: =SUM(B72:G72) -> 2494
A73: Tax provision | B73: 598 | C73: 684 | D73: 669 | E73: 728 | F73: -1067 | G73: -5482 | H73: =SUM(B73:G73) -> -3870
A74: Net Income (loss) | B74: =+B72-B73 -> 2368 | C74: =+C72-C73 -> 1024 | D74: =+D72-D73 -> 361 | E74: =+E72-E73 -> 1933 | F74: =+F72-F73 -> -10254 | G74: =+G72-G73 -> 10932 | H74: =SUM(B74:G74) -> 6364
A75: Noncontrolling interest | B75: 5 | C75: 12 | D75: 5 | E75: -2 | F75: -62 | G75: -9 | H75: =SUM(B75:G75) -> -51
A76: Net income (Loss)-Kraft Heinz | B76: =+B74-B75 -> 2363 | C76: =+C74-C75 -> 1012 | D76: =+D74-D75 -> 356 | E76: =+E74-E75 -> 1935 | F76: =+F74-F75 -> -10192 | G76: =+G74-G75 -> 10941 | H76: =SUM(B76:G76) -> 6415
B77: =+B76-'As Reported'!B70 -> 0 | C77: =+C76-'As Reported'!C70 -> 0 | D77: =+D76-'As Reported'!D70 -> 0 | E77: =+E76-'As Reported'!E70 -> 0 | F77: =+F76-'As Reported'!F70 -> 0 | G77: =+G76-'As Reported'!G70 -> 0
A78: Diluted W. Ave shares outstanding (notes) | B78: 1235 | C78: 1236 | D78: 1228 | E78: 1224 | F78: 1219 | G78: 1228
A79: Diluted EPS | B79: =+B76/B78 -> 1.9133603 | C79: =+C76/C78 -> 0.81877023 | D79: =+D76/D78 -> 0.28990228 | E79: =+E76/E78 -> 1.5808824 | F79: =+F76/F78 -> -8.3609516 | G79: =+G76/G78 -> 8.9096091
A80: Dividends per share (Equity Stmt)) | B80: 1.6 | C80: 1.6 | D80: 1.6 | E80: 1.6 | F80: 2.5 | G80: 2.45
A82: Effective Tax Rate | B82: =+B73/B72 -> 0.20161834 | C82: =+C73/C72 -> 0.40046838 | D82: =+D73/D72 -> 0.64951456 | E82: =+E73/E72 -> 0.27358136 | F82: =+F73/F72 -> 0.094249625 | G82: =+G73/G72 -> -1.0058716 | H82: =+H73/H72 -> -1.5517241
A84: Non-GAAP Measurements:
A85: Net Income | B85: =+B76 -> 2363 | C85: =+C76 -> 1012 | D85: =+D76 -> 356 | E85: =+E76 -> 1935 | F85: =+F76 -> -10192 | G85: =+G76 -> 10941
A86: Add back Income Taxes | B86: =+B73 -> 598 | C86: =+C73 -> 684 | D86: =+D73 -> 669 | E86: =+E73 -> 728 | F86: =+F73 -> -1067 | G86: =+G73 -> -5482
A87: Add back Interest Expense | B87: =+B70 -> 921 | C87: =+C70 -> 2047 | D87: =+D70 -> 1394 | E87: =+E70 -> 1361 | F87: =+F70 -> 1284 | G87: =+G70 -> 1234
A88: EBIT | B88: =SUM(B85:B87) -> 3882 | C88: =SUM(C85:C87) -> 3743 | D88: =SUM(D85:D87) -> 2419 | E88: =SUM(E85:E87) -> 4024 | F88: =SUM(F85:F87) -> -9975 | G88: =SUM(G85:G87) -> 6693
A89: Depreciation and amortization | B89: =+B102 -> 933 | C89: =+C102 -> 910 | D89: =+D102 -> 969 | E89: =+E102 -> 994 | F89: =+F102 -> 983 | G89: =+G102 -> 1031
A90: EBITDA | B90: =+B89+B88 -> 4815 | C90: =+C89+C88 -> 4653 | D90: =+D89+D88 -> 3388 | E90: =+E89+E88 -> 5018 | F90: =+F89+F88 -> -8992 | G90: =+G89+G88 -> 7724
A92: Operating Income | B92: =+B69 -> 3634 | C92: =+C69 -> 3460 | D92: =+D69 -> 2128 | E92: =+E69 -> 3070 | F92: =+F69 -> -10205 | G92: =+G69 -> 6057
A93: Other Income | B93: =-B71 -> 253 | C93: =-C71 -> 295 | D93: =-D71 -> 296 | E93: =-E71 -> 952 | F93: =-F71 -> 168 | G93: =-G71 -> 627
A94: Noncontrolling interest | B94: =-B75 -> -5 | C94: =-C75 -> -12 | D94: =-D75 -> -5 | E94: =-E75 -> 2 | F94: =-F75 -> 62 | G94: =-G75 -> 9
A95: EBIT | B95: =+SUM(B92:B94) -> 3882 | C95: =+SUM(C92:C94) -> 3743 | D95: =+SUM(D92:D94) -> 2419 | E95: =+SUM(E92:E94) -> 4024 | F95: =+SUM(F92:F94) -> -9975 | G95: =+SUM(G92:G94) -> 6693
A97: =+A1 -> Kraft Heinz Company | B97: =+B1 -> Reclassified
A98: Consolidated Cash Flows
A99: =+A3 -> in millions except per share data | F99: Late filing | G99: Restated
A100: =+A4 -> Fiscal year ended 12/31: | B100: 2022 | C100: 2021 | D100: 2020 | E100: 2019 | F100: 2018 | G100: 2017 | H100: Aggregate
A101: Net income (loss) - as reported | B101: =+'As Reported'!B68 -> 2368 | C101: =+'As Reported'!C68 -> 1024 | D101: =+'As Reported'!D68 -> 361 | E101: =+'As Reported'!E68 -> 1933 | F101: =+'As Reported'!F68 -> -10254 | G101: =+'As Reported'!G68 -> 10932 | H101: =SUM(B101:G101) -> 6364
A102: Depreciation & amortization | B102: 933 | C102: 910 | D102: 969 | E102: 994 | F102: 983 | G102: 1031 | H102: =SUM(B102:G102) -> 5820
A103: Amortization of PRB | B103: -14 | C103: -7 | D103: -122 | E103: -306 | F103: -339 | G103: -328 | H103: =SUM(B103:G103) -> -1116
A104: Divestiture-related license income | B104: -56 | C104: -4 | D104: 0 | E104: 0 | F104: 0 | G104: 0 | H104: =SUM(B104:G104) -> -60
A105: Stock-based compensation | B105: 148 | C105: 197 | D105: 156 | E105: 46 | F105: 33 | G105: 46 | H105: =SUM(B105:G105) -> 626
A106: Deferred income taxes | B106: -278 | C106: -1042 | D106: -343 | E106: -293 | F106: -1967 | G106: -6495 | H106: =SUM(B106:G106) -> -10418
...

Sheet Cap. Structure
A1: Kraft Heinz Company | B1: Reclassified
A2: Consolidated Balance Sheets
A3: in millions except per share data | F3: Late filing | G3: Restated
A4: Fiscal year ended 12/31: | B4: 2022 | C4: 2021 | D4: 2020 | E4: 2019 | F4: 2018 | G4: 2017
A5: Assets:
A6: Cash and equivalents | B6: 1040 | C6: 3445 | D6: 3417 | E6: 2279 | F6: 1130 | G6: 1629
A7: Marketable Securities | B7: 0 | C7: 0 | D7: 0 | E7: 0 | F7: 0 | G7: 0
A8: Trade receivables | B8: 2120 | C8: 1957 | D8: 2063 | E8: 1973 | F8: 2129 | G8: 921
A9: Inventories | B9: 3651 | C9: 2729 | D9: 2554 | E9: 2721 | F9: 2667 | G9: 2760
A10: Other current assets | B10: =+B313 -> 1086 | C10: =+C313 -> 863 | D10: =+D313 -> 2788 | E10: =+E313 -> 1124 | F10: =+F313 -> 3149 | G10: =+G313 -> 1891
A11: Total current assets | B11: =SUM(B6:B10) -> 7897 | C11: =SUM(C6:C10) -> 8994 | D11: =SUM(D6:D10) -> 10822 | E11: =SUM(E6:E10) -> 8097 | F11: =SUM(F6:F10) -> 9075 | G11: =SUM(G6:G10) -> 7201
A12: Land | B12: =+B291 -> 200 | C12: =+C291 -> 207 | D12: =+D291 -> 219 | E12: =+E291 -> 210 | F12: =+F291 -> 218 | G12: =+G291 -> 250
A13: Construction in progress | B13: =+B292 -> 1161 | C13: =+C292 -> 1002 | D13: =+D292 -> 792 | E13: =+E292 -> 1033 | F13: =+F292 -> 1165 | G13: =+G292 -> 1345
A14: Depreciable assets | B14: =+B293 -> 51681 | C14: =+C293 -> 52107 | D14: =+D293 -> 52795 | E14: =+E293 -> 53693 | F14: =+F293 -> 52976 | G14: =+G293 -> 66564
A15: PP&E - at cost | B15: =+B294 -> 53042 | C15: =+C294 -> 53316 | D15: =+D294 -> 53806 | E15: =+E294 -> 54936 | F15: =+F294 -> 54359 | G15: =+G294 -> 68159
A16: Accumulated depreciation | B16: =+B295 -> -4212 | C16: =+C295 -> -3868 | D16: =+D295 -> -3563 | E16: =+E295 -> -3187 | F16: =+F295 -> -2584 | G16: =+G295 -> -2089
A17: Property, plant & equipment - net | B17: 6740 | C17: 6806 | D17: 6876 | E17: 7055 | F17: 7078 | G17: 7061
A18: Right of Use assets | B18: =+B300 -> 668 | C18: =+C300 -> 569 | D18: =+D300 -> 562 | E18: =+E300 -> 542 | F18: =+F300 -> 0 | G18: =+G300 -> 0
A19: Goodwill and Intangibles (see detail) | B19: =+B317 -> 73482 | C19: =+C317 -> 74838 | D19: =+D317 -> 79756 | E19: =+E317 -> 84198 | F19: =+F317 -> 85971 | G19: =+G317 -> 104257
A20: Other assets | B20: =+B321 -> 1726 | C20: =+C321 -> 2187 | D20: =+D321 -> 1814 | E20: =+E321 -> 1558 | F20: =+F321 -> 1337 | G20: =+G321 -> 1573
A21: Total Assets | B21: =+B11+SUM(B17:B20) -> 90513 | C21: =+C11+SUM(C17:C20) -> 93394 | D21: =+D11+SUM(D17:D20) -> 99830 | E21: =+E11+SUM(E17:E20) -> 101450 | F21: =+F11+SUM(F17:F20) -> 103461 | G21: =+G11+SUM(G17:G20) -> 120092
A22: Liabilities and Equity
A23: Current Debt (see detail) | B23: =+B325 -> 837 | C23: =+C325 -> 754 | D23: =+D325 -> 236 | E23: =+E325 -> 1028 | F23: =+F325 -> 398 | G23: =+G325 -> 3195
A24: Trade payables | B24: 4848 | C24: 4753 | D24: 4304 | E24: 4003 | F24: 4153 | G24: 4362
A25: Deferred revenue | B25: 0 | C25: 0 | D25: 0 | E25: 0 | F25: 0 | G25: 0
A26: Current portion of operating lease liabilities | B26: =+B301 -> 125 | C26: =+C301 -> 133 | D26: =+D301 -> 135 | E26: =+E301 -> 147 | F26: =+F301 -> 0 | G26: =+G301 -> 0
A27: Other current liabilities (see detail) | B27: =+B333 -> 3218 | C27: =+C333 -> 3424 | D27: =+D333 -> 3386 | E27: =+E333 -> 2697 | F27: =+F333 -> 2952 | G27: =+G333 -> 2597
A28: Total current liabilities | B28: =SUM(B23:B27) -> 9028 | C28: =SUM(C23:C27) -> 9064 | D28: =SUM(D23:D27) -> 8061 | E28: =SUM(E23:E27) -> 7875 | F28: =SUM(F23:F27) -> 7503 | G28: =SUM(G23:G27) -> 10154
A29: Long-term debt | B29: 19233 | C29: 21061 | D29: 28070 | E29: 28216 | F29: 30770 | G29: 28308
A30: LT operating lease liabilities | B30: =+B302 -> 585 | C30: =+C302 -> 484 | D30: =+D302 -> 475 | E30: =+E302 -> 454 | F30: =+F302 -> 0 | G30: =+G302 -> 0
A31: Other non-current liabilities (see detail) | B31: =+B340 -> 12797 | C31: =+C340 -> 13333 | D31: =+D340 -> 12981 | E31: =+E340 -> 13156 | F31: =+F340 -> 13410 | G31: =+G340 -> 15554
A32: Total liabilities | B32: =SUM(B28:B31) -> 41643 | C32: =SUM(C28:C31) -> 43942 | D32: =SUM(D28:D31) -> 49587 | E32: =SUM(E28:E31) -> 49701 | F32: =SUM(F28:F31) -> 51683 | G32: =SUM(G28:G31) -> 54016
A33: Redeemable Non-controlling interest | B33: 40 | C33: 4 | D33: 0 | E33: 0 | F33: 3 | G33: 6
A34: Total Equity | B34: =+B348 -> 48830 | C34: =+C348 -> 49448 | D34: =+D348 -> 50243 | E34: =+E348 -> 51749 | F34: =+F348 -> 51775 | G34: =+G348 -> 66070
A35: Total Liabilities and Equity | B35: =+B34+B33+B32 -> 90513 | C35: =+C34+C33+C32 -> 93394 | D35: =+D34+D33+D32 -> 99830 | E35: =+E34+E33+E32 -> 101450 | F35: =+F34+F33+F32 -> 103461 | G35: =+G34+G33+G32 -> 120092
B36: =+B35-B21 -> 0 | C36: =+C35-C21 -> 0 | D36: =+D35-D21 -> 0 | E36: =+E35-E21 -> 0 | F36: =+F35-F21 -> 0 | G36: =+G35-G21 -> 0
A37: Shares issued | B37: 1243 | C37: 1235 | D37: 1228 | E37: 1224 | F37: 1224 | G37: 1221
A38: Treasury Shares | B38: -18 | C38: -11 | D38: -5 | E38: -3 | F38: -4 | G38: -2
A39: Shares Outstanding | B39: =+B37+B38 -> 1225 | C39: =+C37+C38 -> 1224 | D39: =+D37+D38 -> 1223 | E39: =+E37+E38 -> 1221 | F39: =+F37+F38 -> 1220 | G39: =+G37+G38 -> 1219
A40: Stock price at next 2/28 (60 days after FYE) | B40: 38.13 | C40: 39.22 | D40: 36.38 | E40: 24.77 | F40: 33.19 | G40: 67.14
A41: Market Value of Equity | B41: =+B39*B40 -> 46709.25 | C41: =+C39*C40 -> 48005.28 | D41: =+D39*D40 -> 44492.74 | E41: =+E39*E40 -> 30244.17 | F41: =+F39*F40 -> 40491.8 | G41: =+G39*G40 -> 81843.66
A43: =+A1 -> Kraft Heinz Company | B43: Reclassified
A44: Summary Changes in Equity
A45: =+A3 -> in millions except per share data | F45: Late filing | G45: Restated
A46: =+A4 -> Fiscal year ended 12/31: | B46: 2022 | C46: 2021 | D46: 2020 | E46: 2019 | F46: 2018 | G46: 2017 | H46: Aggregate
A47: Net Income - As Reported | B47: =+'As Reported'!B68 -> 2368 | C47: =+'As Reported'!C68 -> 1024 | D47: =+'As Reported'!D68 -> 361 | E47: =+'As Reported'!E68 -> 1933 | F47: =+'As Reported'!F68 -> -10254 | G47: =+'As Reported'!G68 -> 10932 | H47: =SUM(B47:G47) -> 6364
A48: Other comprehensive income | B48: -993 | C48: 149 | D48: -78 | E48: -72 | F48: -903 | G48: 581 | H48: =SUM(B48:G48) -> -1316
A49: Comprehensive Income affecting equity | B49: =SUM(B47:B48) -> 1375 | C49: =SUM(C47:C48) -> 1173 | D49: =SUM(D47:D48) -> 283 | E49: =SUM(E47:E48) -> 1861 | F49: =SUM(F47:F48) -> -11157 | G49: =SUM(G47:G48) -> 11513 | H49: =SUM(B49:G49) -> 5048
A50: Dividends | B50: -1972 | C50: -1979 | D50: -1973 | E50: -1959 | F50: -3048 | G50: -2988 | H50: =SUM(B50:G50) -> -13919
A51: Other activity (squeeze) | B51: =+B52-SUM(B49:B50) -> -21 | C51: =+C52-SUM(C49:C50) -> 11 | D51: =+D52-SUM(D49:D50) -> 184 | E51: =+E52-SUM(E49:E50) -> 72 | F51: =+F52-SUM(F49:F50) -> -90 | G51: =+G52-SUM(G49:G50) -> 85 | H51: =SUM(B51:G51) -> 241
A52: Change in equity | B52: =+B54-B53 -> -618 | C52: =+C54-C53 -> -795 | D52: =+D54-D53 -> -1506 | E52: =+E54-E53 -> -26 | F52: =+F54-F53 -> -14295 | G52: =+G54-G53 -> 8610 | H52: =SUM(B52:G52) -> -8630
A53: Beginning Equity | B53: =+C54 -> 49448 | C53: =+D54 -> 50243 | D53: =+E54 -> 51749 | E53: =+F54 -> 51775 | F53: =+G54 -> 66070 | G53: 57460 | H53: =+G53 -> 57460
A54: Ending Equity | B54: =+B34 -> 48830 | C54: =+C34 -> 49448 | D54: =+D34 -> 50243 | E54: =+E34 -> 51749 | F54: =+F34 -> 51775 | G54: =+G34 -> 66070 | H54: =++H52+H53 -> 48830
A56: =+A1 -> Kraft Heinz Company | B56: =+B1 -> Reclassified
A57: Consolidated Income Statements
A58: =+A3 -> in millions except per share data | F58: Late filing | G58: Restated
A59: =+A4 -> Fiscal year ended 12/31: | B59: 2022 | C59: 2021 | D59: 2020 | E59: 2019 | F59: 2018 | G59: 2017 | H59: Aggregate
A60: Net sales | B60: 26485 | C60: 26042 | D60: 26185 | E60: 24977 | F60: 26268 | G60: 26076 | H60: =SUM(B60:G60) -> 156033
A61: Cost of goods sold | B61: 18363 | C61: 17360 | D61: 17008 | E61: 16830 | F61: 17347 | G61: 17043 | H61: =SUM(B61:G61) -> 103951
A62: Gross profit | B62: =+B60-B61 -> 8122 | C62: =+C60-C61 -> 8682 | D62: =+D60-D61 -> 9177 | E62: =+E60-E61 -> 8147 | F62: =+F60-F61 -> 8921 | G62: =+G60-G61 -> 9033 | H62: =SUM(B62:G62) -> 52082
A63: SG&A (see detail) | B63: =+B353 -> 2503 | C63: =+C353 -> 2409 | D63: =+D353 -> 2461 | E63: =+E353 -> 1966 | F63: =+F353 -> 1941 | G63: =+G353 -> 1719 | H63: =SUM(B63:G63) -> 12999
A64: Advertising & Promotion | B64: =+B288 -> 945 | C64: =+C288 -> 1039 | D64: =+D288 -> 1070 | E64: =+E288 -> 1100 | F64: =+F288 -> 1140 | G64: =+G288 -> 1115 | H64: =SUM(B64:G64) -> 6409
A65: Research & Devlopment | B65: =+B289 -> 127 | C65: =+C289 -> 140 | D65: =+D289 -> 119 | E65: =+E289 -> 112 | F65: =+F289 -> 109 | G65: =+G289 -> 93 | H65: =SUM(B65:G65) -> 700
A66: Goodwill impairment | B66: 444 | C66: 318 | D66: 2343 | E66: 1197 | F66: 7008 | G66: 0 | H66: =SUM(B66:G66) -> 11310
A67: Intangible impairment | B67: 469 | C67: 1316 | D67: 1056 | E67: 702 | F67: 8928 | G67: 49 | H67: =SUM(B67:G67) -> 12520
A68: Operating expenses | B68: =SUM(B63:B67) -> 4488 | C68: =SUM(C63:C67) -> 5222 | D68: =SUM(D63:D67) -> 7049 | E68: =SUM(E63:E67) -> 5077 | F68: =SUM(F63:F67) -> 19126 | G68: =SUM(G63:G67) -> 2976 | H68: =SUM(B68:G68) -> 43938
A69: Operating income (loss) | B69: =+B62-B68 -> 3634 | C69: =+C62-C68 -> 3460 | D69: =+D62-D68 -> 2128 | E69: =+E62-E68 -> 3070 | F69: =+F62-F68 -> -10205 | G69: =+G62-G68 -> 6057 | H69: =SUM(B69:G69) -> 8144
A70: Interest expense | B70: 921 | C70: 2047 | D70: 1394 | E70: 1361 | F70: 1284 | G70: 1234 | H70: =SUM(B70:G70) -> 8241
A71: Other expense (income) | B71: -253 | C71: -295 | D71: -296 | E71: -952 | F71: -168 | G71: -627 | H71: =SUM(B71:G71) -> -2591
A72: Pretax Income | B72: =+B69-B70-B71 -> 2966 | C72: =+C69-C70-C71 -> 1708 | D72: =+D69-D70-D71 -> 1030 | E72: =+E69-E70-E71 -> 2661 | F72: =+F69-F70-F71 -> -11321 | G72: =+G69-G70-G71 -> 5450 | H72: =SUM(B72:G72) -> 2494
A73: Tax provision | B73: 598 | C73: 684 | D73: 669 | E73: 728 | F73: -1067 | G73: -5482 | H73: =SUM(B73:G73) -> -3870
A74: Net Income (loss) | B74: =+B72-B73 -> 2368 | C74: =+C72-C73 -> 1024 | D74: =+D72-D73 -> 361 | E74: =+E72-E73 -> 1933 | F74: =+F72-F73 -> -10254 | G74: =+G72-G73 -> 10932 | H74: =SUM(B74:G74) -> 6364
A75: Noncontrolling interest | B75: 5 | C75: 12 | D75: 5 | E75: -2 | F75: -62 | G75: -9 | H75: =SUM(B75:G75) -> -51
A76: Net income (Loss)-Kraft Heinz | B76: =+B74-B75 -> 2363 | C76: =+C74-C75 -> 1012 | D76: =+D74-D75 -> 356 | E76: =+E74-E75 -> 1935 | F76: =+F74-F75 -> -10192 | G76: =+G74-G75 -> 10941 | H76: =SUM(B76:G76) -> 6415
B77: =+B76-'As Reported'!B70 -> 0 | C77: =+C76-'As Reported'!C70 -> 0 | D77: =+D76-'As Reported'!D70 -> 0 | E77: =+E76-'As Reported'!E70 -> 0 | F77: =+F76-'As Reported'!F70 -> 0 | G77: =+G76-'As Reported'!G70 -> 0
A78: Diluted W. Ave shares outstanding (notes) | B78: 1235 | C78: 1236 | D78: 1228 | E78: 1224 | F78: 1219 | G78: 1228
A79: Diluted EPS | B79: =+B76/B78 -> 1.9133603 | C79: =+C76/C78 -> 0.81877023 | D79: =+D76/D78 -> 0.28990228 | E79: =+E76/E78 -> 1.5808824 | F79: =+F76/F78 -> -8.3609516 | G79: =+G76/G78 -> 8.9096091
A80: Dividends per share (Equity Stmt)) | B80: 1.6 | C80: 1.6 | D80: 1.6 | E80: 1.6 | F80: 2.5 | G80: 2.45
A82: Effective Tax Rate | B82: =+B73/B72 -> 0.20161834 | C82: =+C73/C72 -> 0.40046838 | D82: =+D73/D72 -> 0.64951456 | E82: =+E73/E72 -> 0.27358136 | F82: =+F73/F72 -> 0.094249625 | G82: =+G73/G72 -> -1.0058716 | H82: =+H73/H72 -> -1.5517241
A84: Non-GAAP Measurements:
A85: Net Income | B85: =+B76 -> 2363 | C85: =+C76 -> 1012 | D85: =+D76 -> 356 | E85: =+E76 -> 1935 | F85: =+F76 -> -10192 | G85: =+G76 -> 10941
A86: Add back Income Taxes | B86: =+B73 -> 598 | C86: =+C73 -> 684 | D86: =+D73 -> 669 | E86: =+E73 -> 728 | F86: =+F73 -> -1067 | G86: =+G73 -> -5482
A87: Add back Interest Expense | B87: =+B70 -> 921 | C87: =+C70 -> 2047 | D87: =+D70 -> 1394 | E87: =+E70 -> 1361 | F87: =+F70 -> 1284 | G87: =+G70 -> 1234
A88: EBIT | B88: =SUM(B85:B87) -> 3882 | C88: =SUM(C85:C87) -> 3743 | D88: =SUM(D85:D87) -> 2419 | E88: =SUM(E85:E87) -> 4024 | F88: =SUM(F85:F87) -> -9975 | G88: =SUM(G85:G87) -> 6693
A89: Depreciation and amortization | B89: =+B102 -> 933 | C89: =+C102 -> 910 | D89: =+D102 -> 969 | E89: =+E102 -> 994 | F89: =+F102 -> 983 | G89: =+G102 -> 1031
A90: EBITDA | B90: =+B89+B88 -> 4815 | C90: =+C89+C88 -> 4653 | D90: =+D89+D88 -> 3388 | E90: =+E89+E88 -> 5018 | F90: =+F89+F88 -> -8992 | G90: =+G89+G88 -> 7724
A92: Operating Income | B92: =+B69 -> 3634 | C92: =+C69 -> 3460 | D92: =+D69 -> 2128 | E92: =+E69 -> 3070 | F92: =+F69 -> -10205 | G92: =+G69 -> 6057
A93: Other Income | B93: =-B71 -> 253 | C93: =-C71 -> 295 | D93: =-D71 -> 296 | E93: =-E71 -> 952 | F93: =-F71 -> 168 | G93: =-G71 -> 627
A94: Noncontrolling interest | B94: =-B75 -> -5 | C94: =-C75 -> -12 | D94: =-D75 -> -5 | E94: =-E75 -> 2 | F94: =-F75 -> 62 | G94: =-G75 -> 9
A95: EBIT | B95: =+SUM(B92:B94) -> 3882 | C95: =+SUM(C92:C94) -> 3743 | D95: =+SUM(D92:D94) -> 2419 | E95: =+SUM(E92:E94) -> 4024 | F95: =+SUM(F92:F94) -> -9975 | G95: =+SUM(G92:G94) -> 6693
A97: =+A1 -> Kraft Heinz Company | B97: =+B1 -> Reclassified
A98: Consolidated Cash Flows
A99: =+A3 -> in millions except per share data | F99: Late filing | G99: Restated
A100: =+A4 -> Fiscal year ended 12/31: | B100: 2022 | C100: 2021 | D100: 2020 | E100: 2019 | F100: 2018 | G100: 2017 | H100: Aggregate
A101: Net income (loss) - as reported | B101: =+'As Reported'!B68 -> 2368 | C101: =+'As Reported'!C68 -> 1024 | D101: =+'As Reported'!D68 -> 361 | E101: =+'As Reported'!E68 -> 1933 | F101: =+'As Reported'!F68 -> -10254 | G101: =+'As Reported'!G68 -> 10932 | H101: =SUM(B101:G101) -> 6364
A102: Depreciation & amortization | B102: 933 | C102: 910 | D102: 969 | E102: 994 | F102: 983 | G102: 1031 | H102: =SUM(B102:G102) -> 5820
A103: Amortization of PRB | B103: -14 | C103: -7 | D103: -122 | E103: -306 | F103: -339 | G103: -328 | H103: =SUM(B103:G103) -> -1116
A104: Divestiture-related license income | B104: -56 | C104: -4 | D104: 0 | E104: 0 | F104: 0 | G104: 0 | H104: =SUM(B104:G104) -> -60
A105: Stock-based compensation | B105: 148 | C105: 197 | D105: 156 | E105: 46 | F105: 33 | G105: 46 | H105: =SUM(B105:G105) -> 626
A106: Deferred income taxes | B106: -278 | C106: -1042 | D106: -343 | E106: -293 | F106: -1967 | G106: -6495 | H106: =SUM(B106:G106) -> -10418
...

Sheet Profitability
A1: Kraft Heinz Company | B1: Reclassified
A2: Consolidated Balance Sheets
A3: in millions except per share data | F3: Late filing | G3: Restated
A4: Year ended near 12/31: | B4: 2022 | C4: 2021 | D4: 2020 | E4: 2019 | F4: 2018 | G4: 2017
A5: Assets:
A6: Cash and equivalents | B6: 1040 | C6: 3445 | D6: 3417 | E6: 2279 | F6: 1130 | G6: 1629
A7: Marketable Securities | B7: 0 | C7: 0 | D7: 0 | E7: 0 | F7: 0 | G7: 0
A8: Trade receivables | B8: 2120 | C8: 1957 | D8: 2063 | E8: 1973 | F8: 2129 | G8: 921
A9: Inventories | B9: 3651 | C9: 2729 | D9: 2554 | E9: 2721 | F9: 2667 | G9: 2760
A10: Other current assets | B10: =+B392 -> 1086 | C10: =+C392 -> 863 | D10: =+D392 -> 2788 | E10: =+E392 -> 1124 | F10: =+F392 -> 3149 | G10: =+G392 -> 1891
A11: Total current assets | B11: =SUM(B6:B10) -> 7897 | C11: =SUM(C6:C10) -> 8994 | D11: =SUM(D6:D10) -> 10822 | E11: =SUM(E6:E10) -> 8097 | F11: =SUM(F6:F10) -> 9075 | G11: =SUM(G6:G10) -> 7201
A12: Land | B12: =+B370 -> 200 | C12: =+C370 -> 207 | D12: =+D370 -> 219 | E12: =+E370 -> 210 | F12: =+F370 -> 218 | G12: =+G370 -> 250
A13: Construction in progress | B13: =+B371 -> 1161 | C13: =+C371 -> 1002 | D13: =+D371 -> 792 | E13: =+E371 -> 1033 | F13: =+F371 -> 1165 | G13: =+G371 -> 1345
A14: Depreciable assets | B14: =+B372 -> 51681 | C14: =+C372 -> 52107 | D14: =+D372 -> 52795 | E14: =+E372 -> 53693 | F14: =+F372 -> 52976 | G14: =+G372 -> 66564
A15: PP&E - at cost | B15: =+B373 -> 53042 | C15: =+C373 -> 53316 | D15: =+D373 -> 53806 | E15: =+E373 -> 54936 | F15: =+F373 -> 54359 | G15: =+G373 -> 68159
A16: Accumulated depreciation | B16: =+B374 -> -4212 | C16: =+C374 -> -3868 | D16: =+D374 -> -3563 | E16: =+E374 -> -3187 | F16: =+F374 -> -2584 | G16: =+G374 -> -2089
A17: Property, plant & equipment - net | B17: 6740 | C17: 6806 | D17: 6876 | E17: 7055 | F17: 7078 | G17: 7061
A18: Right of Use assets | B18: =+B379 -> 668 | C18: =+C379 -> 569 | D18: =+D379 -> 562 | E18: =+E379 -> 542 | F18: =+F379 -> 0 | G18: =+G379 -> 0
A19: Goodwill and Intangibles (see detail) | B19: =+B396 -> 73482 | C19: =+C396 -> 74838 | D19: =+D396 -> 79756 | E19: =+E396 -> 84198 | F19: =+F396 -> 85971 | G19: =+G396 -> 104257
A20: Other assets | B20: =+B400 -> 1726 | C20: =+C400 -> 2187 | D20: =+D400 -> 1814 | E20: =+E400 -> 1558 | F20: =+F400 -> 1337 | G20: =+G400 -> 1573
A21: Total Assets | B21: =+B11+SUM(B17:B20) -> 90513 | C21: =+C11+SUM(C17:C20) -> 93394 | D21: =+D11+SUM(D17:D20) -> 99830 | E21: =+E11+SUM(E17:E20) -> 101450 | F21: =+F11+SUM(F17:F20) -> 103461 | G21: =+G11+SUM(G17:G20) -> 120092
A22: Liabilities and Equity
A23: Current Debt (see detail) | B23: =+B404 -> 837 | C23: =+C404 -> 754 | D23: =+D404 -> 236 | E23: =+E404 -> 1028 | F23: =+F404 -> 398 | G23: =+G404 -> 3195
A24: Trade payables | B24: 4848 | C24: 4753 | D24: 4304 | E24: 4003 | F24: 4153 | G24: 4362
A25: Deferred revenue | B25: 0 | C25: 0 | D25: 0 | E25: 0 | F25: 0 | G25: 0
A26: Current portion of operating lease liabilities | B26: =+B380 -> 125 | C26: =+C380 -> 133 | D26: =+D380 -> 135 | E26: =+E380 -> 147 | F26: =+F380 -> 0 | G26: =+G380 -> 0
A27: Other current liabilities (see detail) | B27: =+B412 -> 3218 | C27: =+C412 -> 3424 | D27: =+D412 -> 3386 | E27: =+E412 -> 2697 | F27: =+F412 -> 2952 | G27: =+G412 -> 2597
A28: Total current liabilities | B28: =SUM(B23:B27) -> 9028 | C28: =SUM(C23:C27) -> 9064 | D28: =SUM(D23:D27) -> 8061 | E28: =SUM(E23:E27) -> 7875 | F28: =SUM(F23:F27) -> 7503 | G28: =SUM(G23:G27) -> 10154
A29: Long-term debt | B29: 19233 | C29: 21061 | D29: 28070 | E29: 28216 | F29: 30770 | G29: 28308
A30: LT operating lease liabilities | B30: =+B381 -> 585 | C30: =+C381 -> 484 | D30: =+D381 -> 475 | E30: =+E381 -> 454 | F30: =+F381 -> 0 | G30: =+G381 -> 0
A31: Other non-current liabilities (see detail) | B31: =+B419 -> 12797 | C31: =+C419 -> 13333 | D31: =+D419 -> 12981 | E31: =+E419 -> 13156 | F31: =+F419 -> 13410 | G31: =+G419 -> 15554
A32: Total liabilities | B32: =SUM(B28:B31) -> 41643 | C32: =SUM(C28:C31) -> 43942 | D32: =SUM(D28:D31) -> 49587 | E32: =SUM(E28:E31) -> 49701 | F32: =SUM(F28:F31) -> 51683 | G32: =SUM(G28:G31) -> 54016
A33: Redeemable Non-controlling interest | B33: 40 | C33: 4 | D33: 0 | E33: 0 | F33: 3 | G33: 6
A34: Total Equity | B34: =+B427 -> 48830 | C34: =+C427 -> 49448 | D34: =+D427 -> 50243 | E34: =+E427 -> 51749 | F34: =+F427 -> 51775 | G34: =+G427 -> 66070
A35: Total Liabilities and Equity | B35: =+B34+B33+B32 -> 90513 | C35: =+C34+C33+C32 -> 93394 | D35: =+D34+D33+D32 -> 99830 | E35: =+E34+E33+E32 -> 101450 | F35: =+F34+F33+F32 -> 103461 | G35: =+G34+G33+G32 -> 120092
B36: =+B35-B21 -> 0 | C36: =+C35-C21 -> 0 | D36: =+D35-D21 -> 0 | E36: =+E35-E21 -> 0 | F36: =+F35-F21 -> 0 | G36: =+G35-G21 -> 0
A37: Shares issued | B37: 1243 | C37: 1235 | D37: 1228 | E37: 1224 | F37: 1224 | G37: 1221
A38: Treasury Shares | B38: -18 | C38: -11 | D38: -5 | E38: -3 | F38: -4 | G38: -2
A39: Shares Outstanding | B39: =+B37+B38 -> 1225 | C39: =+C37+C38 -> 1224 | D39: =+D37+D38 -> 1223 | E39: =+E37+E38 -> 1221 | F39: =+F37+F38 -> 1220 | G39: =+G37+G38 -> 1219
A40: Stock price at next 2/28 (60 days after FYE) | B40: 38.13 | C40: 39.22 | D40: 36.38 | E40: 24.77 | F40: 33.19 | G40: 67.14 | H40: =RATE(5,0,-G40,B40) -> -0.10698841
A41: Market Value of Equity | B41: =+B39*B40 -> 46709.25 | C41: =+C39*C40 -> 48005.28 | D41: =+D39*D40 -> 44492.74 | E41: =+E39*E40 -> 30244.17 | F41: =+F39*F40 -> 40491.8 | G41: =+G39*G40 -> 81843.66
A43: =+A1 -> Kraft Heinz Company | B43: Reclassified
A44: Summary Changes in Equity
A45: =+A3 -> in millions except per share data | F45: Late filing | G45: Restated
A46: =+A4 -> Year ended near 12/31: | B46: 2022 | C46: 2021 | D46: 2020 | E46: 2019 | F46: 2018 | G46: 2017 | H46: Aggregate
A47: Net Income - As Reported | B47: =+'As Reported'!B68 -> 2368 | C47: =+'As Reported'!C68 -> 1024 | D47: =+'As Reported'!D68 -> 361 | E47: =+'As Reported'!E68 -> 1933 | F47: =+'As Reported'!F68 -> -10254 | G47: =+'As Reported'!G68 -> 10932 | H47: =SUM(B47:G47) -> 6364
A48: Other comprehensive income | B48: -993 | C48: 149 | D48: -78 | E48: -72 | F48: -903 | G48: 581 | H48: =SUM(B48:G48) -> -1316
A49: Comprehensive Income affecting equity | B49: =SUM(B47:B48) -> 1375 | C49: =SUM(C47:C48) -> 1173 | D49: =SUM(D47:D48) -> 283 | E49: =SUM(E47:E48) -> 1861 | F49: =SUM(F47:F48) -> -11157 | G49: =SUM(G47:G48) -> 11513 | H49: =SUM(B49:G49) -> 5048
A50: Dividends | B50: -1972 | C50: -1979 | D50: -1973 | E50: -1959 | F50: -3048 | G50: -2988 | H50: =SUM(B50:G50) -> -13919
A51: Other activity (squeeze) | B51: =+B52-SUM(B49:B50) -> -21 | C51: =+C52-SUM(C49:C50) -> 11 | D51: =+D52-SUM(D49:D50) -> 184 | E51: =+E52-SUM(E49:E50) -> 72 | F51: =+F52-SUM(F49:F50) -> -90 | G51: =+G52-SUM(G49:G50) -> 85 | H51: =SUM(B51:G51) -> 241
A52: Change in equity | B52: =+B54-B53 -> -618 | C52: =+C54-C53 -> -795 | D52: =+D54-D53 -> -1506 | E52: =+E54-E53 -> -26 | F52: =+F54-F53 -> -14295 | G52: =+G54-G53 -> 8610 | H52: =SUM(B52:G52) -> -8630
A53: Beginning Equity | B53: =+C54 -> 49448 | C53: =+D54 -> 50243 | D53: =+E54 -> 51749 | E53: =+F54 -> 51775 | F53: =+G54 -> 66070 | G53: 57460 | H53: =+G53 -> 57460
A54: Ending Equity | B54: =+B34 -> 48830 | C54: =+C34 -> 49448 | D54: =+D34 -> 50243 | E54: =+E34 -> 51749 | F54: =+F34 -> 51775 | G54: =+G34 -> 66070 | H54: =++H52+H53 -> 48830
A56: =+A1 -> Kraft Heinz Company | B56: =+B1 -> Reclassified
A57: Consolidated Income Statements
A58: =+A3 -> in millions except per share data | F58: Late filing | G58: Restated
A59: =+A4 -> Year ended near 12/31: | B59: 2022 | C59: 2021 | D59: 2020 | E59: 2019 | F59: 2018 | G59: 2017 | H59: Aggregate
A60: Net sales | B60: 26485 | C60: 26042 | D60: 26185 | E60: 24977 | F60: 26268 | G60: 26076 | H60: =SUM(B60:G60) -> 156033
A61: Cost of goods sold | B61: 18363 | C61: 17360 | D61: 17008 | E61: 16830 | F61: 17347 | G61: 17043 | H61: =SUM(B61:G61) -> 103951
A62: Gross profit | B62: =+B60-B61 -> 8122 | C62: =+C60-C61 -> 8682 | D62: =+D60-D61 -> 9177 | E62: =+E60-E61 -> 8147 | F62: =+F60-F61 -> 8921 | G62: =+G60-G61 -> 9033 | H62: =SUM(B62:G62) -> 52082
A63: SG&A (see detail) | B63: =+B432 -> 2503 | C63: =+C432 -> 2409 | D63: =+D432 -> 2461 | E63: =+E432 -> 1966 | F63: =+F432 -> 1941 | G63: =+G432 -> 1719 | H63: =SUM(B63:G63) -> 12999
A64: Advertising & Promotion | B64: =+B367 -> 945 | C64: =+C367 -> 1039 | D64: =+D367 -> 1070 | E64: =+E367 -> 1100 | F64: =+F367 -> 1140 | G64: =+G367 -> 1115 | H64: =SUM(B64:G64) -> 6409
A65: Research & Devlopment | B65: =+B368 -> 127 | C65: =+C368 -> 140 | D65: =+D368 -> 119 | E65: =+E368 -> 112 | F65: =+F368 -> 109 | G65: =+G368 -> 93 | H65: =SUM(B65:G65) -> 700
A66: Goodwill impairment | B66: 444 | C66: 318 | D66: 2343 | E66: 1197 | F66: 7008 | G66: 0 | H66: =SUM(B66:G66) -> 11310
A67: Intangible impairment | B67: 469 | C67: 1316 | D67: 1056 | E67: 702 | F67: 8928 | G67: 49 | H67: =SUM(B67:G67) -> 12520
A68: Operating expenses | B68: =SUM(B63:B67) -> 4488 | C68: =SUM(C63:C67) -> 5222 | D68: =SUM(D63:D67) -> 7049 | E68: =SUM(E63:E67) -> 5077 | F68: =SUM(F63:F67) -> 19126 | G68: =SUM(G63:G67) -> 2976 | H68: =SUM(B68:G68) -> 43938
A69: Operating income (loss) | B69: =+B62-B68 -> 3634 | C69: =+C62-C68 -> 3460 | D69: =+D62-D68 -> 2128 | E69: =+E62-E68 -> 3070 | F69: =+F62-F68 -> -10205 | G69: =+G62-G68 -> 6057 | H69: =SUM(B69:G69) -> 8144
A70: Interest expense | B70: 921 | C70: 2047 | D70: 1394 | E70: 1361 | F70: 1284 | G70: 1234 | H70: =SUM(B70:G70) -> 8241
A71: Other expense (income) | B71: -253 | C71: -295 | D71: -296 | E71: -952 | F71: -168 | G71: -627 | H71: =SUM(B71:G71) -> -2591
A72: Pretax Income | B72: =+B69-B70-B71 -> 2966 | C72: =+C69-C70-C71 -> 1708 | D72: =+D69-D70-D71 -> 1030 | E72: =+E69-E70-E71 -> 2661 | F72: =+F69-F70-F71 -> -11321 | G72: =+G69-G70-G71 -> 5450 | H72: =SUM(B72:G72) -> 2494
A73: Tax provision | B73: 598 | C73: 684 | D73: 669 | E73: 728 | F73: -1067 | G73: -5482 | H73: =SUM(B73:G73) -> -3870
A74: Net Income (loss) | B74: =+B72-B73 -> 2368 | C74: =+C72-C73 -> 1024 | D74: =+D72-D73 -> 361 | E74: =+E72-E73 -> 1933 | F74: =+F72-F73 -> -10254 | G74: =+G72-G73 -> 10932 | H74: =SUM(B74:G74) -> 6364
A75: Noncontrolling interest | B75: 5 | C75: 12 | D75: 5 | E75: -2 | F75: -62 | G75: -9 | H75: =SUM(B75:G75) -> -51
A76: Net income (Loss)-Kraft Heinz | B76: =+B74-B75 -> 2363 | C76: =+C74-C75 -> 1012 | D76: =+D74-D75 -> 356 | E76: =+E74-E75 -> 1935 | F76: =+F74-F75 -> -10192 | G76: =+G74-G75 -> 10941 | H76: =SUM(B76:G76) -> 6415
B77: =+B76-'As Reported'!B70 -> 0 | C77: =+C76-'As Reported'!C70 -> 0 | D77: =+D76-'As Reported'!D70 -> 0 | E77: =+E76-'As Reported'!E70 -> 0 | F77: =+F76-'As Reported'!F70 -> 0 | G77: =+G76-'As Reported'!G70 -> 0
A78: Diluted W. Ave shares outstanding (notes) | B78: 1235 | C78: 1236 | D78: 1228 | E78: 1224 | F78: 1219 | G78: 1228
A79: Diluted EPS | B79: =+B76/B78 -> 1.9133603 | C79: =+C76/C78 -> 0.81877023 | D79: =+D76/D78 -> 0.28990228 | E79: =+E76/E78 -> 1.5808824 | F79: =+F76/F78 -> -8.3609516 | G79: =+G76/G78 -> 8.9096091
A80: Dividends per share (Equity Stmt)) | B80: 1.6 | C80: 1.6 | D80: 1.6 | E80: 1.6 | F80: 2.5 | G80: 2.45
A82: Effective Tax Rate | B82: =+B73/B72 -> 0.20161834 | C82: =+C73/C72 -> 0.40046838 | D82: =+D73/D72 -> 0.64951456 | E82: =+E73/E72 -> 0.27358136 | F82: =+F73/F72 -> 0.094249625 | G82: =+G73/G72 -> -1.0058716 | H82: =SUM(B82:G82) -> 0.61356071
A84: Non-GAAP Measurements:
A85: Net Income | B85: =+B76 -> 2363 | C85: =+C76 -> 1012 | D85: =+D76 -> 356 | E85: =+E76 -> 1935 | F85: =+F76 -> -10192 | G85: =+G76 -> 10941
A86: Add back Income Taxes | B86: =+B73 -> 598 | C86: =+C73 -> 684 | D86: =+D73 -> 669 | E86: =+E73 -> 728 | F86: =+F73 -> -1067 | G86: =+G73 -> -5482
A87: Add back Interest Expense | B87: =+B70 -> 921 | C87: =+C70 -> 2047 | D87: =+D70 -> 1394 | E87: =+E70 -> 1361 | F87: =+F70 -> 1284 | G87: =+G70 -> 1234
A88: EBIT | B88: =SUM(B85:B87) -> 3882 | C88: =SUM(C85:C87) -> 3743 | D88: =SUM(D85:D87) -> 2419 | E88: =SUM(E85:E87) -> 4024 | F88: =SUM(F85:F87) -> -9975 | G88: =SUM(G85:G87) -> 6693
A89: Depreciation and amortization | B89: =+B152 -> 933 | C89: =+C152 -> 910 | D89: =+D152 -> 969 | E89: =+E152 -> 994 | F89: =+F152 -> 983 | G89: =+G152 -> 1031
A90: EBITDA | B90: =+B89+B88 -> 4815 | C90: =+C89+C88 -> 4653 | D90: =+D89+D88 -> 3388 | E90: =+E89+E88 -> 5018 | F90: =+F89+F88 -> -8992 | G90: =+G89+G88 -> 7724
A92: Operating Income | B92: =+B69 -> 3634 | C92: =+C69 -> 3460 | D92: =+D69 -> 2128 | E92: =+E69 -> 3070 | F92: =+F69 -> -10205 | G92: =+G69 -> 6057
A93: Other Income | B93: =-B71 -> 253 | C93: =-C71 -> 295 | D93: =-D71 -> 296 | E93: =-E71 -> 952 | F93: =-F71 -> 168 | G93: =-G71 -> 627
A94: Noncontrolling interest | B94: =-B75 -> -5 | C94: =-C75 -> -12 | D94: =-D75 -> -5 | E94: =-E75 -> 2 | F94: =-F75 -> 62 | G94: =-G75 -> 9
A95: EBIT | B95: =+SUM(B92:B94) -> 3882 | C95: =+SUM(C92:C94) -> 3743 | D95: =+SUM(D92:D94) -> 2419 | E95: =+SUM(E92:E94) -> 4024 | F95: =+SUM(F92:F94) -> -9975 | G95: =+SUM(G92:G94) -> 6693
A97: =A1 -> Kraft Heinz Company
A98: Reconciliation of Net Income As Reported to Recurring NICO
A99: =A3 -> in millions except per share data
A100: =A4 -> Year ended near 12/31: | B100: 2022 | C100: 2021 | D100: 2020 | E100: 2019 | F100: 2018 | G100: 2017
A101: Net Income - As Reported | B101: 2363 | C101: 1012 | D101: 356 | E101: 1935 | F101: -10192 | G101: 10941
A102: Pretax Adjustments:
A103: Goodwill Impairment (loss) [SG&A] | B103: 444 | C103: 318 | D103: 2300 | E103: 1200 | F103: 7008 | G103: 0
A104: Intangible Asset Impairment (loss) [SG&A] | B104: 469 | C104: 1316 | D104: 1100 | E104: 702 | F104: 8928 | G104: 49
A105: PPE Impairment [COGS] | B105: 86 | C105: 0 | D105: 14 | E105: 0 | F105: 0 | G105: 0
A106: 53rd Week Corrections:
...

Sheet NICO+Recommendation
B1: Kraft Heinz Company | C1: RECURRING | K1: =+C1 -> RECURRING | S1: =+C1 -> RECURRING
B2: Consolidated Balance Sheets | K2: Common Size on Total Assets | S2: Horizontal(Growth) Analysis
B3: in millions except per share data | G3: Late filing | H3: Restated | P3: Restated | S3: 5 Year | T3: Annual | U3: 2021 to | V3: 2020 to | W3: 2019 to | X3: 2018 to | Y3: 2017 to
B4: Fiscal year ended 12/31: | C4: 2022 | D4: 2021 | E4: 2020 | F4: 2019 | G4: 2018 | H4: 2017 | K4: 2022 | L4: 2021 | M4: 2020 | N4: 2019 | O4: 2018 | P4: 2017 | S4: CAGR | T4: Average | U4: 2022 | V4: 2021 | W4: 2020 | X4: 2019 | Y4: 2018
B5: Assets:
B6: Cash and equivalents | C6: 1040 | D6: 3445 | E6: 3417 | F6: 2279 | G6: 1130 | H6: 1629 | K6: =+C6/C$21 -> 0.011490062 | L6: =+D6/D$21 -> 0.036886738 | M6: =+E6/E$21 -> 0.034228188 | N6: =+F6/F$21 -> 0.022464268 | O6: =+G6/G$21 -> 0.01092199 | P6: =+H6/H$21 -> 0.0135646 | S6: =RATE(5,0,-H6,C6) -> -0.085839502 | T6: =AVERAGE(U6:Y6) -> 0.10398284 | U6: =(+C6-D6)/D6 -> -0.69811321 | V6: =(+D6-E6)/E6 -> 0.0081943225 | W6: =(+E6-F6)/F6 -> 0.49934182 | X6: =(+F6-G6)/G6 -> 1.0168142 | Y6: =(+G6-H6)/H6 -> -0.3063229
B7: Marketable Securities | C7: 0 | D7: 0 | E7: 0 | F7: 0 | G7: 0 | H7: 0
B8: Trade receivables | C8: 2120 | D8: 1957 | E8: 2063 | F8: 1973 | G8: 2129 | H8: 921 | K8: =+C8/C$21 -> 0.02342205 | L8: =+D8/D$21 -> 0.020954237 | M8: =+E8/E$21 -> 0.020665131 | N8: =+F8/F$21 -> 0.019448004 | O8: =+G8/G$21 -> 0.020577802 | P8: =+H8/H$21 -> 0.0076691203 | S8: =RATE(5,0,-H8,C8) -> 0.18144973 | T8: =AVERAGE(U8:Y8) -> 0.26317381 | U8: =(+C8-D8)/D8 -> 0.083290751 | V8: =(+D8-E8)/E8 -> -0.051381483 | W8: =(+E8-F8)/F8 -> 0.045615813 | X8: =(+F8-G8)/G8 -> -0.073273837 | Y8: =(+G8-H8)/H8 -> 1.3116178
B9: Inventories | C9: 3651 | D9: 2729 | E9: 2554 | F9: 2721 | G9: 2667 | H9: 2760 | K9: =+C9/C$21 -> 0.040336747 | L9: =+D9/D$21 -> 0.029220293 | M9: =+E9/E$21 -> 0.025583492 | N9: =+F9/F$21 -> 0.026821094 | O9: =+G9/G$21 -> 0.025777829 | P9: =+H9/H$21 -> 0.02298238 | S9: =RATE(5,0,-H9,C9) -> 0.057549125 | T9: =AVERAGE(U9:Y9) -> 0.066309997 | U9: =(+C9-D9)/D9 -> 0.33785269 | V9: =(+D9-E9)/E9 -> 0.068519969 | W9: =(+E9-F9)/F9 -> -0.061374495 | X9: =(+F9-G9)/G9 -> 0.020247469 | Y9: =(+G9-H9)/H9 -> -0.033695652
B10: Other current assets | C10: =+C415 -> 1086 | D10: =+D415 -> 863 | E10: =+E415 -> 2788 | F10: =+F415 -> 1124 | G10: =+G415 -> 3149 | H10: =+H415 -> 1891 | K10: =+C10/C$21 -> 0.011998276 | L10: =+D10/D$21 -> 0.0092404223 | M10: =+E10/E$21 -> 0.027927477 | N10: =+F10/F$21 -> 0.011079349 | O10: =+G10/G$21 -> 0.03043659 | P10: =+H10/H$21 -> 0.015746261 | S10: =RATE(5,0,-H10,C10) -> -0.10499047 | T10: =AVERAGE(U10:Y10) -> 0.21411281 | U10: =(+C10-D10)/D10 -> 0.25840093 | V10: =(+D10-E10)/E10 -> -0.69045911 | W10: =(+E10-F10)/F10 -> 1.480427 | X10: =(+F10-G10)/G10 -> -0.64306129 | Y10: =(+G10-H10)/H10 -> 0.66525648
B11: Total current assets | C11: =SUM(C6:C10) -> 7897 | D11: =SUM(D6:D10) -> 8994 | E11: =SUM(E6:E10) -> 10822 | F11: =SUM(F6:F10) -> 8097 | G11: =SUM(G6:G10) -> 9075 | H11: =SUM(H6:H10) -> 7201 | K11: =+C11/C$21 -> 0.087247136 | L11: =+D11/D$21 -> 0.09630169 | M11: =+E11/E$21 -> 0.10840429 | N11: =+F11/F$21 -> 0.079812716 | O11: =+G11/G$21 -> 0.087714211 | P11: =+H11/H$21 -> 0.059962362 | S11: =RATE(5,0,-H11,C11) -> 0.018623908 | T11: =AVERAGE(U11:Y11) -> 0.039626412 | U11: =(+C11-D11)/D11 -> -0.1219702 | V11: =(+D11-E11)/E11 -> -0.16891517 | W11: =(+E11-F11)/F11 -> 0.3365444 | X11: =(+F11-G11)/G11 -> -0.1077686 | Y11: =(+G11-H11)/H11 -> 0.26024163
B12: Land | C12: =+C393 -> 200 | D12: =+D393 -> 207 | E12: =+E393 -> 219 | F12: =+F393 -> 210 | G12: =+G393 -> 218 | H12: =+H393 -> 250 | K12: =+C12/C$21 -> 0.0022096273 | L12: =+D12/D$21 -> 0.0022164165 | M12: =+E12/E$21 -> 0.0021937293 | N12: =+F12/F$21 -> 0.0020699852 | O12: =+G12/G$21 -> 0.0021070742 | P12: =+H12/H$21 -> 0.0020817373 | S12: =RATE(5,0,-H12,C12) -> -0.0436475 | T12: =AVERAGE(U12:Y12) -> -0.04209021 | U12: =(+C12-D12)/D12 -> -0.033816425 | V12: =(+D12-E12)/E12 -> -0.054794521 | W12: =(+E12-F12)/F12 -> 0.042857143 | X12: =(+F12-G12)/G12 -> -0.036697248 | Y12: =(+G12-H12)/H12 -> -0.128
B13: Construction in progress | C13: =+C394 -> 1161 | D13: =+D394 -> 1002 | E13: =+E394 -> 792 | F13: =+F394 -> 1033 | G13: =+G394 -> 1165 | H13: =+H394 -> 1345 | K13: =+C13/C$21 -> 0.012826887 | L13: =+D13/D$21 -> 0.010728741 | M13: =+E13/E$21 -> 0.0079334869 | N13: =+F13/F$21 -> 0.010182356 | O13: =+G13/G$21 -> 0.011260282 | P13: =+H13/H$21 -> 0.011199747 | S13: =RATE(5,0,-H13,C13) -> -0.028993835 | T13: =AVERAGE(U13:Y13) -> -0.011320126 | U13: =(+C13-D13)/D13 -> 0.15868263 | V13: =(+D13-E13)/E13 -> 0.26515152 | W13: =(+E13-F13)/F13 -> -0.23330106 | X13: =(+F13-G13)/G13 -> -0.11330472 | Y13: =(+G13-H13)/H13 -> -0.133829
B14: Depreciable assets | C14: =+C395 -> 51681 | D14: =+D395 -> 52107 | E14: =+E395 -> 52795 | F14: =+F395 -> 53693 | G14: =+G395 -> 52976 | H14: =+H395 -> 66564 | K14: =+C14/C$21 -> 0.57097875 | L14: =+D14/D$21 -> 0.55792663 | M14: =+E14/E$21 -> 0.52884904 | N14: =+F14/F$21 -> 0.52925579 | O14: =+G14/G$21 -> 0.51203835 | P14: =+H14/H$21 -> 0.55427506 | S14: =RATE(5,0,-H14,C14) -> -0.049355151 | T14: =AVERAGE(U14:Y14) -> -0.045706334 | U14: =(+C14-D14)/D14 -> -0.0081754851 | V14: =(+D14-E14)/E14 -> -0.013031537 | W14: =(+E14-F14)/F14 -> -0.016724713 | X14: =(+F14-G14)/G14 -> 0.013534431 | Y14: =(+G14-H14)/H14 -> -0.20413437
B15: PP&E - at cost | C15: =+C396 -> 53042 | D15: =+D396 -> 53316 | E15: =+E396 -> 53806 | F15: =+F396 -> 54936 | G15: =+G396 -> 54359 | H15: =+H396 -> 68159 | K15: =+C15/C$21 -> 0.58601527 | L15: =+D15/D$21 -> 0.57087179 | M15: =+E15/E$21 -> 0.53897626 | N15: =+F15/F$21 -> 0.54150813 | O15: =+G15/G$21 -> 0.52540571 | P15: =+H15/H$21 -> 0.56755654 | S15: =RATE(5,0,-H15,C15) -> -0.048914991 | T15: =AVERAGE(U15:Y15) -> -0.045333699 | U15: =(+C15-D15)/D15 -> -0.0051391702 | V15: =(+D15-E15)/E15 -> -0.0091067911 | W15: =(+E15-F15)/F15 -> -0.02056939 | X15: =(+F15-G15)/G15 -> 0.010614618 | Y15: =(+G15-H15)/H15 -> -0.20246776
B16: Accumulated depreciation | C16: =+C397 -> -4212 | D16: =+D397 -> -3868 | E16: =+E397 -> -3563 | F16: =+F397 -> -3187 | G16: =+G397 -> -2584 | H16: =+H397 -> -2089 | K16: =+C16/C$21 -> -0.046534752 | L16: =+D16/D$21 -> -0.041415937 | M16: =+E16/E$21 -> -0.035690674 | N16: =+F16/F$21 -> -0.03141449 | O16: =+G16/G$21 -> -0.024975595 | P16: =+H16/H$21 -> -0.017394997 | S16: =RATE(5,0,-H16,C16) -> 0.15056189 | T16: =AVERAGE(U16:Y16) -> 0.15256616 | U16: =(+C16-D16)/D16 -> 0.08893485 | V16: =(+D16-E16)/E16 -> 0.085602021 | W16: =(+E16-F16)/F16 -> 0.11797929 | X16: =(+F16-G16)/G16 -> 0.23335913 | Y16: =(+G16-H16)/H16 -> 0.23695548
B17: Property, plant & equipment - net | C17: 6740 | D17: 6806 | E17: 6876 | F17: 7055 | G17: 7078 | H17: 7061 | K17: =+C17/C$21 -> 0.074464442 | L17: =+D17/D$21 -> 0.07287406 | M17: =+E17/E$21 -> 0.068877091 | N17: =+F17/F$21 -> 0.069541646 | O17: =+G17/G$21 -> 0.068412252 | P17: =+H17/H$21 -> 0.058796589 | S17: =RATE(5,0,-H17,C17) -> -0.0092621911 | T17: =AVERAGE(U17:Y17) -> -0.0092183309 | U17: =(+C17-D17)/D17 -> -0.0096973259 | V17: =(+D17-E17)/E17 -> -0.010180337 | W17: =(+E17-F17)/F17 -> -0.025372077 | X17: =(+F17-G17)/G17 -> -0.0032495055 | Y17: =(+G17-H17)/H17 -> 0.002407591
B18: Right of Use assets | C18: =+C402 -> 668 | D18: =+D402 -> 569 | E18: =+E402 -> 562 | F18: =+F402 -> 542 | G18: =+G402 -> 0 | H18: =+H402 -> 0
B19: Goodwill and Intangibles (see detail) | C19: =+C419 -> 73482 | D19: =+D419 -> 74838 | E19: =+E419 -> 79756 | F19: =+F419 -> 84198 | G19: =+G419 -> 85971 | H19: =+H419 -> 104257 | K19: =+C19/C$21 -> 0.81183918 | L19: =+D19/D$21 -> 0.80131486 | M19: =+E19/E$21 -> 0.79891816 | N19: =+F19/F$21 -> 0.82994579 | O19: =+G19/G$21 -> 0.83095079 | P19: =+H19/H$21 -> 0.86814276 | S19: =RATE(5,0,-H19,C19) -> -0.067572339 | T19: =AVERAGE(U19:Y19) -> -0.065711108 | U19: =(+C19-D19)/D19 -> -0.018119137 | V19: =(+D19-E19)/E19 -> -0.061663072 | W19: =(+E19-F19)/F19 -> -0.052756598 | X19: =(+F19-G19)/G19 -> -0.020623233 | Y19: =(+G19-H19)/H19 -> -0.1753935
B20: Other assets | C20: =+C423 -> 1726 | D20: =+D423 -> 2187 | E20: =+E423 -> 1814 | F20: =+F423 -> 1558 | G20: =+G423 -> 1337 | H20: =+H423 -> 1573 | K20: =+C20/C$21 -> 0.019069084 | L20: =+D20/D$21 -> 0.023416922 | M20: =+E20/E$21 -> 0.018170891 | N20: =+F20/F$21 -> 0.015357319 | O20: =+G20/G$21 -> 0.012922744 | P20: =+H20/H$21 -> 0.013098291 | S20: =RATE(5,0,-H20,C20) -> 0.018737783 | T20: =AVERAGE(U20:Y20) -> 0.034881754 | U20: =(+C20-D20)/D20 -> -0.21079104 | V20: =(+D20-E20)/E20 -> 0.20562293 | W20: =(+E20-F20)/F20 -> 0.16431322 | X20: =(+F20-G20)/G20 -> 0.16529544 | Y20: =(+G20-H20)/H20 -> -0.15003179
B21: Total Assets | C21: =+C11+SUM(C17:C20) -> 90513 | D21: =+D11+SUM(D17:D20) -> 93394 | E21: =+E11+SUM(E17:E20) -> 99830 | F21: =+F11+SUM(F17:F20) -> 101450 | G21: =+G11+SUM(G17:G20) -> 103461 | H21: =+H11+SUM(H17:H20) -> 120092 | K21: =+C21/C$21 -> 1 | L21: =+D21/D$21 -> 1 | M21: =+E21/E$21 -> 1 | N21: =+F21/F$21 -> 1 | O21: =+G21/G$21 -> 1 | P21: =+H21/H$21 -> 1 | S21: =RATE(5,0,-H21,C21) -> -0.054983533 | T21: =AVERAGE(U21:Y21) -> -0.053841726 | U21: =(+C21-D21)/D21 -> -0.030847806 | V21: =(+D21-E21)/E21 -> -0.064469598 | W21: =(+E21-F21)/F21 -> -0.015968457 | X21: =(+F21-G21)/G21 -> -0.019437276 | Y21: =(+G21-H21)/H21 -> -0.13848549
B22: Liabilities and Equity
B23: Current Debt (see detail) | C23: =+C427 -> 837 | D23: =+D427 -> 754 | E23: =+E427 -> 236 | F23: =+F427 -> 1028 | G23: =+G427 -> 398 | H23: =+H427 -> 3195 | K23: =+C23/C$21 -> 0.0092472904 | L23: =+D23/D$21 -> 0.0080733238 | M23: =+E23/E$21 -> 0.0023640188 | N23: =+F23/F$21 -> 0.01013307 | O23: =+G23/G$21 -> 0.0038468602 | P23: =+H23/H$21 -> 0.026604603 | S23: =RATE(5,0,-H23,C23) -> -0.23501852 | T23: =AVERAGE(U23:Y23) -> 0.44841021 | U23: =(+C23-D23)/D23 -> 0.11007958 | V23: =(+D23-E23)/E23 -> 2.1949153 | W23: =(+E23-F23)/F23 -> -0.77042802 | X23: =(+F23-G23)/G23 -> 1.5829146 | Y23: =(+G23-H23)/H23 -> -0.87543036
B24: Trade payables | C24: 4848 | D24: 4753 | E24: 4304 | F24: 4003 | G24: 4153 | H24: 4362 | K24: =+C24/C$21 -> 0.053561367 | L24: =+D24/D$21 -> 0.05089192 | M24: =+E24/E$21 -> 0.043113293 | N24: =+F24/F$21 -> 0.039457861 | O24: =+G24/G$21 -> 0.040140729 | P24: =+H24/H$21 -> 0.036322153 | S24: =RATE(5,0,-H24,C24) -> 0.021351874 | T24: =AVERAGE(U24:Y24) -> 0.023094055 | U24: =(+C24-D24)/D24 -> 0.019987376 | V24: =(+D24-E24)/E24 -> 0.10432156 | W24: =(+E24-F24)/F24 -> 0.075193605 | X24: =(+F24-G24)/G24 -> -0.036118469 | Y24: =(+G24-H24)/H24 -> -0.047913801
B25: Deferred revenue | C25: 0 | D25: 0 | E25: 0 | F25: 0 | G25: 0 | H25: 0 | K25: =+C25/C$21 -> 0 | L25: =+D25/D$21 -> 0 | M25: =+E25/E$21 -> 0 | N25: =+F25/F$21 -> 0 | O25: =+G25/G$21 -> 0 | P25: =+H25/H$21 -> 0
B26: Current portion of operating lease liabilities | C26: =+C403 -> 125 | D26: =+D403 -> 133 | E26: =+E403 -> 135 | F26: =+F403 -> 147 | G26: =+G403 -> 0 | H26: =+H403 -> 0
B27: Other current liabilities (see detail) | C27: =+C435 -> 3218 | D27: =+D435 -> 3424 | E27: =+E435 -> 3386 | F27: =+F435 -> 2697 | G27: =+G435 -> 2952 | H27: =+H435 -> 2597 | K27: =+C27/C$21 -> 0.035552904 | L27: =+D27/D$21 -> 0.036661884 | M27: =+E27/E$21 -> 0.03391766 | N27: =+F27/F$21 -> 0.026584524 | O27: =+G27/G$21 -> 0.028532491 | P27: =+H27/H$21 -> 0.021625087 | S27: =RATE(5,0,-H27,C27) -> 0.04381328 | T27: =AVERAGE(U27:Y27) -> 0.051368449 | U27: =(+C27-D27)/D27 -> -0.060163551 | V27: =(+D27-E27)/E27 -> 0.011222682 | W27: =(+E27-F27)/F27 -> 0.25546904 | X27: =(+F27-G27)/G27 -> -0.086382114 | Y27: =(+G27-H27)/H27 -> 0.13669619
B28: Total current liabilities | C28: =SUM(C23:C27) -> 9028 | D28: =SUM(D23:D27) -> 9064 | E28: =SUM(E23:E27) -> 8061 | F28: =SUM(F23:F27) -> 7875 | G28: =SUM(G23:G27) -> 7503 | H28: =SUM(H23:H27) -> 10154 | K28: =+C28/C$21 -> 0.099742578 | L28: =+D28/D$21 -> 0.097051202 | M28: =+E28/E$21 -> 0.08074727 | N28: =+F28/F$21 -> 0.077624446 | O28: =+G28/G$21 -> 0.07252008 | P28: =+H28/H$21 -> 0.084551844 | S28: =RATE(5,0,-H28,C28) -> -0.023233226 | T28: =AVERAGE(U28:Y28) -> -0.013485134 | U28: =(+C28-D28)/D28 -> -0.0039717564 | V28: =(+D28-E28)/E28 -> 0.12442625 | W28: =(+E28-F28)/F28 -> 0.023619048 | X28: =(+F28-G28)/G28 -> 0.049580168 | Y28: =(+G28-H28)/H28 -> -0.26107938
B29: Long-term debt | C29: 19233 | D29: 21061 | E29: 28070 | F29: 28216 | G29: 30770 | H29: 28308 | K29: =+C29/C$21 -> 0.21248881 | L29: =+D29/D$21 -> 0.22550699 | M29: =+E29/E$21 -> 0.281178 | N29: =+F29/F$21 -> 0.27812716 | O29: =+G29/G$21 -> 0.29740675 | P29: =+H29/H$21 -> 0.23571928 | S29: =RATE(5,0,-H29,C29) -> -0.074391 | T29: =AVERAGE(U29:Y29) -> -0.06753962 | U29: =(+C29-D29)/D29 -> -0.086795499 | V29: =(+D29-E29)/E29 -> -0.24969719 | W29: =(+E29-F29)/F29 -> -0.0051743692 | X29: =(+F29-G29)/G29 -> -0.083002925 | Y29: =(+G29-H29)/H29 -> 0.086971881
B30: LT operating lease liabilities | C30: =+C404 -> 585 | D30: =+D404 -> 484 | E30: =+E404 -> 475 | F30: =+F404 -> 454 | G30: =+G404 -> 0 | H30: =+H404 -> 0
B31: Other non-current liabilities (see detail) | C31: =+C442 -> 12797 | D31: =+D442 -> 13333 | E31: =+E442 -> 12981 | F31: =+F442 -> 13156 | G31: =+G442 -> 13410 | H31: =+H442 -> 15554 | K31: =+C31/C$21 -> 0.14138301 | L31: =+D31/D$21 -> 0.14276078 | M31: =+E31/E$21 -> 0.13003105 | N31: =+F31/F$21 -> 0.12967965 | O31: =+G31/G$21 -> 0.12961406 | P31: =+H31/H$21 -> 0.12951737 | S31: =RATE(5,0,-H31,C31) -> -0.038269886 | T31: =AVERAGE(U31:Y31) -> -0.036633962 | U31: =(+C31-D31)/D31 -> -0.040201005 | V31: =(+D31-E31)/E31 -> 0.027116555 | W31: =(+E31-F31)/F31 -> -0.013301915 | X31: =(+F31-G31)/G31 -> -0.018941089 | Y31: =(+G31-H31)/H31 -> -0.13784236
B32: Total liabilities | C32: =SUM(C28:C31) -> 41643 | D32: =SUM(D28:D31) -> 43942 | E32: =SUM(E28:E31) -> 49587 | F32: =SUM(F28:F31) -> 49701 | G32: =SUM(G28:G31) -> 51683 | H32: =SUM(H28:H31) -> 54016 | K32: =+C32/C$21 -> 0.46007756 | L32: =+D32/D$21 -> 0.47050132 | M32: =+E32/E$21 -> 0.49671441 | N32: =+F32/F$21 -> 0.48990636 | O32: =+G32/G$21 -> 0.49954089 | P32: =+H32/H$21 -> 0.4497885 | S32: =RATE(5,0,-H32,C32) -> -0.050699045 | T32: =AVERAGE(U32:Y32) -> -0.049998615 | U32: =(+C32-D32)/D32 -> -0.052318966 | V32: =(+D32-E32)/E32 -> -0.11384032 | W32: =(+E32-F32)/F32 -> -0.0022937164 | X32: =(+F32-G32)/G32 -> -0.038349167 | Y32: =(+G32-H32)/H32 -> -0.043190906
B33: Redeemable Non-controlling interest | C33: 40 | D33: 4 | E33: 0 | F33: 0 | G33: 3 | H33: 6 | K33: =+C33/C$21 -> 0.00044192547 | L33: =+D33/D$21 -> 4.2829304e-05 | M33: =+E33/E$21 -> 0 | N33: =+F33/F$21 -> 0 | O33: =+G33/G$21 -> 2.8996433e-05 | P33: =+H33/H$21 -> 4.9961696e-05 | S33: =RATE(5,0,-H33,C33) -> 0.46144255 | T33: =AVERAGE(U33:Y33) -> 2.5 | U33: =(+C33-D33)/D33 -> 9 | X33: =(+F33-G33)/G33 -> -1 | Y33: =(+G33-H33)/H33 -> -0.5
B34: Total Equity | C34: =+C450 -> 48830 | D34: =+D450 -> 49448 | E34: =+E450 -> 50243 | F34: =+F450 -> 51749 | G34: =+G450 -> 51775 | H34: =+H450 -> 66070 | K34: =+C34/C$21 -> 0.53948052 | L34: =+D34/D$21 -> 0.52945585 | M34: =+E34/E$21 -> 0.50328559 | N34: =+F34/F$21 -> 0.51009364 | O34: =+G34/G$21 -> 0.50043011 | P34: =+H34/H$21 -> 0.55016154 | S34: =RATE(5,0,-H34,C34) -> -0.05868174 | T34: =AVERAGE(U34:Y34) -> -0.054857339 | U34: =(+C34-D34)/D34 -> -0.012497978 | V34: =(+D34-E34)/E34 -> -0.0158231 | W34: =(+E34-F34)/F34 -> -0.029102012 | X34: =(+F34-G34)/G34 -> -0.00050217286 | Y34: =(+G34-H34)/H34 -> -0.21636143
B35: Total Liabilities and Equity | C35: =+C34+C33+C32 -> 90513 | D35: =+D34+D33+D32 -> 93394 | E35: =+E34+E33+E32 -> 99830 | F35: =+F34+F33+F32 -> 101450 | G35: =+G34+G33+G32 -> 103461 | H35: =+H34+H33+H32 -> 120092 | K35: =+C35/C$21 -> 1 | L35: =+D35/D$21 -> 1 | M35: =+E35/E$21 -> 1 | N35: =+F35/F$21 -> 1 | O35: =+G35/G$21 -> 1 | P35: =+H35/H$21 -> 1 | S35: =RATE(5,0,-H35,C35) -> -0.054983533 | T35: =AVERAGE(U35:Y35) -> -0.053841726 | U35: =(+C35-D35)/D35 -> -0.030847806 | V35: =(+D35-E35)/E35 -> -0.064469598 | W35: =(+E35-F35)/F35 -> -0.015968457 | X35: =(+F35-G35)/G35 -> -0.019437276 | Y35: =(+G35-H35)/H35 -> -0.13848549
C36: =+C35-C21 -> 0 | D36: =+D35-D21 -> 0 | E36: =+E35-E21 -> 0 | F36: =+F35-F21 -> 0 | G36: =+G35-G21 -> 0 | H36: =+H35-H21 -> 0
B37: Shares issued | C37: 1243 | D37: 1235 | E37: 1228 | F37: 1224 | G37: 1224 | H37: 1221
B38: Treasury Shares | C38: -18 | D38: -11 | E38: -5 | F38: -3 | G38: -4 | H38: -2
B39: Shares Outstanding | C39: =+C37+C38 -> 1225 | D39: =+D37+D38 -> 1224 | E39: =+E37+E38 -> 1223 | F39: =+F37+F38 -> 1221 | G39: =+G37+G38 -> 1220 | H39: =+H37+H38 -> 1219
B40: Stock price at next 2/28 (60 days after FYE) | C40: 38.13 | D40: 39.22 | E40: 36.38 | F40: 24.77 | G40: 33.19 | H40: 67.14
B41: Market Value of Equity | C41: =+C39*C40 -> 46709.25 | D41: =+D39*D40 -> 48005.28 | E41: =+E39*E40 -> 44492.74 | F41: =+F39*F40 -> 30244.17 | G41: =+G39*G40 -> 40491.8 | H41: =+H39*H40 -> 81843.66
B43: =+B1 -> Kraft Heinz Company | C43: RECURRING
B44: Summary Changes in Equity
B45: =+B3 -> in millions except per share data | G45: Late filing | H45: Restated
B46: =+B4 -> Fiscal year ended 12/31: | C46: 2022 | D46: 2021 | E46: 2020 | F46: 2019 | G46: 2018 | H46: 2017 | I46: Aggregate
B47: Net Income - As Reported | C47: =+'As Reported'!B68 -> 2368 | D47: =+'As Reported'!C68 -> 1024 | E47: =+'As Reported'!D68 -> 361 | F47: =+'As Reported'!E68 -> 1933 | G47: =+'As Reported'!F68 -> -10254 | H47: =+'As Reported'!G68 -> 10932 | I47: =SUM(C47:H47) -> 6364
B48: Other comprehensive income | C48: -993 | D48: 149 | E48: -78 | F48: -72 | G48: -903 | H48: 581 | I48: =SUM(C48:H48) -> -1316
B49: Comprehensive Income affecting equity | C49: =SUM(C47:C48) -> 1375 | D49: =SUM(D47:D48) -> 1173 | E49: =SUM(E47:E48) -> 283 | F49: =SUM(F47:F48) -> 1861 | G49: =SUM(G47:G48) -> -11157 | H49: =SUM(H47:H48) -> 11513 | I49: =SUM(C49:H49) -> 5048
B50: Dividends | C50: -1972 | D50: -1979 | E50: -1973 | F50: -1959 | G50: -3048 | H50: -2988 | I50: =SUM(C50:H50) -> -13919
B51: Other activity (squeeze) | C51: =+C52-SUM(C49:C50) -> -21 | D51: =+D52-SUM(D49:D50) -> 11 | E51: =+E52-SUM(E49:E50) -> 184 | F51: =+F52-SUM(F49:F50) -> 72 | G51: =+G52-SUM(G49:G50) -> -90 | H51: =+H52-SUM(H49:H50) -> 85 | I51: =SUM(C51:H51) -> 241
B52: Change in equity | C52: =+C54-C53 -> -618 | D52: =+D54-D53 -> -795 | E52: =+E54-E53 -> -1506 | F52: =+F54-F53 -> -26 | G52: =+G54-G53 -> -14295 | H52: =+H54-H53 -> 8610 | I52: =SUM(C52:H52) -> -8630
B53: Beginning Equity | C53: =+D54 -> 49448 | D53: =+E54 -> 50243 | E53: =+F54 -> 51749 | F53: =+G54 -> 51775 | G53: =+H54 -> 66070 | H53: 57460 | I53: =+H53 -> 57460
B54: Ending Equity | C54: =+C34 -> 48830 | D54: =+D34 -> 49448 | E54: =+E34 -> 50243 | F54: =+F34 -> 51749 | G54: =+G34 -> 51775 | H54: =+H34 -> 66070 | I54: =++I52+I53 -> 48830
B56: =+B1 -> Kraft Heinz Company | C56: =+C1 -> RECURRING | K56: =+C56 -> RECURRING | S56: =+C56 -> RECURRING
B57: Consolidated Income Statements | K57: Common Size on Net Sales | S57: Horizontal(Growth) Analysis
B58: =+B3 -> in millions except per share data | G58: Late filing | H58: Restated | P58: Restated | S58: 5 Year | T58: Annual | U58: 2021 to | V58: 2020 to | W58: 2019 to | X58: 2018 to | Y58: 2017 to
B59: =+B4 -> Fiscal year ended 12/31: | C59: 2022 | D59: 2021 | E59: 2020 | F59: 2019 | G59: 2018 | H59: 2017 | I59: Aggregate | K59: 2022 | L59: 2021 | M59: 2020 | N59: 2019 | O59: 2018 | P59: 2017 | Q59: Aggregate | S59: CAGR | T59: Average | U59: 2022 | V59: 2021 | W59: 2020 | X59: 2019 | Y59: 2018
B60: Net sales | C60: =Profitability!B60 -> 26485 | D60: =Profitability!C60 -> 26042 | E60: =Profitability!D60 -> 26185 | F60: =Profitability!E60 -> 24977 | G60: =Profitability!F60 -> 26268 | H60: =Profitability!G60 -> 26076 | I60: =SUM(C60:H60) -> 156033 | K60: =+C60/C$60 -> 1 | L60: =+D60/D$60 -> 1 | M60: =+E60/E$60 -> 1 | N60: =+F60/F$60 -> 1 | O60: =+G60/G$60 -> 1 | P60: =+H60/H$60 -> 1 | Q60: =+I60/I$60 -> 1 | S60: =RATE(5,0,-H60,C60) -> 0.0031174861 | T60: =AVERAGE(U60:Y60) -> 0.0036260354 | U60: =(+C60-D60)/D60 -> 0.017010982 | V60: =(+D60-E60)/E60 -> -0.0054611419 | W60: =(+E60-F60)/F60 -> 0.048364495 | X60: =(+F60-G60)/G60 -> -0.049147251 | Y60: =(+G60-H60)/H60 -> 0.0073630925
B61: Cost of goods sold | C61: =Profitability!B61 -> 18363 | D61: =Profitability!C61 -> 17360 | E61: =Profitability!D61 -> 17008 | F61: =Profitability!E61 -> 16830 | G61: =Profitability!F61 -> 17347 | H61: =Profitability!G61 -> 17043 | I61: =SUM(C61:H61) -> 103951 | K61: =+C61/C$60 -> 0.69333585 | L61: =+D61/D$60 -> 0.66661547 | M61: =+E61/E$60 -> 0.64953217 | N61: =+F61/F$60 -> 0.67381991 | O61: =+G61/G$60 -> 0.66038526 | P61: =+H61/H$60 -> 0.65358951 | Q61: =+I61/I$60 -> 0.66621163 | S61: =RATE(5,0,-H61,C61) -> 0.015031495 | T61: =AVERAGE(U61:Y61) -> 0.015416561 | U61: =(+C61-D61)/D61 -> 0.057776498 | V61: =(+D61-E61)/E61 -> 0.020696143 | W61: =(+E61-F61)/F61 -> 0.010576352 | X61: =(+F61-G61)/G61 -> -0.029803424 | Y61: =(+G61-H61)/H61 -> 0.017837235
B62: Gross profit | C62: =C60-C61 -> 8122 | D62: =D60-D61 -> 8682 | E62: =E60-E61 -> 9177 | F62: =F60-F61 -> 8147 | G62: =G60-G61 -> 8921 | H62: =H60-H61 -> 9033 | I62: =SUM(C62:H62) -> 52082 | K62: =+C62/C$60 -> 0.30666415 | L62: =+D62/D$60 -> 0.33338453 | M62: =+E62/E$60 -> 0.35046783 | N62: =+F62/F$60 -> 0.32618009 | O62: =+G62/G$60 -> 0.33961474 | P62: =+H62/H$60 -> 0.34641049 | Q62: =+I62/I$60 -> 0.33378837 | S62: =RATE(5,0,-H62,C62) -> -0.021037187 | T62: =AVERAGE(U62:Y62) -> -0.018234823 | U62: =(+C62-D62)/D62 -> -0.064501267 | V62: =(+D62-E62)/E62 -> -0.053939196 | W62: =(+E62-F62)/F62 -> 0.12642691 | X62: =(+F62-G62)/G62 -> -0.086761574 | Y62: =(+G62-H62)/H62 -> -0.012398982
B63: SG&A (see detail) | C63: =Profitability!B63 -> 2503 | D63: =Profitability!C63 -> 2409 | E63: =Profitability!D63 -> 2461 | F63: =Profitability!E63 -> 1966 | G63: =Profitability!F63 -> 1941 | H63: =Profitability!G63 -> 1719 | I63: =SUM(C63:H63) -> 12999 | K63: =+C63/C$60 -> 0.094506324 | L63: =+D63/D$60 -> 0.092504416 | M63: =+E63/E$60 -> 0.093985106 | N63: =+F63/F$60 -> 0.078712415 | O63: =+G63/G$60 -> 0.073892188 | P63: =+H63/H$60 -> 0.065922688 | Q63: =+I63/I$60 -> 0.0833093 | S63: =RATE(5,0,-H63,C63) -> 0.07804526 | T63: =AVERAGE(U63:Y63) -> 0.082339159 | U63: =(+C63-D63)/D63 -> 0.03902034 | V63: =(+D63-E63)/E63 -> -0.021129622 | W63: =(+E63-F63)/F63 -> 0.25178026 | X63: =(+F63-G63)/G63 -> 0.012879959 | Y63: =(+G63-H63)/H63 -> 0.12914485
B64: Advertising & Promotion | C64: =Profitability!B64 -> 945 | D64: =Profitability!C64 -> 1039 | E64: =Profitability!D64 -> 1070 | F64: =Profitability!E64 -> 1100 | G64: =Profitability!F64 -> 1140 | H64: =Profitability!G64 -> 1115 | I64: =SUM(C64:H64) -> 6409 | K64: =+C64/C$60 -> 0.035680574 | L64: =+D64/D$60 -> 0.039897089 | M64: =+E64/E$60 -> 0.04086309 | N64: =+F64/F$60 -> 0.044040517 | O64: =+G64/G$60 -> 0.043398812 | P64: =+H64/H$60 -> 0.042759626 | Q64: =+I64/I$60 -> 0.041074644
B65: Research & Devlopment | C65: =Profitability!B65 -> 127 | D65: =Profitability!C65 -> 140 | E65: =Profitability!D65 -> 119 | F65: =Profitability!E65 -> 112 | G65: =Profitability!F65 -> 109 | H65: =Profitability!G65 -> 93 | I65: =SUM(C65:H65) -> 700 | K65: =+C65/C$60 -> 0.0047951671 | L65: =+D65/D$60 -> 0.0053759312 | M65: =+E65/E$60 -> 0.0045445866 | N65: =+F65/F$60 -> 0.0044841254 | O65: =+G65/G$60 -> 0.0041495356 | P65: =+H65/H$60 -> 0.0035664979 | Q65: =+I65/I$60 -> 0.0044862305
B66: Goodwill Imparment | C66: =Profitability!B66 -> 444 | D66: =Profitability!C66 -> 318 | E66: =Profitability!D66 -> 2343 | F66: =Profitability!E66 -> 1197 | G66: =Profitability!F66 -> 7008 | H66: =Profitability!G66 -> 0 | I66: =SUM(C66:H66) -> 11310
B67: Intangible Impartment | C67: =Profitability!B67 -> 469 | D67: =Profitability!C67 -> 1316 | E67: =Profitability!D67 -> 1056 | F67: =Profitability!E67 -> 702 | G67: =Profitability!F67 -> 8928 | H67: =Profitability!G67 -> 49 | I67: =SUM(C67:H67) -> 12520
B68: Operating expenses | C68: =SUM(C63:C67) -> 4488 | D68: =SUM(D63:D67) -> 5222 | E68: =SUM(E63:E67) -> 7049 | F68: =SUM(F63:F67) -> 5077 | G68: =SUM(G63:G67) -> 19126 | H68: =SUM(H63:H67) -> 2976 | I68: =SUM(C68:H68) -> 43938 | K68: =+C68/C$60 -> 0.16945441 | L68: =+D68/D$60 -> 0.20052223 | M68: =+E68/E$60 -> 0.26919992 | N68: =+F68/F$60 -> 0.20326701 | O68: =+G68/G$60 -> 0.72811025 | P68: =+H68/H$60 -> 0.11412793 | Q68: =+I68/I$60 -> 0.28159428 | S68: =RATE(5,0,-H68,C68) -> 0.08563537 | T68: =AVERAGE(U68:Y68) -> 0.93617419 | U68: =(+C68-D68)/D68 -> -0.14055917 | V68: =(+D68-E68)/E68 -> -0.2591857 | W68: =(+E68-F68)/F68 -> 0.38841836 | X68: =(+F68-G68)/G68 -> -0.73454983 | Y68: =(+G68-H68)/H68 -> 5.4267473
B69: Operating income (loss) | C69: =C62-C68 -> 3634 | D69: =D62-D68 -> 3460 | E69: =E62-E68 -> 2128 | F69: =F62-F68 -> 3070 | G69: =G62-G68 -> -10205 | H69: =H62-H68 -> 6057 | I69: =SUM(C69:H69) -> 8144 | K69: =+C69/C$60 -> 0.13720974 | L69: =+D69/D$60 -> 0.1328623 | M69: =+E69/E$60 -> 0.081267901 | N69: =+F69/F$60 -> 0.12291308 | O69: =+G69/G$60 -> -0.38849551 | P69: =+H69/H$60 -> 0.23228256 | Q69: =+I69/I$60 -> 0.052194087 | S69: =RATE(5,0,-H69,C69) -> -0.097129486 | T69: =AVERAGE(U69:Y69) -> -0.72325438 | U69: =(+C69-D69)/D69 -> 0.050289017 | V69: =(+D69-E69)/E69 -> 0.62593985 | W69: =(+E69-F69)/F69 -> -0.30684039 | X69: =(+F69-G69)/G69 -> -1.3008329 | Y69: =(+G69-H69)/H69 -> -2.6848275
B70: Interest expense | C70: =Profitability!B70 -> 921 | D70: =Profitability!C70 -> 2047 | E70: =Profitability!D70 -> 1394 | F70: =Profitability!E70 -> 1361 | G70: =Profitability!F70 -> 1284 | H70: =Profitability!G70 -> 1234 | I70: =SUM(C70:H70) -> 8241 | K70: =+C70/C$60 -> 0.034774401 | L70: =+D70/D$60 -> 0.078603794 | M70: =+E70/E$60 -> 0.053236586 | N70: =+F70/F$60 -> 0.054490131 | O70: =+G70/G$60 -> 0.048880767 | P70: =+H70/H$60 -> 0.047323209 | Q70: =+I70/I$60 -> 0.052815751 | S70: =RATE(5,0,-H70,C70) -> -0.056832355 | T70: =AVERAGE(U70:Y70) -> 0.008619448 | U70: =(+C70-D70)/D70 -> -0.55007328 | V70: =(+D70-E70)/E70 -> 0.46843615 | W70: =(+E70-F70)/F70 -> 0.024246877 | X70: =(+F70-G70)/G70 -> 0.059968847 | Y70: =(+G70-H70)/H70 -> 0.040518639
B71: Other expense (income) | C71: =Profitability!B71 -> -253 | D71: =Profitability!C71 -> -295 | E71: =Profitability!D71 -> -296 | F71: =Profitability!E71 -> -952 | G71: =Profitability!F71 -> -168 | H71: =Profitability!G71 -> -627 | I71: =SUM(C71:H71) -> -2591 | K71: =+C71/C$60 -> -0.0095525769 | L71: =+D71/D$60 -> -0.011327855 | M71: =+E71/E$60 -> -0.011304182 | N71: =+F71/F$60 -> -0.038115066 | O71: =+G71/G$60 -> -0.0063956144 | P71: =+H71/H$60 -> -0.024045099 | Q71: =+I71/I$60 -> -0.016605462 | S71: =RATE(5,0,-H71,C71) -> -0.16599127 | T71: =AVERAGE(U71:Y71) -> 0.61995647 | U71: =(+C71-D71)/D71 -> -0.14237288 | V71: =(+D71-E71)/E71 -> -0.0033783784 | W71: =(+E71-F71)/F71 -> -0.68907563 | X71: =(+F71-G71)/G71 -> 4.6666667 | Y71: =(+G71-H71)/H71 -> -0.73205742
B72: Pretax Income | C72: =C69-C70-C71 -> 2966 | D72: =D69-D70-D71 -> 1708 | E72: =E69-E70-E71 -> 1030 | F72: =F69-F70-F71 -> 2661 | G72: =G69-G70-G71 -> -11321 | H72: =H69-H70-H71 -> 5450 | I72: =SUM(C72:H72) -> 2494 | K72: =+C72/C$60 -> 0.11198792 | L72: =+D72/D$60 -> 0.06558636 | M72: =+E72/E$60 -> 0.039335497 | N72: =+F72/F$60 -> 0.10653801 | O72: =+G72/G$60 -> -0.43098066 | P72: =+H72/H$60 -> 0.20900445 | Q72: =+I72/I$60 -> 0.015983798 | S72: =RATE(5,0,-H72,C72) -> -0.11456858 | T72: =AVERAGE(U72:Y72) -> -0.70608774 | U72: =(+C72-D72)/D72 -> 0.73653396 | V72: =(+D72-E72)/E72 -> 0.65825243 | W72: =(+E72-F72)/F72 -> -0.61292747 | X72: =(+F72-G72)/G72 -> -1.2350499 | Y72: =(+G72-H72)/H72 -> -3.0772477
B73: Tax provision | C73: =Profitability!B73 -> 598 | D73: =Profitability!C73 -> 684 | E73: =Profitability!D73 -> 669 | F73: =Profitability!E73 -> 728 | G73: =Profitability!F73 -> -1067 | H73: =Profitability!G73 -> -5482 | I73: =SUM(C73:H73) -> -3870 | K73: =+C73/C$60 -> 0.022578818 | L73: =+D73/D$60 -> 0.026265264 | M73: =+E73/E$60 -> 0.025548978 | N73: =+F73/F$60 -> 0.029146815 | O73: =+G73/G$60 -> -0.040619765 | P73: =+H73/H$60 -> -0.21023163 | Q73: =+I73/I$60 -> -0.024802446 | S73: =RATE(5,0,H73,C73) -> -0.35797427 | T73: =AVERAGE(U73:Y73) -> -0.53440064 | U73: =(+C73-D73)/D73 -> -0.12573099 | V73: =(+D73-E73)/E73 -> 0.022421525 | W73: =(+E73-F73)/F73 -> -0.081043956 | X73: =(+F73-G73)/G73 -> -1.6822868 | Y73: =(+G73-H73)/H73 -> -0.80536301
B74: Net Income (loss) | C74: =C72-C73 -> 2368 | D74: =D72-D73 -> 1024 | E74: =E72-E73 -> 361 | F74: =F72-F73 -> 1933 | G74: =G72-G73 -> -10254 | H74: =H72-H73 -> 10932 | I74: =SUM(C74:H74) -> 6364 | K74: =+C74/C$60 -> 0.089409099 | L74: =+D74/D$60 -> 0.039321097 | M74: =+E74/E$60 -> 0.013786519 | N74: =+F74/F$60 -> 0.0773912 | O74: =+G74/G$60 -> -0.3903609 | P74: =+H74/H$60 -> 0.41923608 | Q74: =+I74/I$60 -> 0.040786244 | S74: =RATE(5,0,-H74,C74) -> -0.26356162 | T74: =AVERAGE(U74:Y74) -> -0.15813412 | U74: =(+C74-D74)/D74 -> 1.3125 | V74: =(+D74-E74)/E74 -> 1.8365651 | W74: =(+E74-F74)/F74 -> -0.81324366 | X74: =(+F74-G74)/G74 -> -1.1885118 | Y74: =(+G74-H74)/H74 -> -1.9379802
B75: Noncontrolling interest | C75: =Profitability!B75 -> 5 | D75: =Profitability!C75 -> 12 | E75: =Profitability!D75 -> 5 | F75: =Profitability!E75 -> -2 | G75: =Profitability!F75 -> -62 | H75: =Profitability!G75 -> -9 | I75: =SUM(C75:H75) -> -51 | K75: =+C75/C$60 -> 0.00018878611 | L75: =+D75/D$60 -> 0.0004607941 | M75: =+E75/E$60 -> 0.00019094902 | N75: =+F75/F$60 -> -8.0073668e-05 | O75: =+G75/G$60 -> -0.0023602863 | P75: =+H75/H$60 -> -0.00034514496 | Q75: =+I75/I$60 -> -0.00032685393 | S75: =RATE(5,0,H75,C75) -> -0.11091046 | T75: =AVERAGE(U75:Y75) -> 0.44756272 | U75: =(+C75-D75)/D75 -> -0.58333333 | V75: =(+D75-E75)/E75 -> 1.4 | W75: =(+E75-F75)/F75 -> -3.5 | X75: =(+F75-G75)/G75 -> -0.96774194 | Y75: =(+G75-H75)/H75 -> 5.8888889
B76: Non-recurring Net income (Loss)-Kraft Heinz | C76: =C74-C75 -> 2363 | D76: =D74-D75 -> 1012 | E76: =E74-E75 -> 356 | F76: =F74-F75 -> 1935 | G76: =G74-G75 -> -10192 | H76: =H74-H75 -> 10941 | I76: =SUM(C76:H76) -> 6415 | K76: =+C76/C$60 -> 0.089220313 | L76: =+D76/D$60 -> 0.038860303 | M76: =+E76/E$60 -> 0.01359557 | N76: =+F76/F$60 -> 0.077471274 | O76: =+G76/G$60 -> -0.38800061 | P76: =+H76/H$60 -> 0.41958122 | Q76: =+I76/I$60 -> 0.041113098 | S76: =RATE(5,0,-H76,C76) -> -0.26399402 | T76: =AVERAGE(U76:Y76) -> -0.1519481 | U76: =(+C76-D76)/D76 -> 1.3349802 | V76: =(+D76-E76)/E76 -> 1.8426966 | W76: =(+E76-F76)/F76 -> -0.81602067 | X76: =(+F76-G76)/G76 -> -1.1898548 | Y76: =(+G76-H76)/H76 -> -1.9315419
B77: Non-recurring activites (see detail) | C77: =C488 -> 467.31604 | D77: =D488 -> 892.25 | E77: =E488 -> 3066.5 | F77: =F488 -> 1244 | G77: =G488 -> 14119.5 | H77: =H488 -> -6247.5 | I77: =SUM(C77:H77) -> 13542.066 | S77: =RATE(5,0,-I77,+C77) -> -0.48998241 | T77: =AVERAGE(U77:Y77) -> -0.77843395 | U77: =(C77-D77)/D77 -> -0.47624989 | V77: =(D77-E77)/E77 -> -0.7090331 | W77: =(E77-F77)/F77 -> 1.4650322 | X77: =(F77-G77)/G77 -> -0.9118949 | Y77: =(G77-H77)/H77 -> -3.260024
B78: Recurring Net income | C78: =C76+C77 -> 2830.316 | D78: =D76+D77 -> 1904.25 | E78: =E76+E77 -> 3422.5 | F78: =F76+F77 -> 3179 | G78: =G76+G77 -> 3927.5 | H78: =H76+H77 -> 4693.5 | I78: =SUM(C78:H78) -> 19957.066 | S78: =RATE(5,0,-I78,+C78) -> -0.32337561 | T78: =AVERAGE(U78:Y78) -> -0.046896075 | U78: =(C78-D78)/D78 -> 0.48631537 | V78: =(D78-E78)/E78 -> -0.44360847 | W78: =(E78-F78)/F78 -> 0.076596414 | X78: =(F78-G78)/G78 -> -0.19057925 | Y78: =(G78-H78)/H78 -> -0.16320443
B80: Diluted W. Ave shares outstanding (notes) | C80: 1235 | D80: 1236 | E80: 1228 | F80: 1224 | G80: 1219 | H80: 1228
B81: Diluted EPS | C81: =+C78/C80 -> 2.2917539 | D81: =+D78/D80 -> 1.5406553 | E81: =+E78/E80 -> 2.7870521 | F81: =+F78/F80 -> 2.5972222 | G81: =+G78/G80 -> 3.2219032 | H81: =+H78/H80 -> 3.8220684
B82: Dividends per share (Equity Stmt)) | C82: 1.6 | D82: 1.6 | E82: 1.6 | F82: 1.6 | G82: 2.5 | H82: 2.45 | S82: =RATE(5,0,-H80,C80) -> 0.0011374745 | T82: =AVERAGE(U82:Y82) -> 0.0011492606 | U82: =(+C80-D80)/D80 -> -0.00080906149 | V82: =(+D80-E80)/E80 -> 0.006514658 | W82: =(+E80-F80)/F80 -> 0.0032679739 | X82: =(+F80-G80)/G80 -> 0.0041017227 | Y82: =(+G80-H80)/H80 -> -0.0073289902
S83: =RATE(5,0,-H81,C81) -> -0.097236682 | T83: =AVERAGE(U83:Y83) -> -0.047502652 | U83: =(+C81-D81)/D81 -> 0.48751886 | V83: =(+D81-E81)/E81 -> -0.44720971 | W83: =(+E81-F81)/F81 -> 0.073089585 | X83: =(+F81-G81)/G81 -> -0.19388571 | Y83: =(+G81-H81)/H81 -> -0.15702629
B84: Effective Tax Rate | C84: =+C73/C72 -> 0.20161834 | D84: =+D73/D72 -> 0.40046838 | E84: =+E73/E72 -> 0.64951456 | F84: =+F73/F72 -> 0.27358136 | G84: =+G73/G72 -> 0.094249625 | H84: =+H73/H72 -> -1.0058716 | S84: =RATE(5,0,-H82,C82) -> -0.0816869 | T84: =AVERAGE(U84:Y84) -> -0.067918367 | U84: =(+C82-D82)/D82 -> 0 | V84: =(+D82-E82)/E82 -> 0 | W84: =(+E82-F82)/F82 -> 0 | X84: =(+F82-G82)/G82 -> -0.36 | Y84: =(+G82-H82)/H82 -> 0.020408163
B86: Non-GAAP Measurements:
B87: Net Income | C87: =C78 -> 2830.316 | D87: =D78 -> 1904.25 | E87: =E78 -> 3422.5 | F87: =F78 -> 3179 | G87: =G78 -> 3927.5 | H87: =H78 -> 4693.5
B88: Add back Income Taxes | C88: =C73 -> 598 | D88: =D73 -> 684 | E88: =E73 -> 669 | F88: =F73 -> 728 | G88: =G73 -> -1067 | H88: =H73 -> -5482
B89: Add back Interest Expense | C89: =C70 -> 921 | D89: =D70 -> 2047 | E89: =E70 -> 1394 | F89: =F70 -> 1361 | G89: =G70 -> 1284 | H89: =H70 -> 1234
B90: EBIT | C90: =SUM(C87:C89) -> 4349.316 | D90: =SUM(D87:D89) -> 4635.25 | E90: =SUM(E87:E89) -> 5485.5 | F90: =SUM(F87:F89) -> 5268 | G90: =SUM(G87:G89) -> 4144.5 | H90: =SUM(H87:H89) -> 445.5
B91: Depreciation and amortization | C91: =C104 -> 933 | D91: =D104 -> 910 | E91: =E104 -> 969 | F91: =F104 -> 994 | G91: =G104 -> 983 | H91: =H104 -> 1031
B92: EBITDA | C92: =C90+C91 -> 5282.316 | D92: =D90+D91 -> 5545.25 | E92: =E90+E91 -> 6454.5 | F92: =F90+F91 -> 6262 | G92: =G90+G91 -> 5127.5 | H92: =H90+H91 -> 1476.5
B94: Operating Income | C94: =C69 -> 3634 | D94: =D69 -> 3460 | E94: =E69 -> 2128 | F94: =F69 -> 3070 | G94: =G69 -> -10205 | H94: =H69 -> 6057
B95: Other Income | C95: =-C71 -> 253 | D95: =-D71 -> 295 | E95: =-E71 -> 296 | F95: =-F71 -> 952 | G95: =-G71 -> 168 | H95: =-H71 -> 627
B96: Noncontrolling interest | C96: -5 | D96: -12 | E96: -5 | F96: 2 | G96: 62 | H96: 9
B97: EBIT | C97: =SUM(C94:C96) -> 3882 | D97: =SUM(D94:D96) -> 3743 | E97: =SUM(E94:E96) -> 2419 | F97: =SUM(F94:F96) -> 4024 | G97: =SUM(G94:G96) -> -9975 | H97: =SUM(H94:H96) -> 6693
B99: =+B1 -> Kraft Heinz Company | C99: =+C1 -> RECURRING | K99: =+C99 -> RECURRING | S99: =+C99 -> RECURRING
B100: Consolidated Cash Flows | K100: Common Size on Operating Cash Flows | S100: Horizontal(Growth) Analysis
B101: =+B3 -> in millions except per share data | G101: Late filing | H101: Restated | P101: Restated | S101: 5 Year | T101: Annual | U101: 2021 to | V101: 2020 to | W101: 2019 to | X101: 2018 to | Y101: 2017 to
B102: =+B4 -> Fiscal year ended 12/31: | C102: 2022 | D102: 2021 | E102: 2020 | F102: 2019 | G102: 2018 | H102: 2017 | I102: Aggregate | K102: 2022 | L102: 2021 | M102: 2020 | N102: 2019 | O102: 2018 | P102: 2017 | S102: CAGR | T102: Average | U102: 2022 | V102: 2021 | W102: 2020 | X102: 2019 | Y102: 2018
B103: Net income (loss) - as reported | C103: =+'As Reported'!B68 -> 2368 | D103: =+'As Reported'!C68 -> 1024 | E103: =+'As Reported'!D68 -> 361 | F103: =+'As Reported'!E68 -> 1933 | G103: =+'As Reported'!F68 -> -10254 | H103: =+'As Reported'!G68 -> 10932 | I103: =SUM(C103:H103) -> 6364 | S103: =RATE(5,0,-H103,C103) -> -0.26356162 | T103: =AVERAGE(U103:Y103) -> -0.15813412 | U103: =(+C103-D103)/D103 -> 1.3125 | V103: =(+D103-E103)/E103 -> 1.8365651 | W103: =(+E103-F103)/F103 -> -0.81324366 | X103: =(+F103-G103)/G103 -> -1.1885118 | Y103: =(+G103-H103)/H103 -> -1.9379802
B104: Depreciation & amortization | C104: 933 | D104: 910 | E104: 969 | F104: 994 | G104: 983 | H104: 1031 | I104: =SUM(C104:H104) -> 5820 | S104: =RATE(5,0,-H104,C104) -> -0.019777661 | T104: =AVERAGE(U104:Y104) -> -0.01922604 | U104: =(+C104-D104)/D104 -> 0.025274725 | V104: =(+D104-E104)/E104 -> -0.060887513 | W104: =(+E104-F104)/F104 -> -0.025150905 | X104: =(+F104-G104)/G104 -> 0.011190234 | Y104: =(+G104-H104)/H104 -> -0.046556741
